{"time_zh":383.27501605,"results_zh":{"att_strats":[[{"v":18,"t":0.0},{"v":9,"t":12.0},{"v":8,"t":15.0},{"v":82,"t":23.75}]],"att_probs":[1.0],"def_strats":[[[{"v":17,"t_a":0.0,"t_b":24.0}],[{"v":19,"t_a":0.0,"t_b":24.0}]]],"def_probs":[1.0],"obj_core_over_time":[-0.0],"obj_DO_over_time":[-0.0],"obj_AO_over_time":[null],"coreLP_time_over_time":[0.003245007],"DO_time_over_time":[383.256509663],"AO_time_over_time":[null],"convergence_flag":false},"time_ne":0.035824359,"results_ne":{"att_strats":[[{"v":18,"t":0.0},{"v":9,"t":12.0},{"v":8,"t":15.0},{"v":82,"t":23.75}]],"att_probs":[1.0],"def_strats":[[[{"v":17,"t_a":0.0,"t_b":24.0}],[{"v":19,"t_a":0.0,"t_b":24.0}]]],"def_probs":[1.0],"obj_core_over_time":[-0.0],"obj_DO_over_time":[-0.0],"obj_AO_over_time":[null],"coreLP_time_over_time":[0.003509034],"DO_time_over_time":[0.017788036],"AO_time_over_time":[null],"convergence_flag":true}}