{"time_zh":300.876041779,"results_zh":{"att_strats":[[{"v":1,"t":0.0},{"v":2,"t":6.0},{"v":3,"t":22.0},{"v":17,"t":42.75}],[{"v":1,"t":0.0},{"v":5,"t":6.0},{"v":9,"t":42.75},{"v":17,"t":42.75}]],"att_probs":[-0.0,1.0],"def_strats":[[[{"v":7,"t_a":0.0,"t_b":0.0},{"v":3,"t_a":8.0,"t_b":43.0}]],[[{"v":7,"t_a":0.0,"t_b":0.0}]],[[{"v":7,"t_a":0.0,"t_b":0.0}]],[[{"v":7,"t_a":0.0,"t_b":0.0}]],[[{"v":7,"t_a":0.0,"t_b":0.0}]],[[{"v":7,"t_a":0.0,"t_b":0.0}]],[[{"v":7,"t_a":0.0,"t_b":0.0}]],[[{"v":7,"t_a":0.0,"t_b":0.0}]],[[{"v":7,"t_a":0.0,"t_b":0.0}]],[[{"v":7,"t_a":0.0,"t_b":0.0}]],[[{"v":7,"t_a":0.0,"t_b":0.0}]],[[{"v":7,"t_a":0.0,"t_b":0.0}]],[[{"v":7,"t_a":0.0,"t_b":0.0}]],[[{"v":7,"t_a":0.0,"t_b":0.0}]],[[{"v":7,"t_a":0.0,"t_b":0.0}]],[[{"v":7,"t_a":0.0,"t_b":0.0}]],[[{"v":7,"t_a":0.0,"t_b":0.0}]],[[{"v":7,"t_a":0.0,"t_b":0.0}]],[[{"v":7,"t_a":0.0,"t_b":0.0}]],[[{"v":7,"t_a":0.0,"t_b":0.0}]],[[{"v":7,"t_a":0.0,"t_b":0.0}]],[[{"v":7,"t_a":0.0,"t_b":0.0}]],[[{"v":7,"t_a":0.0,"t_b":0.0}]],[[{"v":7,"t_a":0.0,"t_b":0.0}]],[[{"v":7,"t_a":0.0,"t_b":0.0}]],[[{"v":7,"t_a":0.0,"t_b":0.0}]],[[{"v":7,"t_a":0.0,"t_b":0.0}]],[[{"v":7,"t_a":0.0,"t_b":0.0}]],[[{"v":7,"t_a":0.0,"t_b":0.0}]],[[{"v":7,"t_a":0.0,"t_b":0.0}]],[[{"v":7,"t_a":0.0,"t_b":0.0}]],[[{"v":7,"t_a":0.0,"t_b":0.0}]],[[{"v":7,"t_a":0.0,"t_b":0.0}]],[[{"v":7,"t_a":0.0,"t_b":0.0}]],[[{"v":7,"t_a":0.0,"t_b":0.0}]],[[{"v":7,"t_a":0.0,"t_b":0.0}]],[[{"v":7,"t_a":0.0,"t_b":0.0}]],[[{"v":7,"t_a":0.0,"t_b":0.0}]],[[{"v":7,"t_a":0.0,"t_b":0.0}]],[[{"v":7,"t_a":0.0,"t_b":0.0}]],[[{"v":7,"t_a":0.0,"t_b":0.0}]],[[{"v":7,"t_a":0.0,"t_b":0.0}]],[[{"v":7,"t_a":0.0,"t_b":0.0}]],[[{"v":7,"t_a":0.0,"t_b":0.0}]],[[{"v":7,"t_a":0.0,"t_b":0.0}]],[[{"v":7,"t_a":0.0,"t_b":0.0}]],[[{"v":7,"t_a":0.0,"t_b":0.0}]],[[{"v":7,"t_a":0.0,"t_b":0.0}]],[[{"v":7,"t_a":0.0,"t_b":0.0}]],[[{"v":7,"t_a":0.0,"t_b":0.0}]],[[{"v":7,"t_a":0.0,"t_b":0.0}]],[[{"v":7,"t_a":0.0,"t_b":0.0}]],[[{"v":7,"t_a":0.0,"t_b":0.0}]],[[{"v":7,"t_a":0.0,"t_b":0.0}]],[[{"v":7,"t_a":0.0,"t_b":0.0}]],[[{"v":7,"t_a":0.0,"t_b":0.0}]],[[{"v":7,"t_a":0.0,"t_b":0.0}]],[[{"v":7,"t_a":0.0,"t_b":0.0}]],[[{"v":7,"t_a":0.0,"t_b":0.0}]],[[{"v":7,"t_a":0.0,"t_b":0.0}]],[[{"v":7,"t_a":0.0,"t_b":0.0}]],[[{"v":7,"t_a":0.0,"t_b":0.0}]],[[{"v":7,"t_a":0.0,"t_b":0.0}]],[[{"v":7,"t_a":0.0,"t_b":0.0}]],[[{"v":7,"t_a":0.0,"t_b":0.0}]],[[{"v":7,"t_a":0.0,"t_b":0.0}]],[[{"v":7,"t_a":0.0,"t_b":0.0}]],[[{"v":7,"t_a":0.0,"t_b":0.0}]],[[{"v":7,"t_a":0.0,"t_b":0.0}]],[[{"v":7,"t_a":0.0,"t_b":0.0}]],[[{"v":7,"t_a":0.0,"t_b":0.0}]],[[{"v":7,"t_a":0.0,"t_b":0.0}]],[[{"v":7,"t_a":0.0,"t_b":0.0}]],[[{"v":7,"t_a":0.0,"t_b":0.0}]],[[{"v":7,"t_a":0.0,"t_b":0.0}]],[[{"v":7,"t_a":0.0,"t_b":0.0}]],[[{"v":7,"t_a":0.0,"t_b":0.0}]],[[{"v":7,"t_a":0.0,"t_b":0.0}]],[[{"v":7,"t_a":0.0,"t_b":0.0}]],[[{"v":7,"t_a":0.0,"t_b":0.0}]],[[{"v":7,"t_a":0.0,"t_b":0.0}]],[[{"v":7,"t_a":0.0,"t_b":0.0}]],[[{"v":7,"t_a":0.0,"t_b":0.0}]],[[{"v":7,"t_a":0.0,"t_b":0.0}]],[[{"v":7,"t_a":0.0,"t_b":0.0}]],[[{"v":7,"t_a":0.0,"t_b":0.0}]],[[{"v":7,"t_a":0.0,"t_b":0.0}]],[[{"v":7,"t_a":0.0,"t_b":0.0}]],[[{"v":7,"t_a":0.0,"t_b":0.0}]],[[{"v":7,"t_a":0.0,"t_b":0.0}]],[[{"v":7,"t_a":0.0,"t_b":0.0}]],[[{"v":7,"t_a":0.0,"t_b":0.0}]],[[{"v":7,"t_a":0.0,"t_b":0.0}]],[[{"v":7,"t_a":0.0,"t_b":0.0}]],[[{"v":7,"t_a":0.0,"t_b":0.0}]],[[{"v":7,"t_a":0.0,"t_b":0.0}]],[[{"v":7,"t_a":0.0,"t_b":0.0}]],[[{"v":7,"t_a":0.0,"t_b":0.0}]],[[{"v":7,"t_a":0.0,"t_b":0.0}]],[[{"v":7,"t_a":0.0,"t_b":0.0}]],[[{"v":7,"t_a":0.0,"t_b":0.0}]],[[{"v":7,"t_a":0.0,"t_b":0.0}]],[[{"v":7,"t_a":0.0,"t_b":0.0}]],[[{"v":7,"t_a":0.0,"t_b":0.0}]],[[{"v":7,"t_a":0.0,"t_b":0.0}]],[[{"v":7,"t_a":0.0,"t_b":0.0}]],[[{"v":7,"t_a":0.0,"t_b":0.0}]],[[{"v":7,"t_a":0.0,"t_b":0.0}]],[[{"v":7,"t_a":0.0,"t_b":0.0}]],[[{"v":7,"t_a":0.0,"t_b":0.0}]],[[{"v":7,"t_a":0.0,"t_b":0.0}]],[[{"v":7,"t_a":0.0,"t_b":0.0}]],[[{"v":7,"t_a":0.0,"t_b":0.0}]],[[{"v":7,"t_a":0.0,"t_b":0.0}]],[[{"v":7,"t_a":0.0,"t_b":0.0}]],[[{"v":7,"t_a":0.0,"t_b":0.0}]],[[{"v":7,"t_a":0.0,"t_b":0.0}]],[[{"v":7,"t_a":0.0,"t_b":0.0}]],[[{"v":7,"t_a":0.0,"t_b":0.0}]],[[{"v":7,"t_a":0.0,"t_b":0.0}]],[[{"v":7,"t_a":0.0,"t_b":0.0}]],[[{"v":7,"t_a":0.0,"t_b":0.0}]],[[{"v":7,"t_a":0.0,"t_b":0.0}]],[[{"v":7,"t_a":0.0,"t_b":0.0}]],[[{"v":7,"t_a":0.0,"t_b":0.0}]],[[{"v":7,"t_a":0.0,"t_b":0.0}]],[[{"v":7,"t_a":0.0,"t_b":0.0}]],[[{"v":7,"t_a":0.0,"t_b":0.0}]],[[{"v":7,"t_a":0.0,"t_b":0.0}]],[[{"v":7,"t_a":0.0,"t_b":0.0}]],[[{"v":7,"t_a":0.0,"t_b":0.0}]],[[{"v":7,"t_a":0.0,"t_b":0.0}]],[[{"v":7,"t_a":0.0,"t_b":0.0}]],[[{"v":7,"t_a":0.0,"t_b":0.0}]],[[{"v":7,"t_a":0.0,"t_b":0.0}]],[[{"v":7,"t_a":0.0,"t_b":0.0}]],[[{"v":7,"t_a":0.0,"t_b":0.0}]],[[{"v":7,"t_a":0.0,"t_b":0.0}]],[[{"v":7,"t_a":0.0,"t_b":0.0}]],[[{"v":7,"t_a":0.0,"t_b":0.0}]],[[{"v":7,"t_a":0.0,"t_b":0.0}]],[[{"v":7,"t_a":0.0,"t_b":0.0}]],[[{"v":7,"t_a":0.0,"t_b":0.0}]],[[{"v":7,"t_a":0.0,"t_b":0.0}]],[[{"v":7,"t_a":0.0,"t_b":0.0}]],[[{"v":7,"t_a":0.0,"t_b":0.0}]],[[{"v":7,"t_a":0.0,"t_b":0.0}]],[[{"v":7,"t_a":0.0,"t_b":0.0}]],[[{"v":7,"t_a":0.0,"t_b":0.0}]],[[{"v":7,"t_a":0.0,"t_b":0.0}]],[[{"v":7,"t_a":0.0,"t_b":0.0}]],[[{"v":7,"t_a":0.0,"t_b":0.0}]],[[{"v":7,"t_a":0.0,"t_b":0.0}]],[[{"v":7,"t_a":0.0,"t_b":0.0}]],[[{"v":7,"t_a":0.0,"t_b":0.0}]],[[{"v":7,"t_a":0.0,"t_b":0.0}]],[[{"v":7,"t_a":0.0,"t_b":0.0}]],[[{"v":7,"t_a":0.0,"t_b":0.0}]],[[{"v":7,"t_a":0.0,"t_b":0.0}]],[[{"v":7,"t_a":0.0,"t_b":0.0}]],[[{"v":7,"t_a":0.0,"t_b":0.0}]],[[{"v":7,"t_a":0.0,"t_b":0.0}]],[[{"v":7,"t_a":0.0,"t_b":0.0}]],[[{"v":7,"t_a":0.0,"t_b":0.0}]],[[{"v":7,"t_a":0.0,"t_b":0.0}]],[[{"v":7,"t_a":0.0,"t_b":0.0}]],[[{"v":7,"t_a":0.0,"t_b":0.0}]],[[{"v":7,"t_a":0.0,"t_b":0.0}]],[[{"v":7,"t_a":0.0,"t_b":0.0}]],[[{"v":7,"t_a":0.0,"t_b":0.0}]],[[{"v":7,"t_a":0.0,"t_b":0.0}]],[[{"v":7,"t_a":0.0,"t_b":0.0}]],[[{"v":7,"t_a":0.0,"t_b":0.0}]],[[{"v":7,"t_a":0.0,"t_b":0.0}]],[[{"v":7,"t_a":0.0,"t_b":0.0}]],[[{"v":7,"t_a":0.0,"t_b":0.0}]],[[{"v":7,"t_a":0.0,"t_b":0.0}]],[[{"v":7,"t_a":0.0,"t_b":0.0}]],[[{"v":7,"t_a":0.0,"t_b":0.0}]],[[{"v":7,"t_a":0.0,"t_b":0.0}]],[[{"v":7,"t_a":0.0,"t_b":0.0}]],[[{"v":7,"t_a":0.0,"t_b":0.0}]],[[{"v":7,"t_a":0.0,"t_b":0.0}]],[[{"v":7,"t_a":0.0,"t_b":0.0}]],[[{"v":7,"t_a":0.0,"t_b":0.0}]],[[{"v":7,"t_a":0.0,"t_b":0.0}]],[[{"v":7,"t_a":0.0,"t_b":0.0}]],[[{"v":7,"t_a":0.0,"t_b":0.0}]],[[{"v":7,"t_a":0.0,"t_b":0.0}]],[[{"v":7,"t_a":0.0,"t_b":0.0}]],[[{"v":7,"t_a":0.0,"t_b":0.0}]],[[{"v":7,"t_a":0.0,"t_b":0.0}]],[[{"v":7,"t_a":0.0,"t_b":0.0}]],[[{"v":7,"t_a":0.0,"t_b":0.0}]],[[{"v":7,"t_a":0.0,"t_b":0.0}]],[[{"v":7,"t_a":0.0,"t_b":0.0}]],[[{"v":7,"t_a":0.0,"t_b":0.0}]],[[{"v":7,"t_a":0.0,"t_b":0.0}]],[[{"v":7,"t_a":0.0,"t_b":0.0}]],[[{"v":7,"t_a":0.0,"t_b":0.0}]],[[{"v":7,"t_a":0.0,"t_b":0.0}]],[[{"v":7,"t_a":0.0,"t_b":0.0}]],[[{"v":7,"t_a":0.0,"t_b":0.0}]],[[{"v":7,"t_a":0.0,"t_b":0.0}]],[[{"v":7,"t_a":0.0,"t_b":0.0}]],[[{"v":7,"t_a":0.0,"t_b":0.0}]],[[{"v":7,"t_a":0.0,"t_b":0.0}]],[[{"v":7,"t_a":0.0,"t_b":0.0}]],[[{"v":7,"t_a":0.0,"t_b":0.0}]],[[{"v":7,"t_a":0.0,"t_b":0.0}]],[[{"v":7,"t_a":0.0,"t_b":0.0}]],[[{"v":7,"t_a":0.0,"t_b":0.0}]],[[{"v":7,"t_a":0.0,"t_b":0.0}]],[[{"v":7,"t_a":0.0,"t_b":0.0}]],[[{"v":7,"t_a":0.0,"t_b":0.0}]],[[{"v":7,"t_a":0.0,"t_b":0.0}]],[[{"v":7,"t_a":0.0,"t_b":0.0}]],[[{"v":7,"t_a":0.0,"t_b":0.0}]],[[{"v":7,"t_a":0.0,"t_b":0.0}]],[[{"v":7,"t_a":0.0,"t_b":0.0}]],[[{"v":7,"t_a":0.0,"t_b":0.0}]],[[{"v":7,"t_a":0.0,"t_b":0.0}]],[[{"v":7,"t_a":0.0,"t_b":0.0}]],[[{"v":7,"t_a":0.0,"t_b":0.0}]],[[{"v":7,"t_a":0.0,"t_b":0.0}]],[[{"v":7,"t_a":0.0,"t_b":0.0}]],[[{"v":7,"t_a":0.0,"t_b":0.0}]],[[{"v":7,"t_a":0.0,"t_b":0.0}]],[[{"v":7,"t_a":0.0,"t_b":0.0}]],[[{"v":7,"t_a":0.0,"t_b":0.0}]],[[{"v":7,"t_a":0.0,"t_b":0.0}]],[[{"v":7,"t_a":0.0,"t_b":0.0}]],[[{"v":7,"t_a":0.0,"t_b":0.0}]],[[{"v":7,"t_a":0.0,"t_b":0.0}]]],"def_probs":[0.0,1.0,0.0,0.0,0.0,0.0,0.0,0.0,0.0,0.0,0.0,0.0,0.0,0.0,0.0,0.0,0.0,0.0,0.0,0.0,0.0,0.0,0.0,0.0,0.0,0.0,0.0,0.0,0.0,0.0,0.0,0.0,0.0,0.0,0.0,0.0,0.0,0.0,0.0,0.0,0.0,0.0,0.0,0.0,0.0,0.0,0.0,0.0,0.0,0.0,0.0,0.0,0.0,0.0,0.0,0.0,0.0,0.0,0.0,0.0,0.0,0.0,0.0,0.0,0.0,0.0,0.0,0.0,0.0,0.0,0.0,0.0,0.0,0.0,0.0,0.0,0.0,0.0,0.0,0.0,0.0,0.0,0.0,0.0,0.0,0.0,0.0,0.0,0.0,0.0,0.0,0.0,0.0,0.0,0.0,0.0,0.0,0.0,0.0,0.0,0.0,0.0,0.0,0.0,0.0,0.0,0.0,0.0,0.0,0.0,0.0,0.0,0.0,0.0,0.0,0.0,0.0,0.0,0.0,0.0,0.0,0.0,0.0,0.0,0.0,0.0,0.0,0.0,0.0,0.0,0.0,0.0,0.0,0.0,0.0,0.0,0.0,0.0,0.0,0.0,0.0,0.0,0.0,0.0,0.0,0.0,0.0,0.0,0.0,0.0,0.0,0.0,0.0,0.0,0.0,0.0,0.0,0.0,0.0,0.0,0.0,0.0,0.0,0.0,0.0,0.0,0.0,0.0,0.0,0.0,0.0,0.0,0.0,0.0,0.0,0.0,0.0,0.0,0.0,0.0,0.0,0.0,0.0,0.0,0.0,0.0,0.0,0.0,0.0,0.0,0.0,0.0,0.0,0.0,0.0,0.0,0.0,0.0,0.0,0.0,0.0,0.0,0.0,0.0,0.0,0.0,0.0,0.0,0.0,0.0,0.0,0.0,0.0,0.0,0.0,0.0,0.0,0.0,0.0,0.0,0.0,0.0,0.0,0.0,0.0,0.0,0.0,0.0,0.0,0.0,0.0,0.0,0.0,0.0],"obj_core_over_time":[1.0,-0.0,-0.0,-0.0,-0.0,-0.0,-0.0,-0.0,-0.0,-0.0,-0.0,-0.0,-0.0,-0.0,-0.0,-0.0,-0.0,-0.0,-0.0,-0.0,-0.0,-0.0,-0.0,-0.0,-0.0,-0.0,-0.0,-0.0,-0.0,-0.0,-0.0,-0.0,-0.0,-0.0,-0.0,-0.0,-0.0,-0.0,-0.0,-0.0,-0.0,-0.0,-0.0,-0.0,-0.0,-0.0,-0.0,-0.0,-0.0,-0.0,-0.0,-0.0,-0.0,-0.0,-0.0,-0.0,-0.0,-0.0,-0.0,-0.0,-0.0,-0.0,-0.0,-0.0,-0.0,-0.0,-0.0,-0.0,-0.0,-0.0,-0.0,-0.0,-0.0,-0.0,-0.0,-0.0,-0.0,-0.0,-0.0,-0.0,-0.0,-0.0,-0.0,-0.0,-0.0,-0.0,-0.0,-0.0,-0.0,-0.0,-0.0,-0.0,-0.0,-0.0,-0.0,-0.0,-0.0,-0.0,-0.0,-0.0,-0.0,-0.0,-0.0,-0.0,-0.0,-0.0,-0.0,-0.0,-0.0,-0.0,-0.0,-0.0,-0.0,-0.0,-0.0,-0.0,-0.0,-0.0,-0.0,-0.0,-0.0,-0.0,-0.0,-0.0,-0.0,-0.0,-0.0,-0.0,-0.0,-0.0,-0.0,-0.0,-0.0,-0.0,-0.0,-0.0,-0.0,-0.0,-0.0,-0.0,-0.0,-0.0,-0.0,-0.0,-0.0,-0.0,-0.0,-0.0,-0.0,-0.0,-0.0,-0.0,-0.0,-0.0,-0.0,-0.0,-0.0,-0.0,-0.0,-0.0,-0.0,-0.0,-0.0,-0.0,-0.0,-0.0,-0.0,-0.0,-0.0,-0.0,-0.0,-0.0,-0.0,-0.0,-0.0,-0.0,-0.0,-0.0,-0.0,-0.0,-0.0,-0.0,-0.0,-0.0,-0.0,-0.0,-0.0,-0.0,-0.0,-0.0,-0.0,-0.0,-0.0,-0.0,-0.0,-0.0,-0.0,-0.0,-0.0,-0.0,-0.0,-0.0,-0.0,-0.0,-0.0,-0.0,-0.0,-0.0,-0.0,-0.0,-0.0,-0.0,-0.0,-0.0,-0.0,-0.0,-0.0,-0.0,-0.0,-0.0,-0.0,-0.0,-0.0,-0.0,-0.0,-0.0,-0.0,-0.0,-0.0,-0.0,-0.0,-0.0,-0.0,-0.0,-0.0],"obj_DO_over_time":[null,1.0,1.0,1.0,1.0,1.0,1.0,1.0,1.0,1.0,1.0,1.0,1.0,1.0,1.0,1.0,1.0,1.0,1.0,1.0,1.0,1.0,1.0,1.0,1.0,1.0,1.0,1.0,1.0,1.0,1.0,1.0,1.0,1.0,1.0,1.0,1.0,1.0,1.0,1.0,1.0,1.0,1.0,1.0,1.0,1.0,1.0,1.0,1.0,1.0,1.0,1.0,1.0,1.0,1.0,1.0,1.0,1.0,1.0,1.0,1.0,1.0,1.0,1.0,1.0,1.0,1.0,1.0,1.0,1.0,1.0,1.0,1.0,1.0,1.0,1.0,1.0,1.0,1.0,1.0,1.0,1.0,1.0,1.0,1.0,1.0,1.0,1.0,1.0,1.0,1.0,1.0,1.0,1.0,1.0,1.0,1.0,1.0,1.0,1.0,1.0,1.0,1.0,1.0,1.0,1.0,1.0,1.0,1.0,1.0,1.0,1.0,1.0,1.0,1.0,1.0,1.0,1.0,1.0,1.0,1.0,1.0,1.0,1.0,1.0,1.0,1.0,1.0,1.0,1.0,1.0,1.0,1.0,1.0,1.0,1.0,1.0,1.0,1.0,1.0,1.0,1.0,1.0,1.0,1.0,1.0,1.0,1.0,1.0,1.0,1.0,1.0,1.0,1.0,1.0,1.0,1.0,1.0,1.0,1.0,1.0,1.0,1.0,1.0,1.0,1.0,1.0,1.0,1.0,1.0,1.0,1.0,1.0,1.0,1.0,1.0,1.0,1.0,1.0,1.0,1.0,1.0,1.0,1.0,1.0,1.0,1.0,1.0,1.0,1.0,1.0,1.0,1.0,1.0,1.0,1.0,1.0,1.0,1.0,1.0,1.0,1.0,1.0,1.0,1.0,1.0,1.0,1.0,1.0,1.0,1.0,1.0,1.0,1.0,1.0,1.0,1.0,1.0,1.0,1.0,1.0,1.0,1.0,1.0,1.0,1.0,1.0,1.0,1.0,1.0,1.0,1.0,1.0,1.0,null],"obj_AO_over_time":[0.0,null,null,null,null,null,null,null,null,null,null,null,null,null,null,null,null,null,null,null,null,null,null,null,null,null,null,null,null,null,null,null,null,null,null,null,null,null,null,null,null,null,null,null,null,null,null,null,null,null,null,null,null,null,null,null,null,null,null,null,null,null,null,null,null,null,null,null,null,null,null,null,null,null,null,null,null,null,null,null,null,null,null,null,null,null,null,null,null,null,null,null,null,null,null,null,null,null,null,null,null,null,null,null,null,null,null,null,null,null,null,null,null,null,null,null,null,null,null,null,null,null,null,null,null,null,null,null,null,null,null,null,null,null,null,null,null,null,null,null,null,null,null,null,null,null,null,null,null,null,null,null,null,null,null,null,null,null,null,null,null,null,null,null,null,null,null,null,null,null,null,null,null,null,null,null,null,null,null,null,null,null,null,null,null,null,null,null,null,null,null,null,null,null,null,null,null,null,null,null,null,null,null,null,null,null,null,null,null,null,null,null,null,null,null,null,null,null,null,null,null,null,null,null,null,null,null,null,null,null,null,null,null,null,null],"coreLP_time_over_time":[0.004562493,0.004843231,0.004519532,0.004577281,0.005558546,0.004540622,0.004571942,0.00457167,0.004562984,0.004460291,0.004405278,0.004628348,0.004801493,0.004774132,0.004780293,0.004576911,0.004560769,0.004978446,0.004595875,0.004745908,0.004933271,0.004862608,0.004492913,0.004731802,0.004702486,0.004937349,0.005749807,0.00457099,0.00501791,0.004808075,0.004667401,0.004786886,0.004655788,0.004616233,0.005133226,0.004743724,0.00492229,0.00474652,0.004807103,0.004896622,0.004796694,0.004785132,0.004964388,0.00486408,0.004765085,0.004941547,0.048311887,0.004914095,0.004860564,0.004752201,0.004897835,0.00475752,0.004657422,0.005087741,0.004899948,0.005768492,0.004785893,0.004780944,0.004863519,0.005074376,0.00511865,0.004867919,0.004721172,0.004860895,0.005010666,0.004935446,0.004819977,0.004886254,0.004651261,0.004703178,0.004950043,0.004788539,0.004738555,0.004691615,0.004881724,0.005043538,0.005004264,0.005126644,0.005026265,0.004899918,0.004842341,0.004861275,0.004773029,0.004937599,0.004644187,0.005300492,0.004824196,0.004860113,0.00498564,0.004808095,0.005213528,0.00523578,0.005030915,0.005067865,0.005197056,0.005309769,0.005000186,0.005115132,0.004835187,0.004718656,0.005256188,0.005228827,0.005164016,0.00524138,0.004939182,0.005357488,0.005491301,0.005029843,0.004855885,0.004856156,0.004923001,0.005217556,0.005169926,0.005493264,0.004768291,0.005310841,0.005136454,0.005239126,0.00502291,0.005052275,0.00503452,0.005429443,0.004902443,0.00532128,0.005091048,0.005186077,0.004954842,0.005226162,0.00499098,0.005400961,0.005010296,0.005378918,0.005176409,0.005218707,0.004963649,0.005420597,0.005080066,0.005275606,0.005392204,0.005919326,0.005577933,0.00500193,0.005040853,0.00527836,0.004921799,0.005399829,0.005218879,0.005383618,0.005341008,0.005421589,0.005484056,0.005457657,0.005412602,0.005515355,0.00547543,0.005524754,0.005222113,0.005377487,0.005349052,0.005470703,0.005260697,0.005036765,0.005738125,0.005348192,0.005253503,0.005462295,0.005144298,0.005330758,0.005282348,0.005417613,0.005491551,0.005441767,0.005361826,0.005462085,0.005379471,0.005590727,0.005466153,0.005487012,0.005626495,0.005483635,0.005474088,0.005455093,0.005340627,0.005226702,0.005280945,0.005202296,0.005418443,0.005189103,0.005044499,0.005408214,0.005237994,0.005229278,0.005418764,0.005161621,0.00584646,0.005411951,0.005344895,0.005487623,0.005465773,0.005556612,0.0054377,0.005337541,0.005424304,0.005287457,0.005404196,0.005222104,0.005317042,0.005246299,0.005486251,0.005417483,0.004948149,0.00521452,0.005185415,0.005221203,0.005619712,0.005302756,0.005257881,0.005546825,0.005412041,0.005243354,0.005566402,0.005546014,0.005622917,0.005887495,0.006082212,0.005793249,0.005424504,0.005588654,0.005424505,0.005840397,0.005729378,0.005695705,0.005770916,0.005589496,0.006013173],"DO_time_over_time":[null,5.990428854,1.288581861,1.284585864,1.224584866,1.237559274,1.227686592,1.218201698,1.243579691,1.207359722,1.254088921,1.247775354,1.268859939,1.2884434,1.283861511,1.214887012,1.273095837,1.253863117,1.25625665,1.294150788,1.254355342,1.284349458,1.272040171,1.252034575,1.248084665,1.218396685,1.246668642,1.270633725,1.265789954,1.263860694,1.252275269,1.282894882,1.293286582,1.229161745,1.302865761,1.22836601,1.308209956,1.260248689,1.254777257,1.297692501,1.209944124,1.287003582,1.261634896,1.25842041,1.244028385,1.212499771,1.224920178,1.288891413,1.270073572,1.290465284,1.307598997,1.256382325,1.270095755,1.23588235,1.290157235,1.302424583,1.220735755,1.252278375,1.246940784,1.306906505,1.256684143,1.202955295,1.265843944,1.216554308,1.282634884,1.257494066,1.225758805,1.282237015,1.221448405,1.265729019,1.240942428,1.228070763,1.260668268,1.209252452,1.247322722,1.293478533,1.254552322,1.258847312,1.259573079,1.260305366,1.239414284,1.221374026,1.238182568,1.24983082,1.21747943,1.309526123,1.215952848,1.238696043,1.26661719,1.27273514,1.262568083,1.272720172,1.302884057,1.252849248,1.299668227,1.316213733,1.260909994,1.247745957,1.248131964,1.21255792,1.261800248,1.253273788,1.248081529,1.210896264,1.239189101,1.248141533,1.248020405,1.262662981,1.220229283,1.304617509,1.228767334,1.233011038,1.312704643,1.294218375,1.240967335,1.270772597,1.21944629,1.235983329,1.245560748,1.256210954,1.25514653,1.259904892,1.236241075,1.278787757,1.231831098,1.289295904,1.222218625,1.267633171,1.220684829,1.283340691,1.229074403,1.230045079,1.291156835,1.264594645,1.309392411,1.313514836,1.23345313,1.267110418,1.223019361,1.240222545,1.23223093,1.216422952,1.227901796,1.208625431,1.237323591,1.218624613,1.220549706,1.240885623,1.181745295,1.234045144,1.237417468,1.210181248,1.240743315,1.208315591,1.238931986,1.224113769,1.211806727,1.251248567,1.206894366,1.250133288,1.215036252,1.180571627,1.216926338,1.181803264,1.243421122,1.211160602,1.234586752,1.203856681,1.178024465,1.233722967,1.199263391,1.219331062,1.214527986,1.186440957,1.21266975,1.181663771,1.223021104,1.211112582,1.207179543,1.246884578,1.177494518,1.217672503,1.217971535,1.182215939,1.21531154,1.178601941,1.223732261,1.21356165,1.1803824,1.2196169,1.17972828,1.219272052,1.175636933,1.230187907,1.201518883,1.182281642,1.219512775,1.174468735,1.212744841,1.217312696,1.185077243,1.212040747,1.178439406,1.22830277,1.208616115,1.176343081,1.221234464,1.176569888,1.213868045,1.219757555,1.185996461,1.246874379,1.177978879,1.215651391,1.174291642,1.212704376,1.221977392,1.181695762,1.267380266,1.186900502,1.275952592,1.219511071,1.20926184,1.268947394,1.223616986,1.223825779,1.259715927,1.254585495,1.254127583,1.244934109,1.266181741,1.219053441,1.254432588,1.25060685,1.197939581],"AO_time_over_time":[3.999497353,null,null,null,null,null,null,null,null,null,null,null,null,null,null,null,null,null,null,null,null,null,null,null,null,null,null,null,null,null,null,null,null,null,null,null,null,null,null,null,null,null,null,null,null,null,null,null,null,null,null,null,null,null,null,null,null,null,null,null,null,null,null,null,null,null,null,null,null,null,null,null,null,null,null,null,null,null,null,null,null,null,null,null,null,null,null,null,null,null,null,null,null,null,null,null,null,null,null,null,null,null,null,null,null,null,null,null,null,null,null,null,null,null,null,null,null,null,null,null,null,null,null,null,null,null,null,null,null,null,null,null,null,null,null,null,null,null,null,null,null,null,null,null,null,null,null,null,null,null,null,null,null,null,null,null,null,null,null,null,null,null,null,null,null,null,null,null,null,null,null,null,null,null,null,null,null,null,null,null,null,null,null,null,null,null,null,null,null,null,null,null,null,null,null,null,null,null,null,null,null,null,null,null,null,null,null,null,null,null,null,null,null,null,null,null,null,null,null,null,null,null,null,null,null,null,null,null,null,null,null,null,null,null,null],"convergence_flag":false,"time_graph_att_constr":null,"time_graph_def_constr":null},"time_ne":18.893297579,"results_ne":{"att_strats":[[{"v":1,"t":0.0},{"v":2,"t":6.5},{"v":3,"t":22.5},{"v":17,"t":42.5}],[{"v":1,"t":0.0},{"v":5,"t":17.5},{"v":9,"t":36.5},{"v":17,"t":37.5}],[{"v":1,"t":0.0},{"v":5,"t":10.5},{"v":9,"t":29.5},{"v":17,"t":42.5}],[{"v":1,"t":0.0},{"v":5,"t":6.5},{"v":9,"t":24.5},{"v":17,"t":34.5}],[{"v":1,"t":0.0},{"v":5,"t":6.5},{"v":9,"t":26.5},{"v":17,"t":26.5}],[{"v":1,"t":0.0},{"v":5,"t":10.5},{"v":9,"t":33.5},{"v":17,"t":34.5}]],"att_probs":[0.5,0.5,-0.0,-0.0,-0.0,-0.0],"def_strats":[[[{"v":7,"t_a":0.0,"t_b":0.0},{"v":3,"t_a":8.0,"t_b":43.0}]],[[{"v":7,"t_a":0.0,"t_b":4.0},{"v":6,"t_a":11.0,"t_b":12.0},{"v":10,"t_a":15.0,"t_b":18.0},{"v":6,"t_a":19.0,"t_b":19.0},{"v":2,"t_a":21.0,"t_b":21.0},{"v":1,"t_a":22.0,"t_b":23.0},{"v":5,"t_a":26.0,"t_b":26.0},{"v":9,"t_a":35.0,"t_b":43.0}]],[[{"v":7,"t_a":0.0,"t_b":0.0},{"v":6,"t_a":7.0,"t_b":7.0},{"v":10,"t_a":10.0,"t_b":10.0},{"v":14,"t_a":16.0,"t_b":20.0},{"v":13,"t_a":24.0,"t_b":27.0},{"v":9,"t_a":29.0,"t_b":32.0},{"v":5,"t_a":38.0,"t_b":43.0}]],[[{"v":7,"t_a":0.0,"t_b":0.0},{"v":6,"t_a":7.0,"t_b":7.0},{"v":10,"t_a":10.0,"t_b":10.0},{"v":6,"t_a":11.0,"t_b":11.0},{"v":2,"t_a":13.0,"t_b":13.0},{"v":1,"t_a":14.0,"t_b":14.0},{"v":5,"t_a":17.0,"t_b":19.0},{"v":9,"t_a":28.0,"t_b":43.0}]],[[{"v":7,"t_a":0.0,"t_b":0.0},{"v":6,"t_a":7.0,"t_b":7.0},{"v":2,"t_a":9.0,"t_b":9.0},{"v":1,"t_a":10.0,"t_b":10.0},{"v":5,"t_a":13.0,"t_b":15.0},{"v":9,"t_a":24.0,"t_b":29.0},{"v":13,"t_a":37.0,"t_b":37.0},{"v":9,"t_a":39.0,"t_b":43.0}]],[[{"v":7,"t_a":0.0,"t_b":0.0},{"v":6,"t_a":7.0,"t_b":7.0},{"v":2,"t_a":9.0,"t_b":10.0},{"v":1,"t_a":11.0,"t_b":12.0},{"v":5,"t_a":15.0,"t_b":15.0},{"v":9,"t_a":24.0,"t_b":25.0},{"v":13,"t_a":33.0,"t_b":34.0},{"v":9,"t_a":36.0,"t_b":43.0}]],[[{"v":7,"t_a":0.0,"t_b":0.0},{"v":6,"t_a":7.0,"t_b":7.0},{"v":10,"t_a":10.0,"t_b":10.0},{"v":14,"t_a":16.0,"t_b":18.0},{"v":13,"t_a":22.0,"t_b":22.0},{"v":9,"t_a":24.0,"t_b":30.0},{"v":5,"t_a":36.0,"t_b":43.0}]],[[{"v":7,"t_a":0.0,"t_b":2.0},{"v":6,"t_a":9.0,"t_b":10.0},{"v":2,"t_a":12.0,"t_b":13.0},{"v":1,"t_a":14.0,"t_b":14.0},{"v":5,"t_a":17.0,"t_b":17.0},{"v":9,"t_a":26.0,"t_b":43.0}]],[[{"v":7,"t_a":0.0,"t_b":1.0},{"v":6,"t_a":8.0,"t_b":8.0},{"v":10,"t_a":11.0,"t_b":11.0},{"v":14,"t_a":17.0,"t_b":17.0},{"v":13,"t_a":21.0,"t_b":22.0},{"v":9,"t_a":24.0,"t_b":43.0}]]],"def_probs":[0.5,0.0,0.0,0.0,0.0,0.0,0.0,0.0,0.5],"obj_core_over_time":[1.0,-0.0,0.5,-0.0,0.33333333333333337,-0.0,0.3333333333333333,0.33333333333333337,0.3333333333333333,0.4,0.5],"obj_DO_over_time":[null,1.0,0.5,1.0,0.6666666666666667,1.0,0.6666666666666666,0.6666666666666667,0.6666666666666666,0.6,0.5],"obj_AO_over_time":[0.0,null,0.0,null,0.0,null,0.3333333333333333,0.0,0.3333333333333333,0.2,0.5],"coreLP_time_over_time":[4.172762409,0.004974639,0.004826029,0.004365663,0.004445814,0.004569577,0.004675316,0.00468818,0.004794399,0.004687618,0.004645699],"DO_time_over_time":[null,3.253551219,0.374730664,0.350387298,0.338495045,0.352114738,0.355138636,0.352116842,0.359369686,0.356544762,0.360042732],"AO_time_over_time":[3.597108518,null,0.232660213,null,0.220157591,null,0.21176796,0.227386452,0.221770878,0.206381276,0.211286974],"convergence_flag":true,"time_graph_att_constr":0.785672009,"time_graph_def_constr":0.539356468}}