{"time_zh":4.861082375,"results_zh":{"att_strats":[[{"v":1,"t":0.0},{"v":2,"t":3.0},{"v":3,"t":11.0},{"v":17,"t":11.75}]],"att_probs":[1.0],"def_strats":[[[{"v":7,"t_a":0.0,"t_b":0.0},{"v":3,"t_a":8.0,"t_b":12.0}]]],"def_probs":[1.0],"obj_core_over_time":[1.0],"obj_DO_over_time":[null],"obj_AO_over_time":[1.0],"coreLP_time_over_time":[0.004789359],"DO_time_over_time":[null],"AO_time_over_time":[4.138344845],"convergence_flag":true,"time_graph_att_constr":null,"time_graph_def_constr":null},"time_ne":10.038712859,"results_ne":{"att_strats":[[{"v":1,"t":0.0},{"v":2,"t":3.5},{"v":3,"t":11.5},{"v":17,"t":11.5}]],"att_probs":[1.0],"def_strats":[[[{"v":7,"t_a":0.0,"t_b":0.0},{"v":3,"t_a":8.0,"t_b":12.0}]]],"def_probs":[1.0],"obj_core_over_time":[1.0],"obj_DO_over_time":[null],"obj_AO_over_time":[1.0],"coreLP_time_over_time":[4.141892149],"DO_time_over_time":[null],"AO_time_over_time":[3.388123425],"convergence_flag":true,"time_graph_att_constr":0.778384017,"time_graph_def_constr":0.511221513}}