{"time_zh":301.063088866,"results_zh":{"att_strats":[[{"v":17,"t":0.0},{"v":16,"t":3.0},{"v":15,"t":7.0},{"v":50,"t":27.75}],[{"v":17,"t":0.0},{"v":16,"t":3.0},{"v":9,"t":8.0},{"v":10,"t":16.0},{"v":3,"t":22.0},{"v":50,"t":22.0}],[{"v":17,"t":0.0},{"v":16,"t":3.25},{"v":15,"t":7.25},{"v":50,"t":7.25}],[{"v":17,"t":0.0},{"v":16,"t":3.25},{"v":9,"t":8.25},{"v":10,"t":16.25},{"v":3,"t":22.25},{"v":50,"t":22.25}],[{"v":17,"t":0.0},{"v":16,"t":4.25},{"v":9,"t":9.25},{"v":16,"t":10.25},{"v":15,"t":15.25},{"v":50,"t":16.25}],[{"v":17,"t":0.0},{"v":16,"t":4.25},{"v":9,"t":9.25},{"v":10,"t":17.25},{"v":3,"t":23.25},{"v":50,"t":23.25}]],"att_probs":[-0.0,-0.0,-0.0,-0.0,-0.0,1.0],"def_strats":[[[{"v":22,"t_a":0.0,"t_b":0.0},{"v":3,"t_a":24.0,"t_b":28.0}],[{"v":16,"t_a":0.0,"t_b":0.0},{"v":15,"t_a":4.0,"t_b":28.0}],[{"v":19,"t_a":0.0,"t_b":28.0}]],[[{"v":22,"t_a":0.0,"t_b":0.0}],[{"v":16,"t_a":0.0,"t_b":3.0}],[{"v":19,"t_a":0.0,"t_b":0.0}]],[[{"v":22,"t_a":0.0,"t_b":0.0}],[{"v":16,"t_a":0.0,"t_b":4.0}],[{"v":19,"t_a":0.0,"t_b":0.0}]],[[{"v":22,"t_a":0.0,"t_b":0.0}],[{"v":16,"t_a":0.0,"t_b":5.0}],[{"v":19,"t_a":0.0,"t_b":0.0}]]],"def_probs":[0.0,0.0,0.0,1.0],"obj_core_over_time":[1.0,-0.0,1.0,0.5,1.0,0.5,1.0],"obj_DO_over_time":[null,1.0,null,1.0,null,1.0,null],"obj_AO_over_time":[0.0,null,0.0,0.0,0.0,0.0,null],"coreLP_time_over_time":[0.004357378,0.004388146,0.004593372,0.004465211,0.00449141,0.004588653,0.00521998],"DO_time_over_time":[null,96.693337577,null,92.674911471,null,85.095652141,null],"AO_time_over_time":[7.556251607,null,3.186846079,4.323825526,3.303843585,4.372867631,3.129536889],"convergence_flag":false,"time_graph_att_constr":null,"time_graph_def_constr":null},"time_ne":209.179145292,"results_ne":{"att_strats":[[{"v":17,"t":0.0},{"v":16,"t":3.5},{"v":15,"t":7.5},{"v":50,"t":27.5}],[{"v":17,"t":0.0},{"v":16,"t":4.5},{"v":9,"t":9.5},{"v":2,"t":16.5},{"v":1,"t":17.5},{"v":8,"t":24.5},{"v":1,"t":27.5},{"v":50,"t":27.5}],[{"v":17,"t":0.0},{"v":16,"t":3.5},{"v":9,"t":8.5},{"v":2,"t":14.5},{"v":1,"t":18.5},{"v":50,"t":22.5}],[{"v":17,"t":0.0},{"v":16,"t":10.5},{"v":9,"t":19.5},{"v":16,"t":22.5},{"v":15,"t":27.5},{"v":50,"t":27.5}],[{"v":17,"t":0.0},{"v":18,"t":3.5},{"v":25,"t":9.5},{"v":32,"t":12.5},{"v":33,"t":18.5},{"v":41,"t":25.5},{"v":42,"t":27.5},{"v":50,"t":27.5}],[{"v":17,"t":0.0},{"v":18,"t":3.5},{"v":25,"t":9.5},{"v":32,"t":11.5},{"v":33,"t":17.5},{"v":41,"t":23.5},{"v":42,"t":25.5},{"v":50,"t":25.5}],[{"v":17,"t":0.0},{"v":18,"t":2.5},{"v":25,"t":8.5},{"v":33,"t":13.5},{"v":41,"t":19.5},{"v":42,"t":21.5},{"v":50,"t":25.5}],[{"v":17,"t":0.0},{"v":16,"t":9.5},{"v":15,"t":22.5},{"v":50,"t":23.5}],[{"v":17,"t":0.0},{"v":18,"t":2.5},{"v":25,"t":8.5},{"v":33,"t":12.5},{"v":41,"t":18.5},{"v":42,"t":21.5},{"v":50,"t":23.5}],[{"v":17,"t":0.0},{"v":23,"t":11.5},{"v":22,"t":23.5},{"v":29,"t":26.5},{"v":50,"t":27.5}],[{"v":17,"t":0.0},{"v":18,"t":5.5},{"v":11,"t":9.5},{"v":4,"t":18.5},{"v":3,"t":27.5},{"v":50,"t":27.5}],[{"v":17,"t":0.0},{"v":18,"t":2.5},{"v":25,"t":8.5},{"v":32,"t":11.5},{"v":25,"t":13.5},{"v":33,"t":19.5},{"v":41,"t":25.5},{"v":42,"t":27.5},{"v":50,"t":27.5}],[{"v":17,"t":0.0},{"v":18,"t":2.5},{"v":11,"t":5.5},{"v":4,"t":16.5},{"v":3,"t":23.5},{"v":50,"t":26.5}],[{"v":17,"t":0.0},{"v":18,"t":3.5},{"v":11,"t":7.5},{"v":4,"t":16.5},{"v":3,"t":24.5},{"v":50,"t":24.5}],[{"v":17,"t":0.0},{"v":23,"t":14.5},{"v":22,"t":23.5},{"v":29,"t":27.5},{"v":50,"t":27.5}],[{"v":17,"t":0.0},{"v":18,"t":2.5},{"v":11,"t":5.5},{"v":4,"t":14.5},{"v":3,"t":22.5},{"v":50,"t":27.5}],[{"v":17,"t":0.0},{"v":18,"t":2.5},{"v":11,"t":5.5},{"v":4,"t":14.5},{"v":3,"t":21.5},{"v":50,"t":21.5}],[{"v":17,"t":0.0},{"v":23,"t":4.5},{"v":22,"t":17.5},{"v":15,"t":23.5},{"v":50,"t":25.5}],[{"v":17,"t":0.0},{"v":16,"t":17.5},{"v":15,"t":21.5},{"v":50,"t":26.5}],[{"v":17,"t":0.0},{"v":16,"t":3.5},{"v":9,"t":10.5},{"v":2,"t":16.5},{"v":1,"t":17.5},{"v":50,"t":23.5}],[{"v":17,"t":0.0},{"v":18,"t":2.5},{"v":25,"t":9.5},{"v":33,"t":14.5},{"v":41,"t":22.5},{"v":42,"t":24.5},{"v":50,"t":25.5}],[{"v":17,"t":0.0},{"v":16,"t":4.5},{"v":9,"t":9.5},{"v":2,"t":15.5},{"v":1,"t":16.5},{"v":50,"t":23.5}],[{"v":17,"t":0.0},{"v":16,"t":5.5},{"v":9,"t":10.5},{"v":2,"t":16.5},{"v":1,"t":17.5},{"v":50,"t":23.5}],[{"v":17,"t":0.0},{"v":16,"t":4.5},{"v":15,"t":8.5},{"v":22,"t":11.5},{"v":29,"t":14.5},{"v":50,"t":19.5}],[{"v":17,"t":0.0},{"v":16,"t":5.5},{"v":9,"t":10.5},{"v":2,"t":17.5},{"v":1,"t":24.5},{"v":50,"t":26.5}],[{"v":17,"t":0.0},{"v":16,"t":5.5},{"v":9,"t":13.5},{"v":2,"t":23.5},{"v":1,"t":26.5},{"v":50,"t":27.5}],[{"v":17,"t":0.0},{"v":23,"t":4.5},{"v":22,"t":24.5},{"v":29,"t":27.5},{"v":50,"t":27.5}],[{"v":17,"t":0.0},{"v":23,"t":4.5},{"v":22,"t":12.5},{"v":29,"t":15.5},{"v":36,"t":24.5},{"v":50,"t":27.5}],[{"v":17,"t":0.0},{"v":16,"t":10.5},{"v":15,"t":14.5},{"v":50,"t":27.5}],[{"v":17,"t":0.0},{"v":16,"t":14.5},{"v":9,"t":19.5},{"v":2,"t":25.5},{"v":1,"t":26.5},{"v":50,"t":26.5}],[{"v":17,"t":0.0},{"v":16,"t":8.5},{"v":15,"t":12.5},{"v":50,"t":21.5}],[{"v":17,"t":0.0},{"v":16,"t":10.5},{"v":9,"t":16.5},{"v":2,"t":22.5},{"v":1,"t":23.5},{"v":50,"t":27.5}],[{"v":17,"t":0.0},{"v":16,"t":23.5},{"v":15,"t":27.5},{"v":50,"t":27.5}],[{"v":17,"t":0.0},{"v":23,"t":5.5},{"v":22,"t":13.5},{"v":29,"t":17.5},{"v":36,"t":26.5},{"v":50,"t":26.5}],[{"v":17,"t":0.0},{"v":16,"t":19.5},{"v":15,"t":25.5},{"v":50,"t":25.5}],[{"v":17,"t":0.0},{"v":16,"t":11.5},{"v":9,"t":16.5},{"v":2,"t":22.5},{"v":1,"t":23.5},{"v":50,"t":24.5}],[{"v":17,"t":0.0},{"v":23,"t":6.5},{"v":22,"t":15.5},{"v":15,"t":26.5},{"v":50,"t":27.5}],[{"v":17,"t":0.0},{"v":23,"t":7.5},{"v":22,"t":16.5},{"v":15,"t":20.5},{"v":50,"t":25.5}],[{"v":17,"t":0.0},{"v":16,"t":15.5},{"v":9,"t":20.5},{"v":2,"t":26.5},{"v":1,"t":27.5},{"v":50,"t":27.5}],[{"v":17,"t":0.0},{"v":16,"t":11.5},{"v":15,"t":15.5},{"v":50,"t":16.5}],[{"v":17,"t":0.0},{"v":23,"t":9.5},{"v":22,"t":22.5},{"v":29,"t":25.5},{"v":50,"t":25.5}],[{"v":17,"t":0.0},{"v":23,"t":5.5},{"v":22,"t":15.5},{"v":29,"t":18.5},{"v":50,"t":26.5}],[{"v":17,"t":0.0},{"v":16,"t":13.5},{"v":9,"t":20.5},{"v":2,"t":26.5},{"v":1,"t":27.5},{"v":50,"t":27.5}],[{"v":17,"t":0.0},{"v":23,"t":7.5},{"v":22,"t":15.5},{"v":15,"t":19.5},{"v":50,"t":27.5}],[{"v":17,"t":0.0},{"v":18,"t":2.5},{"v":25,"t":10.5},{"v":33,"t":15.5},{"v":41,"t":23.5},{"v":42,"t":25.5},{"v":50,"t":27.5}],[{"v":17,"t":0.0},{"v":23,"t":8.5},{"v":22,"t":16.5},{"v":29,"t":19.5},{"v":50,"t":25.5}],[{"v":17,"t":0.0},{"v":18,"t":3.5},{"v":25,"t":9.5},{"v":33,"t":16.5},{"v":41,"t":23.5},{"v":42,"t":25.5},{"v":50,"t":26.5}],[{"v":17,"t":0.0},{"v":23,"t":6.5},{"v":22,"t":18.5},{"v":29,"t":24.5},{"v":50,"t":27.5}],[{"v":17,"t":0.0},{"v":23,"t":4.5},{"v":22,"t":12.5},{"v":29,"t":23.5},{"v":50,"t":27.5}],[{"v":17,"t":0.0},{"v":16,"t":3.5},{"v":9,"t":8.5},{"v":2,"t":14.5},{"v":1,"t":19.5},{"v":50,"t":21.5}],[{"v":17,"t":0.0},{"v":23,"t":4.5},{"v":22,"t":12.5},{"v":29,"t":20.5},{"v":50,"t":27.5}],[{"v":17,"t":0.0},{"v":23,"t":5.5},{"v":22,"t":13.5},{"v":29,"t":21.5},{"v":50,"t":27.5}],[{"v":17,"t":0.0},{"v":16,"t":4.5},{"v":15,"t":8.5},{"v":50,"t":24.5}],[{"v":17,"t":0.0},{"v":18,"t":2.5},{"v":25,"t":8.5},{"v":32,"t":10.5},{"v":33,"t":16.5},{"v":41,"t":24.5},{"v":42,"t":26.5},{"v":50,"t":27.5}],[{"v":17,"t":0.0},{"v":16,"t":10.5},{"v":9,"t":15.5},{"v":2,"t":21.5},{"v":1,"t":22.5},{"v":50,"t":22.5}],[{"v":17,"t":0.0},{"v":16,"t":10.5},{"v":15,"t":26.5},{"v":50,"t":27.5}],[{"v":17,"t":0.0},{"v":16,"t":20.5},{"v":15,"t":26.5},{"v":50,"t":27.5}],[{"v":17,"t":0.0},{"v":23,"t":5.5},{"v":22,"t":15.5},{"v":29,"t":22.5},{"v":50,"t":27.5}],[{"v":17,"t":0.0},{"v":18,"t":2.5},{"v":25,"t":8.5},{"v":33,"t":12.5},{"v":41,"t":18.5},{"v":42,"t":20.5},{"v":49,"t":25.5},{"v":48,"t":27.5},{"v":50,"t":27.5}],[{"v":17,"t":0.0},{"v":16,"t":21.5},{"v":15,"t":25.5},{"v":50,"t":26.5}],[{"v":17,"t":0.0},{"v":23,"t":8.5},{"v":22,"t":17.5},{"v":29,"t":20.5},{"v":50,"t":20.5}],[{"v":17,"t":0.0},{"v":16,"t":3.5},{"v":9,"t":8.5},{"v":2,"t":14.5},{"v":1,"t":20.5},{"v":50,"t":20.5}],[{"v":17,"t":0.0},{"v":16,"t":15.5},{"v":15,"t":20.5},{"v":50,"t":25.5}],[{"v":17,"t":0.0},{"v":16,"t":9.5},{"v":9,"t":14.5},{"v":2,"t":20.5},{"v":1,"t":21.5},{"v":50,"t":23.5}],[{"v":17,"t":0.0},{"v":16,"t":3.5},{"v":9,"t":8.5},{"v":2,"t":14.5},{"v":1,"t":15.5},{"v":50,"t":27.5}],[{"v":17,"t":0.0},{"v":23,"t":4.5},{"v":22,"t":18.5},{"v":29,"t":21.5},{"v":50,"t":27.5}],[{"v":17,"t":0.0},{"v":16,"t":18.5},{"v":15,"t":24.5},{"v":50,"t":26.5}],[{"v":17,"t":0.0},{"v":16,"t":13.5},{"v":15,"t":17.5},{"v":50,"t":22.5}],[{"v":17,"t":0.0},{"v":16,"t":5.5},{"v":15,"t":18.5},{"v":50,"t":22.5}],[{"v":17,"t":0.0},{"v":18,"t":5.5},{"v":25,"t":11.5},{"v":33,"t":16.5},{"v":41,"t":22.5},{"v":42,"t":24.5},{"v":50,"t":25.5}],[{"v":17,"t":0.0},{"v":16,"t":12.5},{"v":15,"t":16.5},{"v":50,"t":17.5}],[{"v":17,"t":0.0},{"v":16,"t":18.5},{"v":15,"t":23.5},{"v":50,"t":26.5}],[{"v":17,"t":0.0},{"v":18,"t":4.5},{"v":25,"t":11.5},{"v":33,"t":15.5},{"v":41,"t":24.5},{"v":42,"t":27.5},{"v":50,"t":27.5}],[{"v":17,"t":0.0},{"v":18,"t":4.5},{"v":25,"t":11.5},{"v":33,"t":15.5},{"v":41,"t":22.5},{"v":42,"t":24.5},{"v":50,"t":26.5}],[{"v":17,"t":0.0},{"v":18,"t":2.5},{"v":25,"t":11.5},{"v":33,"t":15.5},{"v":41,"t":25.5},{"v":42,"t":27.5},{"v":50,"t":27.5}],[{"v":17,"t":0.0},{"v":18,"t":2.5},{"v":25,"t":11.5},{"v":33,"t":15.5},{"v":41,"t":25.5},{"v":42,"t":27.5},{"v":50,"t":27.5}],[{"v":17,"t":0.0},{"v":18,"t":2.5},{"v":25,"t":8.5},{"v":33,"t":14.5},{"v":41,"t":20.5},{"v":42,"t":27.5},{"v":50,"t":27.5}],[{"v":17,"t":0.0},{"v":18,"t":4.5},{"v":25,"t":10.5},{"v":33,"t":15.5},{"v":41,"t":25.5},{"v":42,"t":27.5},{"v":50,"t":27.5}],[{"v":17,"t":0.0},{"v":16,"t":23.5},{"v":15,"t":27.5},{"v":50,"t":27.5}],[{"v":17,"t":0.0},{"v":18,"t":2.5},{"v":11,"t":5.5},{"v":4,"t":14.5},{"v":3,"t":21.5},{"v":50,"t":24.5}]],"att_probs":[-0.0,-0.0,-0.0,-0.0,-0.0,-0.0,-0.0,-0.0,-0.0,-0.0,-0.0,-0.0,-0.0,-0.0,-0.0,0.39999999999999997,-0.0,-0.0,0.2,-0.0,-0.0,0.2,-0.0,-0.0,-0.0,-0.0,0.2,-0.0,-0.0,-0.0,-0.0,-0.0,-0.0,-0.0,-0.0,-0.0,-0.0,-0.0,-0.0,-0.0,-0.0,-0.0,-0.0,-0.0,-0.0,-0.0,-0.0,-0.0,-0.0,-0.0,-0.0,-0.0,-0.0,-0.0,-0.0,-0.0,-0.0,-0.0,-0.0,-0.0,-0.0,-0.0,-0.0,-0.0,-0.0,-0.0,-0.0,-0.0,-0.0,-0.0,-0.0,-0.0,-0.0,-0.0,-0.0,-0.0,-0.0,-0.0,-0.0,-0.0],"def_strats":[[[{"v":22,"t_a":0.0,"t_b":0.0},{"v":3,"t_a":24.0,"t_b":28.0}],[{"v":16,"t_a":0.0,"t_b":0.0},{"v":15,"t_a":4.0,"t_b":28.0}],[{"v":19,"t_a":0.0,"t_b":28.0}]],[[{"v":22,"t_a":0.0,"t_b":0.0},{"v":15,"t_a":4.0,"t_b":4.0},{"v":16,"t_a":13.0,"t_b":13.0},{"v":15,"t_a":17.0,"t_b":17.0},{"v":8,"t_a":24.0,"t_b":24.0},{"v":1,"t_a":26.0,"t_b":28.0}],[{"v":16,"t_a":0.0,"t_b":0.0},{"v":9,"t_a":5.0,"t_b":8.0},{"v":16,"t_a":9.0,"t_b":9.0},{"v":17,"t_a":19.0,"t_b":19.0},{"v":18,"t_a":21.0,"t_b":22.0},{"v":11,"t_a":25.0,"t_b":28.0}],[{"v":19,"t_a":0.0,"t_b":0.0},{"v":26,"t_a":6.0,"t_b":6.0},{"v":33,"t_a":8.0,"t_b":9.0},{"v":26,"t_a":11.0,"t_b":12.0},{"v":33,"t_a":14.0,"t_b":14.0},{"v":26,"t_a":16.0,"t_b":26.0},{"v":27,"t_a":28.0,"t_b":28.0}]],[[{"v":22,"t_a":0.0,"t_b":0.0},{"v":15,"t_a":4.0,"t_b":8.0},{"v":16,"t_a":17.0,"t_b":20.0},{"v":15,"t_a":24.0,"t_b":24.0},{"v":22,"t_a":27.0,"t_b":28.0}],[{"v":16,"t_a":0.0,"t_b":2.0},{"v":9,"t_a":7.0,"t_b":10.0},{"v":16,"t_a":11.0,"t_b":11.0},{"v":17,"t_a":21.0,"t_b":21.0},{"v":16,"t_a":24.0,"t_b":24.0},{"v":15,"t_a":28.0,"t_b":28.0}],[{"v":19,"t_a":0.0,"t_b":0.0},{"v":26,"t_a":6.0,"t_b":9.0},{"v":33,"t_a":11.0,"t_b":11.0},{"v":26,"t_a":13.0,"t_b":14.0},{"v":27,"t_a":16.0,"t_b":23.0},{"v":26,"t_a":27.0,"t_b":28.0}]],[[{"v":22,"t_a":0.0,"t_b":0.0},{"v":15,"t_a":4.0,"t_b":4.0},{"v":16,"t_a":13.0,"t_b":13.0},{"v":9,"t_a":18.0,"t_b":18.0},{"v":16,"t_a":19.0,"t_b":24.0},{"v":15,"t_a":28.0,"t_b":28.0}],[{"v":16,"t_a":0.0,"t_b":3.0},{"v":9,"t_a":8.0,"t_b":8.0},{"v":2,"t_a":14.0,"t_b":15.0},{"v":9,"t_a":18.0,"t_b":18.0},{"v":16,"t_a":19.0,"t_b":24.0},{"v":15,"t_a":28.0,"t_b":28.0}],[{"v":19,"t_a":0.0,"t_b":0.0},{"v":26,"t_a":6.0,"t_b":6.0},{"v":27,"t_a":8.0,"t_b":8.0},{"v":26,"t_a":12.0,"t_b":13.0},{"v":33,"t_a":15.0,"t_b":16.0},{"v":26,"t_a":18.0,"t_b":18.0},{"v":19,"t_a":21.0,"t_b":22.0},{"v":26,"t_a":28.0,"t_b":28.0}]],[[{"v":22,"t_a":0.0,"t_b":8.0},{"v":15,"t_a":12.0,"t_b":12.0},{"v":22,"t_a":15.0,"t_b":17.0},{"v":15,"t_a":21.0,"t_b":25.0},{"v":22,"t_a":28.0,"t_b":28.0}],[{"v":16,"t_a":0.0,"t_b":2.0},{"v":15,"t_a":6.0,"t_b":6.0},{"v":16,"t_a":15.0,"t_b":16.0},{"v":17,"t_a":26.0,"t_b":28.0}],[{"v":19,"t_a":0.0,"t_b":2.0},{"v":26,"t_a":8.0,"t_b":8.0},{"v":27,"t_a":10.0,"t_b":10.0},{"v":20,"t_a":11.0,"t_b":11.0},{"v":27,"t_a":15.0,"t_b":15.0},{"v":35,"t_a":21.0,"t_b":21.0},{"v":41,"t_a":24.0,"t_b":24.0},{"v":42,"t_a":26.0,"t_b":28.0}]],[[{"v":22,"t_a":0.0,"t_b":0.0},{"v":15,"t_a":4.0,"t_b":6.0},{"v":8,"t_a":13.0,"t_b":13.0},{"v":1,"t_a":15.0,"t_b":15.0},{"v":2,"t_a":18.0,"t_b":18.0},{"v":9,"t_a":21.0,"t_b":21.0},{"v":16,"t_a":22.0,"t_b":23.0},{"v":15,"t_a":27.0,"t_b":28.0}],[{"v":16,"t_a":0.0,"t_b":0.0},{"v":9,"t_a":5.0,"t_b":5.0},{"v":2,"t_a":11.0,"t_b":12.0},{"v":1,"t_a":13.0,"t_b":13.0},{"v":2,"t_a":16.0,"t_b":18.0},{"v":9,"t_a":21.0,"t_b":21.0},{"v":16,"t_a":22.0,"t_b":23.0},{"v":15,"t_a":27.0,"t_b":28.0}],[{"v":19,"t_a":0.0,"t_b":1.0},{"v":26,"t_a":7.0,"t_b":8.0},{"v":27,"t_a":10.0,"t_b":10.0},{"v":26,"t_a":14.0,"t_b":15.0},{"v":33,"t_a":17.0,"t_b":17.0},{"v":41,"t_a":23.0,"t_b":23.0},{"v":42,"t_a":25.0,"t_b":28.0}]],[[{"v":22,"t_a":0.0,"t_b":0.0},{"v":15,"t_a":4.0,"t_b":8.0},{"v":22,"t_a":11.0,"t_b":14.0},{"v":23,"t_a":23.0,"t_b":23.0},{"v":17,"t_a":26.0,"t_b":26.0},{"v":18,"t_a":28.0,"t_b":28.0}],[{"v":16,"t_a":0.0,"t_b":1.0},{"v":15,"t_a":5.0,"t_b":8.0},{"v":22,"t_a":11.0,"t_b":14.0},{"v":23,"t_a":23.0,"t_b":23.0},{"v":17,"t_a":26.0,"t_b":26.0},{"v":18,"t_a":28.0,"t_b":28.0}],[{"v":19,"t_a":0.0,"t_b":1.0},{"v":26,"t_a":7.0,"t_b":7.0},{"v":33,"t_a":9.0,"t_b":10.0},{"v":26,"t_a":12.0,"t_b":12.0},{"v":33,"t_a":14.0,"t_b":16.0},{"v":41,"t_a":22.0,"t_b":23.0},{"v":42,"t_a":25.0,"t_b":28.0}]],[[{"v":22,"t_a":0.0,"t_b":11.0},{"v":29,"t_a":14.0,"t_b":14.0},{"v":36,"t_a":23.0,"t_b":28.0}],[{"v":16,"t_a":0.0,"t_b":2.0},{"v":15,"t_a":6.0,"t_b":8.0},{"v":16,"t_a":17.0,"t_b":17.0},{"v":17,"t_a":27.0,"t_b":28.0}],[{"v":19,"t_a":0.0,"t_b":0.0},{"v":26,"t_a":6.0,"t_b":8.0},{"v":33,"t_a":10.0,"t_b":14.0},{"v":26,"t_a":16.0,"t_b":19.0},{"v":19,"t_a":22.0,"t_b":28.0}]],[[{"v":22,"t_a":0.0,"t_b":0.0},{"v":15,"t_a":4.0,"t_b":5.0},{"v":8,"t_a":12.0,"t_b":13.0},{"v":1,"t_a":15.0,"t_b":20.0},{"v":2,"t_a":23.0,"t_b":24.0},{"v":1,"t_a":25.0,"t_b":28.0}],[{"v":16,"t_a":0.0,"t_b":0.0},{"v":15,"t_a":4.0,"t_b":5.0},{"v":8,"t_a":12.0,"t_b":13.0},{"v":1,"t_a":15.0,"t_b":20.0},{"v":2,"t_a":23.0,"t_b":24.0},{"v":1,"t_a":25.0,"t_b":28.0}],[{"v":19,"t_a":0.0,"t_b":4.0},{"v":26,"t_a":10.0,"t_b":11.0},{"v":33,"t_a":13.0,"t_b":13.0},{"v":41,"t_a":19.0,"t_b":21.0},{"v":42,"t_a":23.0,"t_b":28.0}]],[[{"v":22,"t_a":0.0,"t_b":0.0},{"v":15,"t_a":4.0,"t_b":4.0},{"v":8,"t_a":11.0,"t_b":13.0},{"v":1,"t_a":15.0,"t_b":16.0},{"v":2,"t_a":19.0,"t_b":19.0},{"v":1,"t_a":20.0,"t_b":20.0},{"v":8,"t_a":23.0,"t_b":24.0},{"v":1,"t_a":26.0,"t_b":28.0}],[{"v":16,"t_a":0.0,"t_b":2.0},{"v":9,"t_a":7.0,"t_b":8.0},{"v":16,"t_a":9.0,"t_b":10.0},{"v":9,"t_a":15.0,"t_b":16.0},{"v":2,"t_a":22.0,"t_b":22.0},{"v":1,"t_a":23.0,"t_b":23.0},{"v":2,"t_a":26.0,"t_b":26.0},{"v":1,"t_a":27.0,"t_b":28.0}],[{"v":19,"t_a":0.0,"t_b":3.0},{"v":26,"t_a":9.0,"t_b":10.0},{"v":33,"t_a":12.0,"t_b":12.0},{"v":26,"t_a":14.0,"t_b":17.0},{"v":27,"t_a":19.0,"t_b":19.0},{"v":20,"t_a":20.0,"t_b":21.0},{"v":27,"t_a":25.0,"t_b":26.0},{"v":20,"t_a":27.0,"t_b":28.0}]],[[{"v":22,"t_a":0.0,"t_b":0.0},{"v":15,"t_a":4.0,"t_b":4.0},{"v":8,"t_a":11.0,"t_b":11.0},{"v":1,"t_a":13.0,"t_b":17.0},{"v":8,"t_a":20.0,"t_b":20.0},{"v":15,"t_a":22.0,"t_b":28.0}],[{"v":16,"t_a":0.0,"t_b":5.0},{"v":9,"t_a":10.0,"t_b":10.0},{"v":2,"t_a":16.0,"t_b":16.0},{"v":9,"t_a":19.0,"t_b":21.0},{"v":16,"t_a":22.0,"t_b":23.0},{"v":9,"t_a":28.0,"t_b":28.0}],[{"v":19,"t_a":0.0,"t_b":0.0},{"v":26,"t_a":6.0,"t_b":6.0},{"v":33,"t_a":8.0,"t_b":8.0},{"v":26,"t_a":10.0,"t_b":10.0},{"v":33,"t_a":12.0,"t_b":14.0},{"v":26,"t_a":16.0,"t_b":19.0},{"v":19,"t_a":22.0,"t_b":22.0},{"v":26,"t_a":28.0,"t_b":28.0}]],[[{"v":22,"t_a":0.0,"t_b":1.0},{"v":23,"t_a":10.0,"t_b":14.0},{"v":22,"t_a":22.0,"t_b":22.0},{"v":29,"t_a":25.0,"t_b":28.0}],[{"v":16,"t_a":0.0,"t_b":0.0},{"v":15,"t_a":4.0,"t_b":4.0},{"v":8,"t_a":11.0,"t_b":11.0},{"v":15,"t_a":13.0,"t_b":13.0},{"v":16,"t_a":22.0,"t_b":28.0}],[{"v":19,"t_a":0.0,"t_b":1.0},{"v":26,"t_a":7.0,"t_b":7.0},{"v":27,"t_a":9.0,"t_b":12.0},{"v":26,"t_a":16.0,"t_b":18.0},{"v":33,"t_a":20.0,"t_b":20.0},{"v":41,"t_a":26.0,"t_b":26.0},{"v":42,"t_a":28.0,"t_b":28.0}]],[[{"v":22,"t_a":0.0,"t_b":0.0},{"v":23,"t_a":9.0,"t_b":14.0},{"v":22,"t_a":22.0,"t_b":22.0},{"v":29,"t_a":25.0,"t_b":28.0}],[{"v":16,"t_a":0.0,"t_b":0.0},{"v":15,"t_a":4.0,"t_b":4.0},{"v":8,"t_a":11.0,"t_b":11.0},{"v":15,"t_a":13.0,"t_b":13.0},{"v":22,"t_a":16.0,"t_b":18.0},{"v":15,"t_a":22.0,"t_b":24.0},{"v":22,"t_a":27.0,"t_b":28.0}],[{"v":19,"t_a":0.0,"t_b":0.0},{"v":26,"t_a":6.0,"t_b":6.0},{"v":33,"t_a":8.0,"t_b":8.0},{"v":25,"t_a":13.0,"t_b":13.0},{"v":33,"t_a":17.0,"t_b":19.0},{"v":26,"t_a":21.0,"t_b":21.0},{"v":27,"t_a":23.0,"t_b":26.0},{"v":20,"t_a":27.0,"t_b":28.0}]],[[{"v":22,"t_a":0.0,"t_b":0.0},{"v":15,"t_a":4.0,"t_b":4.0},{"v":8,"t_a":11.0,"t_b":11.0},{"v":1,"t_a":13.0,"t_b":13.0},{"v":2,"t_a":16.0,"t_b":17.0},{"v":3,"t_a":25.0,"t_b":28.0}],[{"v":16,"t_a":0.0,"t_b":2.0},{"v":15,"t_a":6.0,"t_b":9.0},{"v":8,"t_a":16.0,"t_b":18.0},{"v":15,"t_a":20.0,"t_b":20.0},{"v":22,"t_a":23.0,"t_b":25.0},{"v":29,"t_a":28.0,"t_b":28.0}],[{"v":19,"t_a":0.0,"t_b":0.0},{"v":26,"t_a":6.0,"t_b":8.0},{"v":27,"t_a":10.0,"t_b":11.0},{"v":26,"t_a":15.0,"t_b":16.0},{"v":33,"t_a":18.0,"t_b":18.0},{"v":26,"t_a":20.0,"t_b":22.0},{"v":19,"t_a":25.0,"t_b":28.0}]],[[{"v":22,"t_a":0.0,"t_b":0.0},{"v":15,"t_a":4.0,"t_b":4.0},{"v":8,"t_a":11.0,"t_b":12.0},{"v":1,"t_a":14.0,"t_b":14.0},{"v":2,"t_a":17.0,"t_b":17.0},{"v":3,"t_a":25.0,"t_b":28.0}],[{"v":16,"t_a":0.0,"t_b":4.0},{"v":15,"t_a":8.0,"t_b":11.0},{"v":16,"t_a":20.0,"t_b":20.0},{"v":9,"t_a":25.0,"t_b":25.0},{"v":16,"t_a":26.0,"t_b":28.0}],[{"v":19,"t_a":0.0,"t_b":1.0},{"v":26,"t_a":7.0,"t_b":9.0},{"v":33,"t_a":11.0,"t_b":13.0},{"v":26,"t_a":15.0,"t_b":16.0},{"v":33,"t_a":18.0,"t_b":19.0},{"v":41,"t_a":25.0,"t_b":25.0},{"v":42,"t_a":27.0,"t_b":28.0}]],[[{"v":22,"t_a":0.0,"t_b":3.0},{"v":15,"t_a":7.0,"t_b":7.0},{"v":8,"t_a":14.0,"t_b":14.0},{"v":1,"t_a":16.0,"t_b":16.0},{"v":8,"t_a":19.0,"t_b":19.0},{"v":15,"t_a":21.0,"t_b":22.0},{"v":22,"t_a":25.0,"t_b":25.0},{"v":29,"t_a":28.0,"t_b":28.0}],[{"v":16,"t_a":0.0,"t_b":1.0},{"v":9,"t_a":6.0,"t_b":7.0},{"v":10,"t_a":15.0,"t_b":17.0},{"v":3,"t_a":23.0,"t_b":24.0},{"v":10,"t_a":28.0,"t_b":28.0}],[{"v":19,"t_a":0.0,"t_b":0.0},{"v":26,"t_a":6.0,"t_b":6.0},{"v":27,"t_a":8.0,"t_b":12.0},{"v":26,"t_a":16.0,"t_b":17.0},{"v":33,"t_a":19.0,"t_b":25.0},{"v":26,"t_a":27.0,"t_b":28.0}]],[[{"v":22,"t_a":0.0,"t_b":0.0},{"v":23,"t_a":9.0,"t_b":13.0},{"v":22,"t_a":21.0,"t_b":23.0},{"v":15,"t_a":27.0,"t_b":28.0}],[{"v":16,"t_a":0.0,"t_b":3.0},{"v":9,"t_a":8.0,"t_b":9.0},{"v":10,"t_a":17.0,"t_b":17.0},{"v":3,"t_a":23.0,"t_b":28.0}],[{"v":19,"t_a":0.0,"t_b":3.0},{"v":26,"t_a":9.0,"t_b":9.0},{"v":33,"t_a":11.0,"t_b":13.0},{"v":41,"t_a":19.0,"t_b":19.0},{"v":42,"t_a":21.0,"t_b":28.0}]],[[{"v":22,"t_a":0.0,"t_b":0.0},{"v":15,"t_a":4.0,"t_b":8.0},{"v":22,"t_a":11.0,"t_b":11.0},{"v":15,"t_a":15.0,"t_b":15.0},{"v":22,"t_a":18.0,"t_b":19.0},{"v":29,"t_a":22.0,"t_b":22.0},{"v":37,"t_a":26.0,"t_b":28.0}],[{"v":16,"t_a":0.0,"t_b":4.0},{"v":9,"t_a":9.0,"t_b":9.0},{"v":10,"t_a":17.0,"t_b":17.0},{"v":3,"t_a":23.0,"t_b":24.0},{"v":10,"t_a":28.0,"t_b":28.0}],[{"v":19,"t_a":0.0,"t_b":0.0},{"v":26,"t_a":6.0,"t_b":6.0},{"v":33,"t_a":8.0,"t_b":8.0},{"v":25,"t_a":13.0,"t_b":14.0},{"v":33,"t_a":18.0,"t_b":18.0},{"v":26,"t_a":20.0,"t_b":22.0},{"v":19,"t_a":25.0,"t_b":28.0}]],[[{"v":22,"t_a":0.0,"t_b":5.0},{"v":15,"t_a":9.0,"t_b":9.0},{"v":16,"t_a":18.0,"t_b":18.0},{"v":15,"t_a":22.0,"t_b":23.0},{"v":22,"t_a":26.0,"t_b":28.0}],[{"v":16,"t_a":0.0,"t_b":4.0},{"v":9,"t_a":9.0,"t_b":9.0},{"v":10,"t_a":17.0,"t_b":17.0},{"v":3,"t_a":23.0,"t_b":28.0}],[{"v":19,"t_a":0.0,"t_b":4.0},{"v":26,"t_a":10.0,"t_b":11.0},{"v":33,"t_a":13.0,"t_b":14.0},{"v":26,"t_a":16.0,"t_b":20.0},{"v":19,"t_a":23.0,"t_b":28.0}]],[[{"v":22,"t_a":0.0,"t_b":3.0},{"v":15,"t_a":7.0,"t_b":7.0},{"v":8,"t_a":14.0,"t_b":14.0},{"v":1,"t_a":16.0,"t_b":16.0},{"v":2,"t_a":19.0,"t_b":21.0},{"v":1,"t_a":22.0,"t_b":22.0},{"v":8,"t_a":25.0,"t_b":25.0},{"v":15,"t_a":27.0,"t_b":28.0}],[{"v":16,"t_a":0.0,"t_b":1.0},{"v":9,"t_a":6.0,"t_b":7.0},{"v":10,"t_a":15.0,"t_b":16.0},{"v":3,"t_a":22.0,"t_b":23.0},{"v":10,"t_a":27.0,"t_b":28.0}],[{"v":19,"t_a":0.0,"t_b":0.0},{"v":26,"t_a":6.0,"t_b":6.0},{"v":27,"t_a":8.0,"t_b":9.0},{"v":26,"t_a":13.0,"t_b":14.0},{"v":33,"t_a":16.0,"t_b":17.0},{"v":25,"t_a":22.0,"t_b":23.0},{"v":32,"t_a":25.0,"t_b":26.0},{"v":25,"t_a":28.0,"t_b":28.0}]],[[{"v":22,"t_a":0.0,"t_b":0.0},{"v":15,"t_a":4.0,"t_b":4.0},{"v":8,"t_a":11.0,"t_b":13.0},{"v":15,"t_a":15.0,"t_b":15.0},{"v":22,"t_a":18.0,"t_b":18.0},{"v":15,"t_a":22.0,"t_b":23.0},{"v":22,"t_a":26.0,"t_b":28.0}],[{"v":16,"t_a":0.0,"t_b":2.0},{"v":9,"t_a":7.0,"t_b":7.0},{"v":2,"t_a":13.0,"t_b":13.0},{"v":3,"t_a":21.0,"t_b":24.0},{"v":10,"t_a":28.0,"t_b":28.0}],[{"v":19,"t_a":0.0,"t_b":0.0},{"v":26,"t_a":6.0,"t_b":6.0},{"v":33,"t_a":8.0,"t_b":8.0},{"v":25,"t_a":13.0,"t_b":17.0},{"v":32,"t_a":19.0,"t_b":20.0},{"v":25,"t_a":22.0,"t_b":22.0},{"v":33,"t_a":26.0,"t_b":26.0},{"v":26,"t_a":28.0,"t_b":28.0}]],[[{"v":22,"t_a":0.0,"t_b":3.0},{"v":15,"t_a":7.0,"t_b":8.0},{"v":22,"t_a":11.0,"t_b":24.0},{"v":15,"t_a":28.0,"t_b":28.0}],[{"v":16,"t_a":0.0,"t_b":2.0},{"v":9,"t_a":7.0,"t_b":8.0},{"v":10,"t_a":16.0,"t_b":16.0},{"v":3,"t_a":22.0,"t_b":28.0}],[{"v":19,"t_a":0.0,"t_b":1.0},{"v":26,"t_a":7.0,"t_b":10.0},{"v":33,"t_a":12.0,"t_b":14.0},{"v":41,"t_a":20.0,"t_b":20.0},{"v":42,"t_a":22.0,"t_b":28.0}]],[[{"v":22,"t_a":0.0,"t_b":0.0},{"v":15,"t_a":4.0,"t_b":4.0},{"v":8,"t_a":11.0,"t_b":12.0},{"v":1,"t_a":14.0,"t_b":16.0},{"v":8,"t_a":19.0,"t_b":19.0},{"v":1,"t_a":21.0,"t_b":21.0},{"v":8,"t_a":24.0,"t_b":25.0},{"v":1,"t_a":27.0,"t_b":28.0}],[{"v":16,"t_a":0.0,"t_b":0.0},{"v":9,"t_a":5.0,"t_b":6.0},{"v":10,"t_a":14.0,"t_b":15.0},{"v":3,"t_a":21.0,"t_b":28.0}],[{"v":19,"t_a":0.0,"t_b":3.0},{"v":26,"t_a":9.0,"t_b":10.0},{"v":33,"t_a":12.0,"t_b":14.0},{"v":26,"t_a":16.0,"t_b":16.0},{"v":33,"t_a":18.0,"t_b":19.0},{"v":26,"t_a":21.0,"t_b":21.0},{"v":27,"t_a":23.0,"t_b":25.0},{"v":20,"t_a":26.0,"t_b":28.0}]],[[{"v":22,"t_a":0.0,"t_b":4.0},{"v":23,"t_a":13.0,"t_b":15.0},{"v":22,"t_a":23.0,"t_b":24.0},{"v":29,"t_a":27.0,"t_b":28.0}],[{"v":16,"t_a":0.0,"t_b":4.0},{"v":17,"t_a":14.0,"t_b":14.0},{"v":16,"t_a":17.0,"t_b":18.0},{"v":15,"t_a":22.0,"t_b":28.0}],[{"v":19,"t_a":0.0,"t_b":5.0},{"v":26,"t_a":11.0,"t_b":13.0},{"v":33,"t_a":15.0,"t_b":17.0},{"v":41,"t_a":23.0,"t_b":23.0},{"v":42,"t_a":25.0,"t_b":28.0}]],[[{"v":22,"t_a":0.0,"t_b":3.0},{"v":15,"t_a":7.0,"t_b":11.0},{"v":22,"t_a":14.0,"t_b":14.0},{"v":29,"t_a":17.0,"t_b":17.0},{"v":37,"t_a":21.0,"t_b":21.0},{"v":29,"t_a":28.0,"t_b":28.0}],[{"v":16,"t_a":0.0,"t_b":0.0},{"v":9,"t_a":5.0,"t_b":5.0},{"v":2,"t_a":11.0,"t_b":11.0},{"v":3,"t_a":19.0,"t_b":23.0},{"v":10,"t_a":27.0,"t_b":28.0}],[{"v":19,"t_a":0.0,"t_b":4.0},{"v":26,"t_a":10.0,"t_b":10.0},{"v":27,"t_a":12.0,"t_b":12.0},{"v":26,"t_a":16.0,"t_b":16.0},{"v":27,"t_a":18.0,"t_b":19.0},{"v":26,"t_a":23.0,"t_b":25.0},{"v":27,"t_a":27.0,"t_b":27.0},{"v":20,"t_a":28.0,"t_b":28.0}]],[[{"v":22,"t_a":0.0,"t_b":0.0},{"v":15,"t_a":4.0,"t_b":7.0},{"v":16,"t_a":16.0,"t_b":21.0},{"v":15,"t_a":25.0,"t_b":25.0},{"v":22,"t_a":28.0,"t_b":28.0}],[{"v":16,"t_a":0.0,"t_b":1.0},{"v":9,"t_a":6.0,"t_b":7.0},{"v":2,"t_a":13.0,"t_b":13.0},{"v":3,"t_a":21.0,"t_b":22.0},{"v":10,"t_a":26.0,"t_b":28.0}],[{"v":19,"t_a":0.0,"t_b":0.0},{"v":26,"t_a":6.0,"t_b":11.0},{"v":33,"t_a":13.0,"t_b":15.0},{"v":26,"t_a":17.0,"t_b":17.0},{"v":19,"t_a":20.0,"t_b":20.0},{"v":26,"t_a":26.0,"t_b":26.0},{"v":27,"t_a":28.0,"t_b":28.0}]],[[{"v":22,"t_a":0.0,"t_b":0.0},{"v":15,"t_a":4.0,"t_b":4.0},{"v":16,"t_a":13.0,"t_b":14.0},{"v":15,"t_a":18.0,"t_b":20.0},{"v":22,"t_a":23.0,"t_b":25.0},{"v":29,"t_a":28.0,"t_b":28.0}],[{"v":16,"t_a":0.0,"t_b":0.0},{"v":9,"t_a":5.0,"t_b":8.0},{"v":2,"t_a":14.0,"t_b":16.0},{"v":3,"t_a":24.0,"t_b":28.0}],[{"v":19,"t_a":0.0,"t_b":9.0},{"v":26,"t_a":15.0,"t_b":17.0},{"v":27,"t_a":19.0,"t_b":19.0},{"v":20,"t_a":20.0,"t_b":20.0},{"v":13,"t_a":27.0,"t_b":28.0}]],[[{"v":22,"t_a":0.0,"t_b":2.0},{"v":15,"t_a":6.0,"t_b":6.0},{"v":8,"t_a":13.0,"t_b":14.0},{"v":1,"t_a":16.0,"t_b":18.0},{"v":8,"t_a":21.0,"t_b":24.0},{"v":15,"t_a":26.0,"t_b":28.0}],[{"v":16,"t_a":0.0,"t_b":0.0},{"v":9,"t_a":5.0,"t_b":5.0},{"v":2,"t_a":11.0,"t_b":12.0},{"v":3,"t_a":20.0,"t_b":24.0},{"v":10,"t_a":28.0,"t_b":28.0}],[{"v":19,"t_a":0.0,"t_b":5.0},{"v":26,"t_a":11.0,"t_b":11.0},{"v":33,"t_a":13.0,"t_b":13.0},{"v":26,"t_a":15.0,"t_b":17.0},{"v":27,"t_a":19.0,"t_b":19.0},{"v":35,"t_a":25.0,"t_b":25.0},{"v":28,"t_a":26.0,"t_b":28.0}]],[[{"v":22,"t_a":0.0,"t_b":0.0},{"v":15,"t_a":4.0,"t_b":4.0},{"v":16,"t_a":13.0,"t_b":17.0},{"v":15,"t_a":21.0,"t_b":22.0},{"v":22,"t_a":25.0,"t_b":28.0}],[{"v":16,"t_a":0.0,"t_b":0.0},{"v":9,"t_a":5.0,"t_b":5.0},{"v":2,"t_a":11.0,"t_b":11.0},{"v":1,"t_a":12.0,"t_b":12.0},{"v":2,"t_a":15.0,"t_b":17.0},{"v":3,"t_a":25.0,"t_b":28.0}],[{"v":19,"t_a":0.0,"t_b":2.0},{"v":26,"t_a":8.0,"t_b":10.0},{"v":33,"t_a":12.0,"t_b":15.0},{"v":26,"t_a":17.0,"t_b":22.0},{"v":27,"t_a":24.0,"t_b":25.0},{"v":20,"t_a":26.0,"t_b":28.0}]],[[{"v":22,"t_a":0.0,"t_b":0.0},{"v":15,"t_a":4.0,"t_b":4.0},{"v":8,"t_a":11.0,"t_b":11.0},{"v":1,"t_a":13.0,"t_b":13.0},{"v":2,"t_a":16.0,"t_b":16.0},{"v":3,"t_a":24.0,"t_b":28.0}],[{"v":16,"t_a":0.0,"t_b":10.0},{"v":15,"t_a":14.0,"t_b":24.0},{"v":22,"t_a":27.0,"t_b":28.0}],[{"v":19,"t_a":0.0,"t_b":3.0},{"v":26,"t_a":9.0,"t_b":11.0},{"v":33,"t_a":13.0,"t_b":15.0},{"v":26,"t_a":17.0,"t_b":18.0},{"v":19,"t_a":21.0,"t_b":21.0},{"v":26,"t_a":27.0,"t_b":28.0}]],[[{"v":22,"t_a":0.0,"t_b":4.0},{"v":23,"t_a":13.0,"t_b":15.0},{"v":17,"t_a":18.0,"t_b":18.0},{"v":16,"t_a":21.0,"t_b":23.0},{"v":15,"t_a":27.0,"t_b":28.0}],[{"v":16,"t_a":0.0,"t_b":5.0},{"v":9,"t_a":10.0,"t_b":20.0},{"v":16,"t_a":21.0,"t_b":23.0},{"v":15,"t_a":27.0,"t_b":28.0}],[{"v":19,"t_a":0.0,"t_b":2.0},{"v":26,"t_a":8.0,"t_b":10.0},{"v":33,"t_a":12.0,"t_b":13.0},{"v":26,"t_a":15.0,"t_b":15.0},{"v":27,"t_a":17.0,"t_b":18.0},{"v":20,"t_a":19.0,"t_b":19.0},{"v":27,"t_a":23.0,"t_b":23.0},{"v":26,"t_a":27.0,"t_b":28.0}]],[[{"v":22,"t_a":0.0,"t_b":2.0},{"v":23,"t_a":11.0,"t_b":16.0},{"v":22,"t_a":24.0,"t_b":25.0},{"v":29,"t_a":28.0,"t_b":28.0}],[{"v":16,"t_a":0.0,"t_b":5.0},{"v":9,"t_a":10.0,"t_b":10.0},{"v":2,"t_a":16.0,"t_b":16.0},{"v":1,"t_a":17.0,"t_b":18.0},{"v":2,"t_a":21.0,"t_b":22.0},{"v":1,"t_a":23.0,"t_b":28.0}],[{"v":19,"t_a":0.0,"t_b":0.0},{"v":26,"t_a":6.0,"t_b":6.0},{"v":27,"t_a":8.0,"t_b":8.0},{"v":35,"t_a":14.0,"t_b":14.0},{"v":27,"t_a":17.0,"t_b":17.0},{"v":35,"t_a":23.0,"t_b":24.0},{"v":27,"t_a":27.0,"t_b":28.0}]],[[{"v":22,"t_a":0.0,"t_b":2.0},{"v":15,"t_a":6.0,"t_b":6.0},{"v":22,"t_a":9.0,"t_b":13.0},{"v":15,"t_a":17.0,"t_b":21.0},{"v":22,"t_a":24.0,"t_b":28.0}],[{"v":16,"t_a":0.0,"t_b":8.0},{"v":9,"t_a":13.0,"t_b":16.0},{"v":16,"t_a":17.0,"t_b":17.0},{"v":15,"t_a":21.0,"t_b":28.0}],[{"v":19,"t_a":0.0,"t_b":0.0},{"v":26,"t_a":6.0,"t_b":6.0},{"v":33,"t_a":8.0,"t_b":8.0},{"v":26,"t_a":10.0,"t_b":10.0},{"v":33,"t_a":12.0,"t_b":12.0},{"v":26,"t_a":14.0,"t_b":17.0},{"v":27,"t_a":19.0,"t_b":23.0},{"v":20,"t_a":24.0,"t_b":28.0}]],[[{"v":22,"t_a":0.0,"t_b":10.0},{"v":15,"t_a":14.0,"t_b":15.0},{"v":22,"t_a":18.0,"t_b":18.0},{"v":29,"t_a":21.0,"t_b":28.0}],[{"v":16,"t_a":0.0,"t_b":2.0},{"v":9,"t_a":7.0,"t_b":7.0},{"v":10,"t_a":15.0,"t_b":15.0},{"v":3,"t_a":21.0,"t_b":28.0}],[{"v":19,"t_a":0.0,"t_b":0.0},{"v":26,"t_a":6.0,"t_b":7.0},{"v":27,"t_a":9.0,"t_b":12.0},{"v":26,"t_a":16.0,"t_b":18.0},{"v":19,"t_a":21.0,"t_b":21.0},{"v":26,"t_a":27.0,"t_b":28.0}]],[[{"v":22,"t_a":0.0,"t_b":10.0},{"v":15,"t_a":14.0,"t_b":15.0},{"v":8,"t_a":22.0,"t_b":22.0},{"v":1,"t_a":24.0,"t_b":28.0}],[{"v":16,"t_a":0.0,"t_b":0.0},{"v":9,"t_a":5.0,"t_b":5.0},{"v":10,"t_a":13.0,"t_b":13.0},{"v":3,"t_a":19.0,"t_b":22.0},{"v":10,"t_a":26.0,"t_b":28.0}],[{"v":19,"t_a":0.0,"t_b":2.0},{"v":26,"t_a":8.0,"t_b":9.0},{"v":33,"t_a":11.0,"t_b":17.0},{"v":41,"t_a":23.0,"t_b":23.0},{"v":42,"t_a":25.0,"t_b":28.0}]],[[{"v":22,"t_a":0.0,"t_b":5.0},{"v":15,"t_a":9.0,"t_b":9.0},{"v":22,"t_a":12.0,"t_b":13.0},{"v":15,"t_a":17.0,"t_b":21.0},{"v":22,"t_a":24.0,"t_b":25.0},{"v":29,"t_a":28.0,"t_b":28.0}],[{"v":16,"t_a":0.0,"t_b":15.0},{"v":17,"t_a":25.0,"t_b":26.0},{"v":18,"t_a":28.0,"t_b":28.0}],[{"v":19,"t_a":0.0,"t_b":0.0},{"v":26,"t_a":6.0,"t_b":6.0},{"v":33,"t_a":8.0,"t_b":9.0},{"v":26,"t_a":11.0,"t_b":11.0},{"v":27,"t_a":13.0,"t_b":13.0},{"v":20,"t_a":14.0,"t_b":14.0},{"v":27,"t_a":18.0,"t_b":18.0},{"v":26,"t_a":22.0,"t_b":22.0},{"v":19,"t_a":25.0,"t_b":28.0}]],[[{"v":22,"t_a":0.0,"t_b":1.0},{"v":15,"t_a":5.0,"t_b":5.0},{"v":16,"t_a":14.0,"t_b":17.0},{"v":15,"t_a":21.0,"t_b":24.0},{"v":22,"t_a":27.0,"t_b":28.0}],[{"v":16,"t_a":0.0,"t_b":0.0},{"v":9,"t_a":5.0,"t_b":6.0},{"v":10,"t_a":14.0,"t_b":14.0},{"v":3,"t_a":20.0,"t_b":28.0}],[{"v":19,"t_a":0.0,"t_b":0.0},{"v":26,"t_a":6.0,"t_b":6.0},{"v":27,"t_a":8.0,"t_b":11.0},{"v":26,"t_a":15.0,"t_b":18.0},{"v":19,"t_a":21.0,"t_b":21.0},{"v":26,"t_a":27.0,"t_b":28.0}]],[[{"v":22,"t_a":0.0,"t_b":1.0},{"v":23,"t_a":10.0,"t_b":15.0},{"v":22,"t_a":23.0,"t_b":24.0},{"v":15,"t_a":28.0,"t_b":28.0}],[{"v":16,"t_a":0.0,"t_b":2.0},{"v":9,"t_a":7.0,"t_b":7.0},{"v":16,"t_a":8.0,"t_b":23.0},{"v":15,"t_a":27.0,"t_b":28.0}],[{"v":19,"t_a":0.0,"t_b":0.0},{"v":26,"t_a":6.0,"t_b":6.0},{"v":33,"t_a":8.0,"t_b":8.0},{"v":26,"t_a":10.0,"t_b":10.0},{"v":33,"t_a":12.0,"t_b":14.0},{"v":41,"t_a":20.0,"t_b":22.0},{"v":42,"t_a":24.0,"t_b":28.0}]],[[{"v":22,"t_a":0.0,"t_b":5.0},{"v":15,"t_a":9.0,"t_b":9.0},{"v":22,"t_a":12.0,"t_b":14.0},{"v":29,"t_a":17.0,"t_b":28.0}],[{"v":16,"t_a":0.0,"t_b":11.0},{"v":9,"t_a":16.0,"t_b":16.0},{"v":16,"t_a":17.0,"t_b":28.0}],[{"v":19,"t_a":0.0,"t_b":0.0},{"v":26,"t_a":6.0,"t_b":6.0},{"v":33,"t_a":8.0,"t_b":9.0},{"v":26,"t_a":11.0,"t_b":11.0},{"v":33,"t_a":13.0,"t_b":14.0},{"v":26,"t_a":16.0,"t_b":18.0},{"v":19,"t_a":21.0,"t_b":28.0}]],[[{"v":22,"t_a":0.0,"t_b":6.0},{"v":15,"t_a":10.0,"t_b":14.0},{"v":22,"t_a":17.0,"t_b":19.0},{"v":15,"t_a":23.0,"t_b":28.0}],[{"v":16,"t_a":0.0,"t_b":17.0},{"v":15,"t_a":21.0,"t_b":21.0},{"v":22,"t_a":24.0,"t_b":28.0}],[{"v":19,"t_a":0.0,"t_b":3.0},{"v":26,"t_a":9.0,"t_b":9.0},{"v":33,"t_a":11.0,"t_b":13.0},{"v":26,"t_a":15.0,"t_b":15.0},{"v":33,"t_a":17.0,"t_b":19.0},{"v":41,"t_a":25.0,"t_b":26.0},{"v":40,"t_a":27.0,"t_b":28.0}]],[[{"v":22,"t_a":0.0,"t_b":0.0},{"v":15,"t_a":4.0,"t_b":4.0},{"v":22,"t_a":7.0,"t_b":7.0},{"v":15,"t_a":11.0,"t_b":11.0},{"v":22,"t_a":14.0,"t_b":14.0},{"v":29,"t_a":17.0,"t_b":18.0},{"v":36,"t_a":27.0,"t_b":28.0}],[{"v":16,"t_a":0.0,"t_b":0.0},{"v":9,"t_a":5.0,"t_b":6.0},{"v":2,"t_a":12.0,"t_b":12.0},{"v":1,"t_a":13.0,"t_b":15.0},{"v":8,"t_a":18.0,"t_b":18.0},{"v":1,"t_a":20.0,"t_b":25.0},{"v":8,"t_a":28.0,"t_b":28.0}],[{"v":19,"t_a":0.0,"t_b":0.0},{"v":26,"t_a":6.0,"t_b":6.0},{"v":33,"t_a":8.0,"t_b":8.0},{"v":25,"t_a":13.0,"t_b":13.0},{"v":33,"t_a":17.0,"t_b":18.0},{"v":25,"t_a":23.0,"t_b":23.0},{"v":18,"t_a":28.0,"t_b":28.0}]],[[{"v":22,"t_a":0.0,"t_b":0.0},{"v":15,"t_a":4.0,"t_b":4.0},{"v":8,"t_a":11.0,"t_b":11.0},{"v":1,"t_a":13.0,"t_b":13.0},{"v":8,"t_a":16.0,"t_b":16.0},{"v":1,"t_a":18.0,"t_b":19.0},{"v":2,"t_a":22.0,"t_b":23.0},{"v":1,"t_a":24.0,"t_b":24.0},{"v":2,"t_a":27.0,"t_b":28.0}],[{"v":16,"t_a":0.0,"t_b":0.0},{"v":9,"t_a":5.0,"t_b":5.0},{"v":10,"t_a":13.0,"t_b":14.0},{"v":3,"t_a":20.0,"t_b":28.0}],[{"v":19,"t_a":0.0,"t_b":5.0},{"v":26,"t_a":11.0,"t_b":12.0},{"v":33,"t_a":14.0,"t_b":17.0},{"v":25,"t_a":22.0,"t_b":24.0},{"v":33,"t_a":28.0,"t_b":28.0}]],[[{"v":22,"t_a":0.0,"t_b":4.0},{"v":15,"t_a":8.0,"t_b":9.0},{"v":22,"t_a":12.0,"t_b":21.0},{"v":15,"t_a":25.0,"t_b":28.0}],[{"v":16,"t_a":0.0,"t_b":0.0},{"v":9,"t_a":5.0,"t_b":7.0},{"v":10,"t_a":15.0,"t_b":15.0},{"v":3,"t_a":21.0,"t_b":22.0},{"v":10,"t_a":26.0,"t_b":28.0}],[{"v":19,"t_a":0.0,"t_b":0.0},{"v":26,"t_a":6.0,"t_b":6.0},{"v":33,"t_a":8.0,"t_b":8.0},{"v":26,"t_a":10.0,"t_b":18.0},{"v":33,"t_a":20.0,"t_b":20.0},{"v":41,"t_a":26.0,"t_b":28.0}]],[[{"v":22,"t_a":0.0,"t_b":0.0},{"v":29,"t_a":3.0,"t_b":3.0},{"v":22,"t_a":13.0,"t_b":14.0},{"v":15,"t_a":18.0,"t_b":20.0},{"v":22,"t_a":23.0,"t_b":23.0},{"v":29,"t_a":26.0,"t_b":28.0}],[{"v":16,"t_a":0.0,"t_b":4.0},{"v":9,"t_a":9.0,"t_b":10.0},{"v":16,"t_a":11.0,"t_b":16.0},{"v":15,"t_a":20.0,"t_b":23.0},{"v":22,"t_a":26.0,"t_b":28.0}],[{"v":19,"t_a":0.0,"t_b":0.0},{"v":26,"t_a":6.0,"t_b":6.0},{"v":27,"t_a":8.0,"t_b":8.0},{"v":26,"t_a":12.0,"t_b":12.0},{"v":33,"t_a":14.0,"t_b":16.0},{"v":41,"t_a":22.0,"t_b":22.0},{"v":42,"t_a":24.0,"t_b":28.0}]],[[{"v":22,"t_a":0.0,"t_b":0.0},{"v":15,"t_a":4.0,"t_b":4.0},{"v":8,"t_a":11.0,"t_b":12.0},{"v":15,"t_a":14.0,"t_b":28.0}],[{"v":16,"t_a":0.0,"t_b":1.0},{"v":9,"t_a":6.0,"t_b":7.0},{"v":2,"t_a":13.0,"t_b":13.0},{"v":3,"t_a":21.0,"t_b":24.0},{"v":10,"t_a":28.0,"t_b":28.0}],[{"v":19,"t_a":0.0,"t_b":3.0},{"v":26,"t_a":9.0,"t_b":9.0},{"v":33,"t_a":11.0,"t_b":13.0},{"v":41,"t_a":19.0,"t_b":19.0},{"v":42,"t_a":21.0,"t_b":28.0}]],[[{"v":22,"t_a":0.0,"t_b":0.0},{"v":15,"t_a":4.0,"t_b":6.0},{"v":22,"t_a":9.0,"t_b":13.0},{"v":15,"t_a":17.0,"t_b":18.0},{"v":22,"t_a":21.0,"t_b":22.0},{"v":29,"t_a":25.0,"t_b":28.0}],[{"v":16,"t_a":0.0,"t_b":16.0},{"v":15,"t_a":20.0,"t_b":28.0}],[{"v":19,"t_a":0.0,"t_b":5.0},{"v":26,"t_a":11.0,"t_b":11.0},{"v":33,"t_a":13.0,"t_b":15.0},{"v":41,"t_a":21.0,"t_b":23.0},{"v":47,"t_a":26.0,"t_b":26.0},{"v":46,"t_a":28.0,"t_b":28.0}]],[[{"v":22,"t_a":0.0,"t_b":0.0},{"v":15,"t_a":4.0,"t_b":4.0},{"v":22,"t_a":7.0,"t_b":15.0},{"v":29,"t_a":18.0,"t_b":28.0}],[{"v":16,"t_a":0.0,"t_b":0.0},{"v":9,"t_a":5.0,"t_b":5.0},{"v":2,"t_a":11.0,"t_b":13.0},{"v":3,"t_a":21.0,"t_b":28.0}],[{"v":19,"t_a":0.0,"t_b":2.0},{"v":26,"t_a":8.0,"t_b":9.0},{"v":33,"t_a":11.0,"t_b":13.0},{"v":26,"t_a":15.0,"t_b":16.0},{"v":27,"t_a":18.0,"t_b":20.0},{"v":20,"t_a":21.0,"t_b":21.0},{"v":13,"t_a":28.0,"t_b":28.0}]],[[{"v":22,"t_a":0.0,"t_b":0.0},{"v":15,"t_a":4.0,"t_b":4.0},{"v":8,"t_a":11.0,"t_b":11.0},{"v":1,"t_a":13.0,"t_b":13.0},{"v":2,"t_a":16.0,"t_b":17.0},{"v":1,"t_a":18.0,"t_b":21.0},{"v":8,"t_a":24.0,"t_b":24.0},{"v":1,"t_a":26.0,"t_b":28.0}],[{"v":16,"t_a":0.0,"t_b":1.0},{"v":9,"t_a":6.0,"t_b":6.0},{"v":10,"t_a":14.0,"t_b":14.0},{"v":3,"t_a":20.0,"t_b":28.0}],[{"v":19,"t_a":0.0,"t_b":3.0},{"v":26,"t_a":9.0,"t_b":12.0},{"v":33,"t_a":14.0,"t_b":16.0},{"v":41,"t_a":22.0,"t_b":22.0},{"v":42,"t_a":24.0,"t_b":28.0}]],[[{"v":22,"t_a":0.0,"t_b":3.0},{"v":15,"t_a":7.0,"t_b":8.0},{"v":22,"t_a":11.0,"t_b":16.0},{"v":15,"t_a":20.0,"t_b":23.0},{"v":22,"t_a":26.0,"t_b":28.0}],[{"v":16,"t_a":0.0,"t_b":11.0},{"v":9,"t_a":16.0,"t_b":16.0},{"v":2,"t_a":22.0,"t_b":23.0},{"v":1,"t_a":24.0,"t_b":28.0}],[{"v":19,"t_a":0.0,"t_b":0.0},{"v":26,"t_a":6.0,"t_b":6.0},{"v":27,"t_a":8.0,"t_b":8.0},{"v":20,"t_a":9.0,"t_b":10.0},{"v":27,"t_a":14.0,"t_b":16.0},{"v":35,"t_a":22.0,"t_b":22.0},{"v":42,"t_a":27.0,"t_b":28.0}]],[[{"v":22,"t_a":0.0,"t_b":2.0},{"v":15,"t_a":6.0,"t_b":12.0},{"v":22,"t_a":15.0,"t_b":16.0},{"v":15,"t_a":20.0,"t_b":20.0},{"v":22,"t_a":23.0,"t_b":24.0},{"v":29,"t_a":27.0,"t_b":28.0}],[{"v":16,"t_a":0.0,"t_b":12.0},{"v":9,"t_a":17.0,"t_b":17.0},{"v":2,"t_a":23.0,"t_b":23.0},{"v":1,"t_a":24.0,"t_b":28.0}],[{"v":19,"t_a":0.0,"t_b":3.0},{"v":26,"t_a":9.0,"t_b":9.0},{"v":33,"t_a":11.0,"t_b":16.0},{"v":26,"t_a":18.0,"t_b":18.0},{"v":33,"t_a":20.0,"t_b":20.0},{"v":26,"t_a":22.0,"t_b":23.0},{"v":27,"t_a":25.0,"t_b":25.0},{"v":20,"t_a":26.0,"t_b":28.0}]],[[{"v":22,"t_a":0.0,"t_b":0.0},{"v":29,"t_a":3.0,"t_b":3.0},{"v":37,"t_a":7.0,"t_b":7.0},{"v":29,"t_a":14.0,"t_b":20.0},{"v":37,"t_a":24.0,"t_b":28.0}],[{"v":16,"t_a":0.0,"t_b":15.0},{"v":15,"t_a":19.0,"t_b":28.0}],[{"v":19,"t_a":0.0,"t_b":4.0},{"v":26,"t_a":10.0,"t_b":12.0},{"v":33,"t_a":14.0,"t_b":16.0},{"v":41,"t_a":22.0,"t_b":25.0},{"v":42,"t_a":27.0,"t_b":28.0}]],[[{"v":22,"t_a":0.0,"t_b":0.0},{"v":29,"t_a":3.0,"t_b":3.0},{"v":22,"t_a":13.0,"t_b":22.0},{"v":29,"t_a":25.0,"t_b":28.0}],[{"v":16,"t_a":0.0,"t_b":17.0},{"v":15,"t_a":21.0,"t_b":28.0}],[{"v":19,"t_a":0.0,"t_b":0.0},{"v":12,"t_a":10.0,"t_b":10.0},{"v":11,"t_a":18.0,"t_b":18.0},{"v":12,"t_a":28.0,"t_b":28.0}]],[[{"v":22,"t_a":0.0,"t_b":0.0},{"v":15,"t_a":4.0,"t_b":4.0},{"v":8,"t_a":11.0,"t_b":12.0},{"v":1,"t_a":14.0,"t_b":19.0},{"v":2,"t_a":22.0,"t_b":25.0},{"v":1,"t_a":26.0,"t_b":28.0}],[{"v":16,"t_a":0.0,"t_b":0.0},{"v":9,"t_a":5.0,"t_b":5.0},{"v":2,"t_a":11.0,"t_b":12.0},{"v":3,"t_a":20.0,"t_b":28.0}],[{"v":19,"t_a":0.0,"t_b":0.0},{"v":26,"t_a":6.0,"t_b":6.0},{"v":33,"t_a":8.0,"t_b":8.0},{"v":26,"t_a":10.0,"t_b":11.0},{"v":33,"t_a":13.0,"t_b":17.0},{"v":41,"t_a":23.0,"t_b":25.0},{"v":42,"t_a":27.0,"t_b":28.0}]],[[{"v":22,"t_a":0.0,"t_b":5.0},{"v":15,"t_a":9.0,"t_b":15.0},{"v":22,"t_a":18.0,"t_b":20.0},{"v":29,"t_a":23.0,"t_b":28.0}],[{"v":16,"t_a":0.0,"t_b":0.0},{"v":9,"t_a":5.0,"t_b":5.0},{"v":10,"t_a":13.0,"t_b":15.0},{"v":3,"t_a":21.0,"t_b":28.0}],[{"v":19,"t_a":0.0,"t_b":2.0},{"v":26,"t_a":8.0,"t_b":10.0},{"v":33,"t_a":12.0,"t_b":14.0},{"v":41,"t_a":20.0,"t_b":20.0},{"v":42,"t_a":22.0,"t_b":28.0}]],[[{"v":22,"t_a":0.0,"t_b":3.0},{"v":15,"t_a":7.0,"t_b":7.0},{"v":22,"t_a":10.0,"t_b":23.0},{"v":15,"t_a":27.0,"t_b":28.0}],[{"v":16,"t_a":0.0,"t_b":0.0},{"v":9,"t_a":5.0,"t_b":5.0},{"v":10,"t_a":13.0,"t_b":15.0},{"v":3,"t_a":21.0,"t_b":28.0}],[{"v":19,"t_a":0.0,"t_b":1.0},{"v":26,"t_a":7.0,"t_b":9.0},{"v":33,"t_a":11.0,"t_b":16.0},{"v":41,"t_a":22.0,"t_b":22.0},{"v":42,"t_a":24.0,"t_b":28.0}]],[[{"v":22,"t_a":0.0,"t_b":0.0},{"v":15,"t_a":4.0,"t_b":4.0},{"v":8,"t_a":11.0,"t_b":11.0},{"v":1,"t_a":13.0,"t_b":14.0},{"v":2,"t_a":17.0,"t_b":19.0},{"v":1,"t_a":20.0,"t_b":20.0},{"v":2,"t_a":23.0,"t_b":23.0},{"v":1,"t_a":24.0,"t_b":28.0}],[{"v":16,"t_a":0.0,"t_b":3.0},{"v":9,"t_a":8.0,"t_b":8.0},{"v":10,"t_a":16.0,"t_b":17.0},{"v":3,"t_a":23.0,"t_b":24.0},{"v":10,"t_a":28.0,"t_b":28.0}],[{"v":19,"t_a":0.0,"t_b":1.0},{"v":26,"t_a":7.0,"t_b":8.0},{"v":27,"t_a":10.0,"t_b":11.0},{"v":26,"t_a":15.0,"t_b":18.0},{"v":27,"t_a":20.0,"t_b":20.0},{"v":20,"t_a":21.0,"t_b":21.0},{"v":27,"t_a":25.0,"t_b":25.0},{"v":20,"t_a":26.0,"t_b":28.0}]],[[{"v":22,"t_a":0.0,"t_b":0.0},{"v":15,"t_a":4.0,"t_b":8.0},{"v":8,"t_a":15.0,"t_b":15.0},{"v":1,"t_a":17.0,"t_b":28.0}],[{"v":16,"t_a":0.0,"t_b":1.0},{"v":9,"t_a":6.0,"t_b":6.0},{"v":2,"t_a":12.0,"t_b":13.0},{"v":3,"t_a":21.0,"t_b":28.0}],[{"v":19,"t_a":0.0,"t_b":4.0},{"v":26,"t_a":10.0,"t_b":10.0},{"v":33,"t_a":12.0,"t_b":15.0},{"v":32,"t_a":20.0,"t_b":21.0},{"v":33,"t_a":27.0,"t_b":28.0}]],[[{"v":22,"t_a":0.0,"t_b":0.0},{"v":15,"t_a":4.0,"t_b":4.0},{"v":8,"t_a":11.0,"t_b":11.0},{"v":1,"t_a":13.0,"t_b":13.0},{"v":2,"t_a":16.0,"t_b":16.0},{"v":3,"t_a":24.0,"t_b":28.0}],[{"v":16,"t_a":0.0,"t_b":3.0},{"v":9,"t_a":8.0,"t_b":11.0},{"v":16,"t_a":12.0,"t_b":23.0},{"v":9,"t_a":28.0,"t_b":28.0}],[{"v":19,"t_a":0.0,"t_b":3.0},{"v":26,"t_a":9.0,"t_b":10.0},{"v":33,"t_a":12.0,"t_b":14.0},{"v":41,"t_a":20.0,"t_b":21.0},{"v":42,"t_a":23.0,"t_b":28.0}]],[[{"v":22,"t_a":0.0,"t_b":0.0},{"v":15,"t_a":4.0,"t_b":8.0},{"v":22,"t_a":11.0,"t_b":18.0},{"v":15,"t_a":22.0,"t_b":28.0}],[{"v":16,"t_a":0.0,"t_b":2.0},{"v":9,"t_a":7.0,"t_b":7.0},{"v":2,"t_a":13.0,"t_b":13.0},{"v":3,"t_a":21.0,"t_b":28.0}],[{"v":19,"t_a":0.0,"t_b":0.0},{"v":26,"t_a":6.0,"t_b":6.0},{"v":33,"t_a":8.0,"t_b":8.0},{"v":26,"t_a":10.0,"t_b":10.0},{"v":33,"t_a":12.0,"t_b":15.0},{"v":41,"t_a":21.0,"t_b":24.0},{"v":40,"t_a":25.0,"t_b":28.0}]],[[{"v":22,"t_a":0.0,"t_b":3.0},{"v":15,"t_a":7.0,"t_b":10.0},{"v":16,"t_a":19.0,"t_b":20.0},{"v":9,"t_a":25.0,"t_b":26.0},{"v":16,"t_a":27.0,"t_b":28.0}],[{"v":16,"t_a":0.0,"t_b":2.0},{"v":9,"t_a":7.0,"t_b":8.0},{"v":10,"t_a":16.0,"t_b":17.0},{"v":3,"t_a":23.0,"t_b":28.0}],[{"v":19,"t_a":0.0,"t_b":4.0},{"v":26,"t_a":10.0,"t_b":10.0},{"v":33,"t_a":12.0,"t_b":15.0},{"v":26,"t_a":17.0,"t_b":17.0},{"v":19,"t_a":20.0,"t_b":20.0},{"v":26,"t_a":26.0,"t_b":26.0},{"v":27,"t_a":28.0,"t_b":28.0}]],[[{"v":22,"t_a":0.0,"t_b":0.0},{"v":15,"t_a":4.0,"t_b":9.0},{"v":8,"t_a":16.0,"t_b":16.0},{"v":15,"t_a":18.0,"t_b":18.0},{"v":8,"t_a":25.0,"t_b":25.0},{"v":1,"t_a":27.0,"t_b":28.0}],[{"v":16,"t_a":0.0,"t_b":2.0},{"v":9,"t_a":7.0,"t_b":7.0},{"v":10,"t_a":15.0,"t_b":15.0},{"v":3,"t_a":21.0,"t_b":28.0}],[{"v":19,"t_a":0.0,"t_b":0.0},{"v":26,"t_a":6.0,"t_b":6.0},{"v":33,"t_a":8.0,"t_b":8.0},{"v":26,"t_a":10.0,"t_b":10.0},{"v":33,"t_a":12.0,"t_b":12.0},{"v":41,"t_a":18.0,"t_b":19.0},{"v":42,"t_a":21.0,"t_b":28.0}]],[[{"v":22,"t_a":0.0,"t_b":0.0},{"v":15,"t_a":4.0,"t_b":4.0},{"v":8,"t_a":11.0,"t_b":12.0},{"v":1,"t_a":14.0,"t_b":15.0},{"v":2,"t_a":18.0,"t_b":18.0},{"v":3,"t_a":26.0,"t_b":28.0}],[{"v":16,"t_a":0.0,"t_b":19.0},{"v":15,"t_a":23.0,"t_b":28.0}],[{"v":19,"t_a":0.0,"t_b":2.0},{"v":26,"t_a":8.0,"t_b":8.0},{"v":33,"t_a":10.0,"t_b":17.0},{"v":26,"t_a":19.0,"t_b":19.0},{"v":27,"t_a":21.0,"t_b":21.0},{"v":20,"t_a":22.0,"t_b":24.0},{"v":27,"t_a":28.0,"t_b":28.0}]],[[{"v":22,"t_a":0.0,"t_b":0.0},{"v":15,"t_a":4.0,"t_b":4.0},{"v":8,"t_a":11.0,"t_b":11.0},{"v":1,"t_a":13.0,"t_b":13.0},{"v":2,"t_a":16.0,"t_b":16.0},{"v":3,"t_a":24.0,"t_b":28.0}],[{"v":16,"t_a":0.0,"t_b":20.0},{"v":9,"t_a":25.0,"t_b":26.0},{"v":16,"t_a":27.0,"t_b":28.0}],[{"v":19,"t_a":0.0,"t_b":0.0},{"v":26,"t_a":6.0,"t_b":6.0},{"v":33,"t_a":8.0,"t_b":13.0},{"v":41,"t_a":19.0,"t_b":19.0},{"v":42,"t_a":21.0,"t_b":28.0}]],[[{"v":22,"t_a":0.0,"t_b":0.0},{"v":15,"t_a":4.0,"t_b":9.0},{"v":22,"t_a":12.0,"t_b":15.0},{"v":15,"t_a":19.0,"t_b":20.0},{"v":22,"t_a":23.0,"t_b":25.0},{"v":29,"t_a":28.0,"t_b":28.0}],[{"v":16,"t_a":0.0,"t_b":0.0},{"v":9,"t_a":5.0,"t_b":5.0},{"v":2,"t_a":11.0,"t_b":13.0},{"v":3,"t_a":21.0,"t_b":28.0}],[{"v":19,"t_a":0.0,"t_b":9.0},{"v":26,"t_a":15.0,"t_b":15.0},{"v":33,"t_a":17.0,"t_b":17.0},{"v":41,"t_a":23.0,"t_b":23.0},{"v":42,"t_a":25.0,"t_b":28.0}]],[[{"v":22,"t_a":0.0,"t_b":0.0},{"v":15,"t_a":4.0,"t_b":4.0},{"v":8,"t_a":11.0,"t_b":13.0},{"v":1,"t_a":15.0,"t_b":18.0},{"v":2,"t_a":21.0,"t_b":21.0},{"v":1,"t_a":22.0,"t_b":28.0}],[{"v":16,"t_a":0.0,"t_b":0.0},{"v":9,"t_a":5.0,"t_b":6.0},{"v":2,"t_a":12.0,"t_b":13.0},{"v":3,"t_a":21.0,"t_b":28.0}],[{"v":19,"t_a":0.0,"t_b":0.0},{"v":26,"t_a":6.0,"t_b":6.0},{"v":27,"t_a":8.0,"t_b":8.0},{"v":35,"t_a":14.0,"t_b":16.0},{"v":42,"t_a":21.0,"t_b":28.0}]],[[{"v":22,"t_a":0.0,"t_b":0.0},{"v":15,"t_a":4.0,"t_b":7.0},{"v":8,"t_a":14.0,"t_b":14.0},{"v":1,"t_a":16.0,"t_b":20.0},{"v":8,"t_a":23.0,"t_b":24.0},{"v":15,"t_a":26.0,"t_b":28.0}],[{"v":16,"t_a":0.0,"t_b":0.0},{"v":9,"t_a":5.0,"t_b":5.0},{"v":10,"t_a":13.0,"t_b":15.0},{"v":3,"t_a":21.0,"t_b":28.0}],[{"v":19,"t_a":0.0,"t_b":2.0},{"v":26,"t_a":8.0,"t_b":10.0},{"v":33,"t_a":12.0,"t_b":19.0},{"v":41,"t_a":25.0,"t_b":28.0}]],[[{"v":22,"t_a":0.0,"t_b":4.0},{"v":15,"t_a":8.0,"t_b":9.0},{"v":22,"t_a":12.0,"t_b":17.0},{"v":15,"t_a":21.0,"t_b":28.0}],[{"v":16,"t_a":0.0,"t_b":1.0},{"v":9,"t_a":6.0,"t_b":7.0},{"v":2,"t_a":13.0,"t_b":13.0},{"v":3,"t_a":21.0,"t_b":28.0}],[{"v":19,"t_a":0.0,"t_b":3.0},{"v":26,"t_a":9.0,"t_b":10.0},{"v":33,"t_a":12.0,"t_b":13.0},{"v":26,"t_a":15.0,"t_b":15.0},{"v":33,"t_a":17.0,"t_b":17.0},{"v":41,"t_a":23.0,"t_b":23.0},{"v":42,"t_a":25.0,"t_b":28.0}]],[[{"v":22,"t_a":0.0,"t_b":0.0},{"v":15,"t_a":4.0,"t_b":5.0},{"v":22,"t_a":8.0,"t_b":8.0},{"v":15,"t_a":12.0,"t_b":16.0},{"v":22,"t_a":19.0,"t_b":19.0},{"v":29,"t_a":22.0,"t_b":28.0}],[{"v":16,"t_a":0.0,"t_b":3.0},{"v":9,"t_a":8.0,"t_b":9.0},{"v":2,"t_a":15.0,"t_b":15.0},{"v":3,"t_a":23.0,"t_b":28.0}],[{"v":19,"t_a":0.0,"t_b":5.0},{"v":26,"t_a":11.0,"t_b":11.0},{"v":33,"t_a":13.0,"t_b":16.0},{"v":26,"t_a":18.0,"t_b":19.0},{"v":27,"t_a":21.0,"t_b":25.0},{"v":20,"t_a":26.0,"t_b":28.0}]],[[{"v":22,"t_a":0.0,"t_b":3.0},{"v":15,"t_a":7.0,"t_b":9.0},{"v":22,"t_a":12.0,"t_b":12.0},{"v":29,"t_a":15.0,"t_b":28.0}],[{"v":16,"t_a":0.0,"t_b":12.0},{"v":9,"t_a":17.0,"t_b":17.0},{"v":16,"t_a":18.0,"t_b":19.0},{"v":15,"t_a":23.0,"t_b":28.0}],[{"v":19,"t_a":0.0,"t_b":0.0},{"v":26,"t_a":6.0,"t_b":6.0},{"v":27,"t_a":8.0,"t_b":8.0},{"v":35,"t_a":14.0,"t_b":15.0},{"v":41,"t_a":18.0,"t_b":23.0},{"v":42,"t_a":25.0,"t_b":28.0}]],[[{"v":22,"t_a":0.0,"t_b":0.0},{"v":15,"t_a":4.0,"t_b":23.0},{"v":22,"t_a":26.0,"t_b":28.0}],[{"v":16,"t_a":0.0,"t_b":1.0},{"v":9,"t_a":6.0,"t_b":6.0},{"v":2,"t_a":12.0,"t_b":13.0},{"v":3,"t_a":21.0,"t_b":28.0}],[{"v":19,"t_a":0.0,"t_b":0.0},{"v":26,"t_a":6.0,"t_b":6.0},{"v":33,"t_a":8.0,"t_b":8.0},{"v":25,"t_a":13.0,"t_b":14.0},{"v":33,"t_a":18.0,"t_b":18.0},{"v":26,"t_a":20.0,"t_b":20.0},{"v":33,"t_a":22.0,"t_b":23.0},{"v":26,"t_a":25.0,"t_b":28.0}]],[[{"v":22,"t_a":0.0,"t_b":0.0},{"v":15,"t_a":4.0,"t_b":9.0},{"v":22,"t_a":12.0,"t_b":16.0},{"v":15,"t_a":20.0,"t_b":21.0},{"v":22,"t_a":24.0,"t_b":24.0},{"v":29,"t_a":27.0,"t_b":28.0}],[{"v":16,"t_a":0.0,"t_b":4.0},{"v":9,"t_a":9.0,"t_b":9.0},{"v":2,"t_a":15.0,"t_b":15.0},{"v":3,"t_a":23.0,"t_b":28.0}],[{"v":19,"t_a":0.0,"t_b":0.0},{"v":26,"t_a":6.0,"t_b":6.0},{"v":33,"t_a":8.0,"t_b":8.0},{"v":26,"t_a":10.0,"t_b":10.0},{"v":33,"t_a":12.0,"t_b":13.0},{"v":41,"t_a":19.0,"t_b":25.0},{"v":42,"t_a":27.0,"t_b":28.0}]],[[{"v":22,"t_a":0.0,"t_b":0.0},{"v":15,"t_a":4.0,"t_b":4.0},{"v":8,"t_a":11.0,"t_b":14.0},{"v":1,"t_a":16.0,"t_b":17.0},{"v":2,"t_a":20.0,"t_b":21.0},{"v":1,"t_a":22.0,"t_b":22.0},{"v":2,"t_a":25.0,"t_b":26.0},{"v":1,"t_a":27.0,"t_b":28.0}],[{"v":16,"t_a":0.0,"t_b":0.0},{"v":9,"t_a":5.0,"t_b":7.0},{"v":10,"t_a":15.0,"t_b":15.0},{"v":3,"t_a":21.0,"t_b":28.0}],[{"v":19,"t_a":0.0,"t_b":3.0},{"v":26,"t_a":9.0,"t_b":10.0},{"v":33,"t_a":12.0,"t_b":13.0},{"v":26,"t_a":15.0,"t_b":15.0},{"v":33,"t_a":17.0,"t_b":17.0},{"v":41,"t_a":23.0,"t_b":26.0},{"v":42,"t_a":28.0,"t_b":28.0}]],[[{"v":22,"t_a":0.0,"t_b":0.0},{"v":15,"t_a":4.0,"t_b":6.0},{"v":8,"t_a":13.0,"t_b":13.0},{"v":1,"t_a":15.0,"t_b":22.0},{"v":8,"t_a":25.0,"t_b":26.0},{"v":15,"t_a":28.0,"t_b":28.0}],[{"v":16,"t_a":0.0,"t_b":0.0},{"v":9,"t_a":5.0,"t_b":6.0},{"v":2,"t_a":12.0,"t_b":13.0},{"v":3,"t_a":21.0,"t_b":28.0}],[{"v":19,"t_a":0.0,"t_b":0.0},{"v":26,"t_a":6.0,"t_b":6.0},{"v":33,"t_a":8.0,"t_b":8.0},{"v":26,"t_a":10.0,"t_b":10.0},{"v":33,"t_a":12.0,"t_b":12.0},{"v":41,"t_a":18.0,"t_b":20.0},{"v":42,"t_a":22.0,"t_b":28.0}]],[[{"v":22,"t_a":0.0,"t_b":0.0},{"v":15,"t_a":4.0,"t_b":8.0},{"v":22,"t_a":11.0,"t_b":28.0}],[{"v":16,"t_a":0.0,"t_b":21.0},{"v":15,"t_a":25.0,"t_b":28.0}],[{"v":19,"t_a":0.0,"t_b":4.0},{"v":26,"t_a":10.0,"t_b":10.0},{"v":33,"t_a":12.0,"t_b":19.0},{"v":41,"t_a":25.0,"t_b":26.0},{"v":40,"t_a":27.0,"t_b":28.0}]],[[{"v":22,"t_a":0.0,"t_b":0.0},{"v":15,"t_a":4.0,"t_b":4.0},{"v":8,"t_a":11.0,"t_b":12.0},{"v":15,"t_a":14.0,"t_b":18.0},{"v":22,"t_a":21.0,"t_b":21.0},{"v":29,"t_a":24.0,"t_b":28.0}],[{"v":16,"t_a":0.0,"t_b":2.0},{"v":9,"t_a":7.0,"t_b":7.0},{"v":2,"t_a":13.0,"t_b":13.0},{"v":3,"t_a":21.0,"t_b":28.0}],[{"v":19,"t_a":0.0,"t_b":0.0},{"v":26,"t_a":6.0,"t_b":8.0},{"v":33,"t_a":10.0,"t_b":10.0},{"v":26,"t_a":12.0,"t_b":14.0},{"v":33,"t_a":16.0,"t_b":16.0},{"v":34,"t_a":25.0,"t_b":28.0}]],[[{"v":22,"t_a":0.0,"t_b":2.0},{"v":29,"t_a":5.0,"t_b":5.0},{"v":22,"t_a":15.0,"t_b":21.0},{"v":15,"t_a":25.0,"t_b":28.0}],[{"v":16,"t_a":0.0,"t_b":2.0},{"v":9,"t_a":7.0,"t_b":7.0},{"v":2,"t_a":13.0,"t_b":13.0},{"v":3,"t_a":21.0,"t_b":28.0}],[{"v":19,"t_a":0.0,"t_b":4.0},{"v":26,"t_a":10.0,"t_b":10.0},{"v":27,"t_a":12.0,"t_b":12.0},{"v":26,"t_a":16.0,"t_b":16.0},{"v":33,"t_a":18.0,"t_b":20.0},{"v":26,"t_a":22.0,"t_b":23.0},{"v":27,"t_a":25.0,"t_b":26.0},{"v":20,"t_a":27.0,"t_b":28.0}]],[[{"v":22,"t_a":0.0,"t_b":0.0},{"v":23,"t_a":9.0,"t_b":10.0},{"v":17,"t_a":13.0,"t_b":13.0},{"v":16,"t_a":16.0,"t_b":16.0},{"v":15,"t_a":20.0,"t_b":28.0}],[{"v":16,"t_a":0.0,"t_b":1.0},{"v":9,"t_a":6.0,"t_b":7.0},{"v":10,"t_a":15.0,"t_b":15.0},{"v":3,"t_a":21.0,"t_b":28.0}],[{"v":19,"t_a":0.0,"t_b":1.0},{"v":26,"t_a":7.0,"t_b":16.0},{"v":33,"t_a":18.0,"t_b":18.0},{"v":26,"t_a":20.0,"t_b":20.0},{"v":33,"t_a":22.0,"t_b":22.0},{"v":25,"t_a":27.0,"t_b":28.0}]],[[{"v":22,"t_a":0.0,"t_b":0.0},{"v":15,"t_a":4.0,"t_b":21.0},{"v":22,"t_a":24.0,"t_b":25.0},{"v":29,"t_a":28.0,"t_b":28.0}],[{"v":16,"t_a":0.0,"t_b":3.0},{"v":9,"t_a":8.0,"t_b":8.0},{"v":2,"t_a":14.0,"t_b":14.0},{"v":3,"t_a":22.0,"t_b":28.0}],[{"v":19,"t_a":0.0,"t_b":0.0},{"v":26,"t_a":6.0,"t_b":8.0},{"v":33,"t_a":10.0,"t_b":12.0},{"v":26,"t_a":14.0,"t_b":18.0},{"v":27,"t_a":20.0,"t_b":21.0},{"v":35,"t_a":27.0,"t_b":27.0},{"v":28,"t_a":28.0,"t_b":28.0}]],[[{"v":22,"t_a":0.0,"t_b":3.0},{"v":15,"t_a":7.0,"t_b":21.0},{"v":22,"t_a":24.0,"t_b":28.0}],[{"v":16,"t_a":0.0,"t_b":0.0},{"v":9,"t_a":5.0,"t_b":5.0},{"v":2,"t_a":11.0,"t_b":11.0},{"v":3,"t_a":19.0,"t_b":28.0}],[{"v":19,"t_a":0.0,"t_b":0.0},{"v":26,"t_a":6.0,"t_b":6.0},{"v":27,"t_a":8.0,"t_b":8.0},{"v":35,"t_a":14.0,"t_b":15.0},{"v":27,"t_a":18.0,"t_b":18.0},{"v":35,"t_a":24.0,"t_b":26.0},{"v":28,"t_a":27.0,"t_b":28.0}]],[[{"v":22,"t_a":0.0,"t_b":0.0},{"v":15,"t_a":4.0,"t_b":4.0},{"v":8,"t_a":11.0,"t_b":12.0},{"v":15,"t_a":14.0,"t_b":16.0},{"v":22,"t_a":19.0,"t_b":19.0},{"v":15,"t_a":23.0,"t_b":28.0}],[{"v":16,"t_a":0.0,"t_b":0.0},{"v":9,"t_a":5.0,"t_b":5.0},{"v":2,"t_a":11.0,"t_b":12.0},{"v":3,"t_a":20.0,"t_b":28.0}],[{"v":19,"t_a":0.0,"t_b":3.0},{"v":26,"t_a":9.0,"t_b":9.0},{"v":33,"t_a":11.0,"t_b":11.0},{"v":26,"t_a":13.0,"t_b":14.0},{"v":33,"t_a":16.0,"t_b":16.0},{"v":26,"t_a":18.0,"t_b":19.0},{"v":33,"t_a":21.0,"t_b":22.0},{"v":26,"t_a":24.0,"t_b":24.0},{"v":19,"t_a":27.0,"t_b":28.0}]],[[{"v":22,"t_a":0.0,"t_b":0.0},{"v":15,"t_a":4.0,"t_b":12.0},{"v":22,"t_a":15.0,"t_b":24.0},{"v":15,"t_a":28.0,"t_b":28.0}],[{"v":16,"t_a":0.0,"t_b":0.0},{"v":9,"t_a":5.0,"t_b":6.0},{"v":10,"t_a":14.0,"t_b":15.0},{"v":3,"t_a":21.0,"t_b":28.0}],[{"v":19,"t_a":0.0,"t_b":0.0},{"v":26,"t_a":6.0,"t_b":6.0},{"v":33,"t_a":8.0,"t_b":8.0},{"v":41,"t_a":14.0,"t_b":14.0},{"v":33,"t_a":18.0,"t_b":19.0},{"v":25,"t_a":24.0,"t_b":24.0},{"v":32,"t_a":26.0,"t_b":28.0}]],[[{"v":22,"t_a":0.0,"t_b":0.0},{"v":15,"t_a":4.0,"t_b":4.0},{"v":16,"t_a":13.0,"t_b":20.0},{"v":15,"t_a":24.0,"t_b":25.0},{"v":22,"t_a":28.0,"t_b":28.0}],[{"v":16,"t_a":0.0,"t_b":3.0},{"v":9,"t_a":8.0,"t_b":8.0},{"v":2,"t_a":14.0,"t_b":15.0},{"v":3,"t_a":23.0,"t_b":28.0}],[{"v":19,"t_a":0.0,"t_b":0.0},{"v":26,"t_a":6.0,"t_b":6.0},{"v":33,"t_a":8.0,"t_b":8.0},{"v":26,"t_a":10.0,"t_b":11.0},{"v":33,"t_a":13.0,"t_b":13.0},{"v":26,"t_a":15.0,"t_b":18.0},{"v":27,"t_a":20.0,"t_b":20.0},{"v":34,"t_a":28.0,"t_b":28.0}]],[[{"v":22,"t_a":0.0,"t_b":0.0},{"v":15,"t_a":4.0,"t_b":4.0},{"v":16,"t_a":13.0,"t_b":20.0},{"v":15,"t_a":24.0,"t_b":25.0},{"v":22,"t_a":28.0,"t_b":28.0}],[{"v":16,"t_a":0.0,"t_b":3.0},{"v":9,"t_a":8.0,"t_b":8.0},{"v":2,"t_a":14.0,"t_b":14.0},{"v":3,"t_a":22.0,"t_b":28.0}],[{"v":19,"t_a":0.0,"t_b":3.0},{"v":26,"t_a":9.0,"t_b":16.0},{"v":19,"t_a":19.0,"t_b":19.0},{"v":26,"t_a":25.0,"t_b":25.0},{"v":33,"t_a":27.0,"t_b":28.0}]],[[{"v":22,"t_a":0.0,"t_b":0.0},{"v":15,"t_a":4.0,"t_b":4.0},{"v":16,"t_a":13.0,"t_b":24.0},{"v":15,"t_a":28.0,"t_b":28.0}],[{"v":16,"t_a":0.0,"t_b":0.0},{"v":9,"t_a":5.0,"t_b":5.0},{"v":10,"t_a":13.0,"t_b":14.0},{"v":3,"t_a":20.0,"t_b":28.0}],[{"v":19,"t_a":0.0,"t_b":0.0},{"v":12,"t_a":10.0,"t_b":10.0},{"v":11,"t_a":18.0,"t_b":20.0},{"v":18,"t_a":22.0,"t_b":24.0},{"v":11,"t_a":27.0,"t_b":28.0}]],[[{"v":22,"t_a":0.0,"t_b":0.0},{"v":15,"t_a":4.0,"t_b":28.0}],[{"v":16,"t_a":0.0,"t_b":1.0},{"v":9,"t_a":6.0,"t_b":7.0},{"v":10,"t_a":15.0,"t_b":16.0},{"v":3,"t_a":22.0,"t_b":28.0}],[{"v":19,"t_a":0.0,"t_b":9.0},{"v":26,"t_a":15.0,"t_b":18.0},{"v":19,"t_a":21.0,"t_b":22.0},{"v":26,"t_a":28.0,"t_b":28.0}]],[[{"v":22,"t_a":0.0,"t_b":0.0},{"v":15,"t_a":4.0,"t_b":4.0},{"v":16,"t_a":13.0,"t_b":14.0},{"v":15,"t_a":18.0,"t_b":20.0},{"v":22,"t_a":23.0,"t_b":24.0},{"v":15,"t_a":28.0,"t_b":28.0}],[{"v":16,"t_a":0.0,"t_b":0.0},{"v":9,"t_a":5.0,"t_b":5.0},{"v":2,"t_a":11.0,"t_b":13.0},{"v":3,"t_a":21.0,"t_b":28.0}],[{"v":19,"t_a":0.0,"t_b":0.0},{"v":26,"t_a":6.0,"t_b":6.0},{"v":27,"t_a":8.0,"t_b":10.0},{"v":26,"t_a":14.0,"t_b":15.0},{"v":19,"t_a":18.0,"t_b":18.0},{"v":26,"t_a":24.0,"t_b":24.0},{"v":33,"t_a":26.0,"t_b":26.0},{"v":26,"t_a":28.0,"t_b":28.0}]],[[{"v":22,"t_a":0.0,"t_b":4.0},{"v":29,"t_a":7.0,"t_b":8.0},{"v":22,"t_a":18.0,"t_b":20.0},{"v":15,"t_a":24.0,"t_b":25.0},{"v":22,"t_a":28.0,"t_b":28.0}],[{"v":16,"t_a":0.0,"t_b":6.0},{"v":9,"t_a":11.0,"t_b":11.0},{"v":10,"t_a":19.0,"t_b":19.0},{"v":3,"t_a":25.0,"t_b":28.0}],[{"v":19,"t_a":0.0,"t_b":0.0},{"v":26,"t_a":6.0,"t_b":7.0},{"v":33,"t_a":9.0,"t_b":11.0},{"v":26,"t_a":13.0,"t_b":16.0},{"v":19,"t_a":19.0,"t_b":19.0},{"v":26,"t_a":25.0,"t_b":26.0},{"v":27,"t_a":28.0,"t_b":28.0}]],[[{"v":22,"t_a":0.0,"t_b":0.0},{"v":15,"t_a":4.0,"t_b":4.0},{"v":8,"t_a":11.0,"t_b":11.0},{"v":15,"t_a":13.0,"t_b":15.0},{"v":22,"t_a":18.0,"t_b":20.0},{"v":15,"t_a":24.0,"t_b":25.0},{"v":22,"t_a":28.0,"t_b":28.0}],[{"v":16,"t_a":0.0,"t_b":2.0},{"v":9,"t_a":7.0,"t_b":7.0},{"v":2,"t_a":13.0,"t_b":13.0},{"v":3,"t_a":21.0,"t_b":28.0}],[{"v":19,"t_a":0.0,"t_b":0.0},{"v":26,"t_a":6.0,"t_b":6.0},{"v":33,"t_a":8.0,"t_b":8.0},{"v":25,"t_a":13.0,"t_b":13.0},{"v":33,"t_a":17.0,"t_b":18.0},{"v":25,"t_a":23.0,"t_b":23.0},{"v":33,"t_a":27.0,"t_b":28.0}]],[[{"v":22,"t_a":0.0,"t_b":0.0},{"v":15,"t_a":4.0,"t_b":4.0},{"v":8,"t_a":11.0,"t_b":12.0},{"v":1,"t_a":14.0,"t_b":19.0},{"v":8,"t_a":22.0,"t_b":22.0},{"v":15,"t_a":24.0,"t_b":28.0}],[{"v":16,"t_a":0.0,"t_b":0.0},{"v":9,"t_a":5.0,"t_b":5.0},{"v":10,"t_a":13.0,"t_b":15.0},{"v":3,"t_a":21.0,"t_b":28.0}],[{"v":19,"t_a":0.0,"t_b":1.0},{"v":26,"t_a":7.0,"t_b":9.0},{"v":33,"t_a":11.0,"t_b":12.0},{"v":26,"t_a":14.0,"t_b":16.0},{"v":33,"t_a":18.0,"t_b":18.0},{"v":32,"t_a":23.0,"t_b":24.0},{"v":25,"t_a":26.0,"t_b":28.0}]],[[{"v":22,"t_a":0.0,"t_b":0.0},{"v":15,"t_a":4.0,"t_b":4.0},{"v":8,"t_a":11.0,"t_b":12.0},{"v":15,"t_a":14.0,"t_b":28.0}],[{"v":16,"t_a":0.0,"t_b":0.0},{"v":9,"t_a":5.0,"t_b":5.0},{"v":2,"t_a":11.0,"t_b":13.0},{"v":3,"t_a":21.0,"t_b":28.0}],[{"v":19,"t_a":0.0,"t_b":2.0},{"v":26,"t_a":8.0,"t_b":8.0},{"v":33,"t_a":10.0,"t_b":11.0},{"v":26,"t_a":13.0,"t_b":14.0},{"v":33,"t_a":16.0,"t_b":18.0},{"v":26,"t_a":20.0,"t_b":20.0},{"v":27,"t_a":22.0,"t_b":27.0},{"v":20,"t_a":28.0,"t_b":28.0}]],[[{"v":22,"t_a":0.0,"t_b":3.0},{"v":15,"t_a":7.0,"t_b":14.0},{"v":22,"t_a":17.0,"t_b":28.0}],[{"v":16,"t_a":0.0,"t_b":0.0},{"v":9,"t_a":5.0,"t_b":5.0},{"v":10,"t_a":13.0,"t_b":15.0},{"v":3,"t_a":21.0,"t_b":28.0}],[{"v":19,"t_a":0.0,"t_b":5.0},{"v":26,"t_a":11.0,"t_b":11.0},{"v":33,"t_a":13.0,"t_b":13.0},{"v":26,"t_a":15.0,"t_b":16.0},{"v":27,"t_a":18.0,"t_b":18.0},{"v":35,"t_a":24.0,"t_b":24.0},{"v":41,"t_a":27.0,"t_b":28.0}]],[[{"v":22,"t_a":0.0,"t_b":6.0},{"v":15,"t_a":10.0,"t_b":20.0},{"v":22,"t_a":23.0,"t_b":24.0},{"v":29,"t_a":27.0,"t_b":28.0}],[{"v":16,"t_a":0.0,"t_b":0.0},{"v":9,"t_a":5.0,"t_b":6.0},{"v":10,"t_a":14.0,"t_b":15.0},{"v":3,"t_a":21.0,"t_b":28.0}],[{"v":19,"t_a":0.0,"t_b":7.0},{"v":26,"t_a":13.0,"t_b":16.0},{"v":33,"t_a":18.0,"t_b":18.0},{"v":41,"t_a":24.0,"t_b":28.0}]],[[{"v":22,"t_a":0.0,"t_b":4.0},{"v":15,"t_a":8.0,"t_b":13.0},{"v":22,"t_a":16.0,"t_b":19.0},{"v":15,"t_a":23.0,"t_b":24.0},{"v":22,"t_a":27.0,"t_b":28.0}],[{"v":16,"t_a":0.0,"t_b":2.0},{"v":9,"t_a":7.0,"t_b":7.0},{"v":2,"t_a":13.0,"t_b":13.0},{"v":3,"t_a":21.0,"t_b":24.0},{"v":10,"t_a":28.0,"t_b":28.0}],[{"v":19,"t_a":0.0,"t_b":3.0},{"v":26,"t_a":9.0,"t_b":11.0},{"v":33,"t_a":13.0,"t_b":13.0},{"v":26,"t_a":15.0,"t_b":17.0},{"v":33,"t_a":19.0,"t_b":19.0},{"v":32,"t_a":24.0,"t_b":24.0},{"v":25,"t_a":26.0,"t_b":26.0},{"v":32,"t_a":28.0,"t_b":28.0}]],[[{"v":22,"t_a":0.0,"t_b":0.0},{"v":15,"t_a":4.0,"t_b":4.0},{"v":8,"t_a":11.0,"t_b":12.0},{"v":1,"t_a":14.0,"t_b":28.0}],[{"v":16,"t_a":0.0,"t_b":1.0},{"v":9,"t_a":6.0,"t_b":6.0},{"v":10,"t_a":14.0,"t_b":15.0},{"v":3,"t_a":21.0,"t_b":28.0}],[{"v":19,"t_a":0.0,"t_b":0.0},{"v":26,"t_a":6.0,"t_b":7.0},{"v":33,"t_a":9.0,"t_b":10.0},{"v":26,"t_a":12.0,"t_b":16.0},{"v":27,"t_a":18.0,"t_b":22.0},{"v":35,"t_a":28.0,"t_b":28.0}]],[[{"v":22,"t_a":0.0,"t_b":0.0},{"v":15,"t_a":4.0,"t_b":21.0},{"v":22,"t_a":24.0,"t_b":24.0},{"v":29,"t_a":27.0,"t_b":28.0}],[{"v":16,"t_a":0.0,"t_b":0.0},{"v":9,"t_a":5.0,"t_b":6.0},{"v":2,"t_a":12.0,"t_b":12.0},{"v":3,"t_a":20.0,"t_b":28.0}],[{"v":19,"t_a":0.0,"t_b":4.0},{"v":26,"t_a":10.0,"t_b":11.0},{"v":33,"t_a":13.0,"t_b":14.0},{"v":26,"t_a":16.0,"t_b":16.0},{"v":33,"t_a":18.0,"t_b":18.0},{"v":41,"t_a":24.0,"t_b":25.0},{"v":42,"t_a":27.0,"t_b":28.0}]],[[{"v":22,"t_a":0.0,"t_b":0.0},{"v":15,"t_a":4.0,"t_b":9.0},{"v":22,"t_a":12.0,"t_b":15.0},{"v":15,"t_a":19.0,"t_b":25.0},{"v":22,"t_a":28.0,"t_b":28.0}],[{"v":16,"t_a":0.0,"t_b":0.0},{"v":9,"t_a":5.0,"t_b":6.0},{"v":10,"t_a":14.0,"t_b":14.0},{"v":3,"t_a":20.0,"t_b":28.0}],[{"v":19,"t_a":0.0,"t_b":3.0},{"v":26,"t_a":9.0,"t_b":9.0},{"v":33,"t_a":11.0,"t_b":15.0},{"v":26,"t_a":17.0,"t_b":17.0},{"v":33,"t_a":19.0,"t_b":19.0},{"v":26,"t_a":21.0,"t_b":22.0},{"v":27,"t_a":24.0,"t_b":24.0},{"v":20,"t_a":25.0,"t_b":28.0}]],[[{"v":22,"t_a":0.0,"t_b":3.0},{"v":15,"t_a":7.0,"t_b":9.0},{"v":22,"t_a":12.0,"t_b":14.0},{"v":29,"t_a":17.0,"t_b":28.0}],[{"v":16,"t_a":0.0,"t_b":1.0},{"v":9,"t_a":6.0,"t_b":6.0},{"v":2,"t_a":12.0,"t_b":12.0},{"v":3,"t_a":20.0,"t_b":28.0}],[{"v":19,"t_a":0.0,"t_b":6.0},{"v":26,"t_a":12.0,"t_b":13.0},{"v":33,"t_a":15.0,"t_b":16.0},{"v":41,"t_a":22.0,"t_b":28.0}]],[[{"v":22,"t_a":0.0,"t_b":5.0},{"v":15,"t_a":9.0,"t_b":28.0}],[{"v":16,"t_a":0.0,"t_b":4.0},{"v":9,"t_a":9.0,"t_b":9.0},{"v":10,"t_a":17.0,"t_b":17.0},{"v":3,"t_a":23.0,"t_b":28.0}],[{"v":19,"t_a":0.0,"t_b":5.0},{"v":26,"t_a":11.0,"t_b":11.0},{"v":33,"t_a":13.0,"t_b":15.0},{"v":26,"t_a":17.0,"t_b":17.0},{"v":27,"t_a":19.0,"t_b":19.0},{"v":20,"t_a":20.0,"t_b":21.0},{"v":27,"t_a":25.0,"t_b":25.0},{"v":20,"t_a":26.0,"t_b":28.0}]],[[{"v":22,"t_a":0.0,"t_b":0.0},{"v":15,"t_a":4.0,"t_b":6.0},{"v":8,"t_a":13.0,"t_b":13.0},{"v":1,"t_a":15.0,"t_b":17.0},{"v":8,"t_a":20.0,"t_b":20.0},{"v":15,"t_a":22.0,"t_b":28.0}],[{"v":16,"t_a":0.0,"t_b":0.0},{"v":9,"t_a":5.0,"t_b":6.0},{"v":10,"t_a":14.0,"t_b":15.0},{"v":3,"t_a":21.0,"t_b":28.0}],[{"v":19,"t_a":0.0,"t_b":0.0},{"v":26,"t_a":6.0,"t_b":6.0},{"v":33,"t_a":8.0,"t_b":8.0},{"v":25,"t_a":13.0,"t_b":13.0},{"v":33,"t_a":17.0,"t_b":18.0},{"v":26,"t_a":20.0,"t_b":20.0},{"v":19,"t_a":23.0,"t_b":28.0}]],[[{"v":22,"t_a":0.0,"t_b":0.0},{"v":15,"t_a":4.0,"t_b":28.0}],[{"v":16,"t_a":0.0,"t_b":1.0},{"v":9,"t_a":6.0,"t_b":6.0},{"v":2,"t_a":12.0,"t_b":13.0},{"v":3,"t_a":21.0,"t_b":28.0}],[{"v":19,"t_a":0.0,"t_b":0.0},{"v":26,"t_a":6.0,"t_b":8.0},{"v":33,"t_a":10.0,"t_b":14.0},{"v":26,"t_a":16.0,"t_b":16.0},{"v":33,"t_a":18.0,"t_b":23.0},{"v":26,"t_a":25.0,"t_b":26.0},{"v":33,"t_a":28.0,"t_b":28.0}]],[[{"v":22,"t_a":0.0,"t_b":5.0},{"v":29,"t_a":8.0,"t_b":11.0},{"v":36,"t_a":20.0,"t_b":28.0}],[{"v":16,"t_a":0.0,"t_b":5.0},{"v":9,"t_a":10.0,"t_b":10.0},{"v":2,"t_a":16.0,"t_b":16.0},{"v":3,"t_a":24.0,"t_b":28.0}],[{"v":19,"t_a":0.0,"t_b":1.0},{"v":26,"t_a":7.0,"t_b":7.0},{"v":19,"t_a":10.0,"t_b":10.0},{"v":26,"t_a":16.0,"t_b":18.0},{"v":19,"t_a":21.0,"t_b":22.0},{"v":26,"t_a":28.0,"t_b":28.0}]],[[{"v":22,"t_a":0.0,"t_b":0.0},{"v":15,"t_a":4.0,"t_b":4.0},{"v":16,"t_a":13.0,"t_b":15.0},{"v":15,"t_a":19.0,"t_b":19.0},{"v":22,"t_a":22.0,"t_b":22.0},{"v":15,"t_a":26.0,"t_b":28.0}],[{"v":16,"t_a":0.0,"t_b":0.0},{"v":9,"t_a":5.0,"t_b":5.0},{"v":10,"t_a":13.0,"t_b":15.0},{"v":3,"t_a":21.0,"t_b":28.0}],[{"v":19,"t_a":0.0,"t_b":0.0},{"v":26,"t_a":6.0,"t_b":6.0},{"v":33,"t_a":8.0,"t_b":8.0},{"v":25,"t_a":13.0,"t_b":13.0},{"v":33,"t_a":17.0,"t_b":17.0},{"v":41,"t_a":23.0,"t_b":23.0},{"v":42,"t_a":25.0,"t_b":28.0}]],[[{"v":22,"t_a":0.0,"t_b":0.0},{"v":15,"t_a":4.0,"t_b":12.0},{"v":22,"t_a":15.0,"t_b":16.0},{"v":15,"t_a":20.0,"t_b":24.0},{"v":22,"t_a":27.0,"t_b":28.0}],[{"v":16,"t_a":0.0,"t_b":0.0},{"v":9,"t_a":5.0,"t_b":5.0},{"v":2,"t_a":11.0,"t_b":12.0},{"v":3,"t_a":20.0,"t_b":28.0}],[{"v":19,"t_a":0.0,"t_b":2.0},{"v":26,"t_a":8.0,"t_b":8.0},{"v":27,"t_a":10.0,"t_b":11.0},{"v":35,"t_a":17.0,"t_b":17.0},{"v":41,"t_a":20.0,"t_b":26.0},{"v":42,"t_a":28.0,"t_b":28.0}]],[[{"v":22,"t_a":0.0,"t_b":2.0},{"v":29,"t_a":5.0,"t_b":5.0},{"v":22,"t_a":15.0,"t_b":28.0}],[{"v":16,"t_a":0.0,"t_b":0.0},{"v":9,"t_a":5.0,"t_b":6.0},{"v":2,"t_a":12.0,"t_b":12.0},{"v":3,"t_a":20.0,"t_b":28.0}],[{"v":19,"t_a":0.0,"t_b":3.0},{"v":26,"t_a":9.0,"t_b":11.0},{"v":27,"t_a":13.0,"t_b":15.0},{"v":35,"t_a":21.0,"t_b":22.0},{"v":42,"t_a":27.0,"t_b":28.0}]],[[{"v":22,"t_a":0.0,"t_b":4.0},{"v":15,"t_a":8.0,"t_b":10.0},{"v":22,"t_a":13.0,"t_b":14.0},{"v":15,"t_a":18.0,"t_b":19.0},{"v":22,"t_a":22.0,"t_b":25.0},{"v":29,"t_a":28.0,"t_b":28.0}],[{"v":16,"t_a":0.0,"t_b":2.0},{"v":9,"t_a":7.0,"t_b":7.0},{"v":10,"t_a":15.0,"t_b":15.0},{"v":3,"t_a":21.0,"t_b":28.0}],[{"v":19,"t_a":0.0,"t_b":0.0},{"v":26,"t_a":6.0,"t_b":6.0},{"v":33,"t_a":8.0,"t_b":8.0},{"v":25,"t_a":13.0,"t_b":13.0},{"v":33,"t_a":17.0,"t_b":17.0},{"v":41,"t_a":23.0,"t_b":25.0},{"v":42,"t_a":27.0,"t_b":28.0}]],[[{"v":22,"t_a":0.0,"t_b":0.0},{"v":15,"t_a":4.0,"t_b":4.0},{"v":22,"t_a":7.0,"t_b":18.0},{"v":29,"t_a":21.0,"t_b":28.0}],[{"v":16,"t_a":0.0,"t_b":0.0},{"v":9,"t_a":5.0,"t_b":5.0},{"v":2,"t_a":11.0,"t_b":13.0},{"v":3,"t_a":21.0,"t_b":28.0}],[{"v":19,"t_a":0.0,"t_b":0.0},{"v":26,"t_a":6.0,"t_b":6.0},{"v":33,"t_a":8.0,"t_b":9.0},{"v":26,"t_a":11.0,"t_b":11.0},{"v":33,"t_a":13.0,"t_b":14.0},{"v":41,"t_a":20.0,"t_b":26.0},{"v":40,"t_a":27.0,"t_b":28.0}]],[[{"v":22,"t_a":0.0,"t_b":0.0},{"v":15,"t_a":4.0,"t_b":4.0},{"v":8,"t_a":11.0,"t_b":11.0},{"v":1,"t_a":13.0,"t_b":17.0},{"v":2,"t_a":20.0,"t_b":21.0},{"v":1,"t_a":22.0,"t_b":24.0},{"v":8,"t_a":27.0,"t_b":28.0}],[{"v":16,"t_a":0.0,"t_b":0.0},{"v":9,"t_a":5.0,"t_b":5.0},{"v":10,"t_a":13.0,"t_b":13.0},{"v":3,"t_a":19.0,"t_b":23.0},{"v":10,"t_a":27.0,"t_b":28.0}],[{"v":19,"t_a":0.0,"t_b":1.0},{"v":26,"t_a":7.0,"t_b":9.0},{"v":27,"t_a":11.0,"t_b":11.0},{"v":35,"t_a":17.0,"t_b":20.0},{"v":42,"t_a":25.0,"t_b":28.0}]],[[{"v":22,"t_a":0.0,"t_b":0.0},{"v":15,"t_a":4.0,"t_b":6.0},{"v":8,"t_a":13.0,"t_b":13.0},{"v":1,"t_a":15.0,"t_b":17.0},{"v":2,"t_a":20.0,"t_b":21.0},{"v":1,"t_a":22.0,"t_b":24.0},{"v":2,"t_a":27.0,"t_b":27.0},{"v":1,"t_a":28.0,"t_b":28.0}],[{"v":16,"t_a":0.0,"t_b":1.0},{"v":9,"t_a":6.0,"t_b":7.0},{"v":2,"t_a":13.0,"t_b":13.0},{"v":3,"t_a":21.0,"t_b":28.0}],[{"v":19,"t_a":0.0,"t_b":0.0},{"v":26,"t_a":6.0,"t_b":6.0},{"v":33,"t_a":8.0,"t_b":8.0},{"v":25,"t_a":13.0,"t_b":13.0},{"v":33,"t_a":17.0,"t_b":17.0},{"v":41,"t_a":23.0,"t_b":23.0},{"v":42,"t_a":25.0,"t_b":28.0}]],[[{"v":22,"t_a":0.0,"t_b":3.0},{"v":15,"t_a":7.0,"t_b":9.0},{"v":22,"t_a":12.0,"t_b":16.0},{"v":15,"t_a":20.0,"t_b":28.0}],[{"v":16,"t_a":0.0,"t_b":0.0},{"v":9,"t_a":5.0,"t_b":5.0},{"v":10,"t_a":13.0,"t_b":14.0},{"v":3,"t_a":20.0,"t_b":28.0}],[{"v":19,"t_a":0.0,"t_b":0.0},{"v":26,"t_a":6.0,"t_b":6.0},{"v":27,"t_a":8.0,"t_b":8.0},{"v":26,"t_a":12.0,"t_b":12.0},{"v":33,"t_a":14.0,"t_b":15.0},{"v":41,"t_a":21.0,"t_b":22.0},{"v":42,"t_a":24.0,"t_b":24.0},{"v":49,"t_a":28.0,"t_b":28.0}]],[[{"v":22,"t_a":0.0,"t_b":3.0},{"v":15,"t_a":7.0,"t_b":8.0},{"v":22,"t_a":11.0,"t_b":11.0},{"v":15,"t_a":15.0,"t_b":19.0},{"v":22,"t_a":22.0,"t_b":28.0}],[{"v":16,"t_a":0.0,"t_b":2.0},{"v":9,"t_a":7.0,"t_b":7.0},{"v":10,"t_a":15.0,"t_b":15.0},{"v":3,"t_a":21.0,"t_b":22.0},{"v":10,"t_a":26.0,"t_b":28.0}],[{"v":19,"t_a":0.0,"t_b":3.0},{"v":26,"t_a":9.0,"t_b":9.0},{"v":27,"t_a":11.0,"t_b":14.0},{"v":35,"t_a":20.0,"t_b":21.0},{"v":42,"t_a":26.0,"t_b":28.0}]],[[{"v":22,"t_a":0.0,"t_b":1.0},{"v":15,"t_a":5.0,"t_b":7.0},{"v":8,"t_a":14.0,"t_b":14.0},{"v":1,"t_a":16.0,"t_b":17.0},{"v":2,"t_a":20.0,"t_b":23.0},{"v":1,"t_a":24.0,"t_b":25.0},{"v":2,"t_a":28.0,"t_b":28.0}],[{"v":16,"t_a":0.0,"t_b":2.0},{"v":9,"t_a":7.0,"t_b":8.0},{"v":10,"t_a":16.0,"t_b":16.0},{"v":3,"t_a":22.0,"t_b":28.0}],[{"v":19,"t_a":0.0,"t_b":0.0},{"v":26,"t_a":6.0,"t_b":10.0},{"v":33,"t_a":12.0,"t_b":13.0},{"v":41,"t_a":19.0,"t_b":23.0},{"v":40,"t_a":24.0,"t_b":28.0}]],[[{"v":22,"t_a":0.0,"t_b":0.0},{"v":23,"t_a":9.0,"t_b":9.0},{"v":17,"t_a":12.0,"t_b":12.0},{"v":16,"t_a":15.0,"t_b":16.0},{"v":15,"t_a":20.0,"t_b":20.0},{"v":22,"t_a":23.0,"t_b":24.0},{"v":29,"t_a":27.0,"t_b":28.0}],[{"v":16,"t_a":0.0,"t_b":0.0},{"v":9,"t_a":5.0,"t_b":6.0},{"v":10,"t_a":14.0,"t_b":16.0},{"v":3,"t_a":22.0,"t_b":24.0},{"v":10,"t_a":28.0,"t_b":28.0}],[{"v":19,"t_a":0.0,"t_b":0.0},{"v":12,"t_a":10.0,"t_b":10.0},{"v":11,"t_a":18.0,"t_b":18.0},{"v":18,"t_a":20.0,"t_b":20.0},{"v":11,"t_a":23.0,"t_b":23.0},{"v":18,"t_a":25.0,"t_b":25.0},{"v":11,"t_a":28.0,"t_b":28.0}]]],"def_probs":[0.0,0.0,0.0,0.0,0.0,0.0,0.0,0.0,0.0,0.0,0.0,0.0,0.0,0.0,0.0,0.0,0.0,0.0,0.0,0.0,0.0,0.0,0.0,0.0,0.0,0.0,0.0,0.0,0.0,0.0,0.0,0.0,0.0,0.0,0.0,0.0,0.0,0.0,0.0,0.0,0.0,0.0,0.0,0.0,0.0,0.0,0.0,0.0,0.0,0.0,0.0,0.0,0.0,0.0,0.0,0.0,0.0,0.0,0.0,0.0,0.0,0.0,0.0,0.0,0.0,0.0,0.0,0.0,0.0,0.0,0.0,0.0,0.0,0.3999999999999999,0.0,0.0,0.0,0.0,0.0,0.0,0.0,0.0,0.0,0.0,0.0,0.0,0.0,0.0,0.0,0.0,0.0,0.0,0.0,0.20000000000000004,0.0,0.0,0.0,0.0,0.0,0.20000000000000004,0.0,0.0,0.0,0.0,0.0,0.20000000000000007,0.0,0.0,0.0,0.0,0.0,0.0],"obj_core_over_time":[1.0,-0.0,0.5,1.0,0.5,-0.0,0.33333333333333337,0.5,-0.0,0.33333333333333337,0.5,0.3333333333333333,-0.0,0.3333333333333333,0.3333333333333333,0.3333333333333333,-0.0,0.27272727272727276,0.5,0.4,-0.0,0.2857142857142857,0.3333333333333333,0.3333333333333333,0.3,0.5,0.3333333333333333,0.3333333333333333,0.33333333333333337,0.3333333333333333,0.27272727272727276,0.33333333333333337,0.3333333333333333,0.29411764705882354,0.28571428571428575,0.30769230769230765,0.3,0.33333333333333337,0.3272727272727273,0.30769230769230765,0.4,0.33333333333333337,0.35714285714285715,0.36363636363636365,0.38461538461538464,0.388235294117647,0.3880597014925373,0.4042553191489361,0.4285714285714286,0.41379310344827586,0.4318181818181818,0.4202898550724638,0.45454545454545453,0.4516129032258065,0.46093749999999994,0.47530864197530864,0.5,0.5,0.506172839506173,0.5116279069767441,0.5,0.5,0.510752688172043,0.5090909090909091,0.5185185185185185,0.5172413793103449,0.5200000000000001,0.5238095238095238,0.5277777777777778,0.5250000000000001,0.5263157894736841,0.5225225225225225,0.5217391304347826,0.5211267605633803,0.5250000000000001,0.5625,0.5625,0.5625000000000001,0.5666666666666665,0.5666666666666667,0.5625,0.5666666666666667,0.5625000000000003,0.5624999999999999,0.5625000000000002,0.5650000000000001,0.5625,0.5625,0.5625,0.5641025641025641,0.5657894736842106,0.5694444444444444,0.5714285714285714,0.5714285714285714,0.5714285714285714,0.5786802030456853,0.5789473684210527,0.5784313725490197,0.5833333333333334,0.5833333333333334,0.5833333333333333,0.6,0.5882352941176471,0.5882352941176471,0.5882352941176471,0.5882352941176471,0.5882352941176471,0.6,0.6,0.6,0.6,0.6000000000000001,0.6,0.6],"obj_DO_over_time":[null,1.0,1.0,null,1.0,1.0,1.0,1.0,1.0,1.0,1.0,1.0,1.0,1.0,1.0,1.0,1.0,1.0,1.0,0.7000000000000001,1.0,0.7142857142857142,1.0,1.0,0.7000000000000002,1.0,1.0,0.6666666666666666,0.7777777777777779,1.0000000000000002,0.8181818181818183,0.8333333333333334,0.6666666666666666,0.7647058823529411,0.8571428571428571,0.7692307692307693,0.75,0.8333333333333335,0.7636363636363637,0.7692307692307692,0.7555555555555554,0.6666666666666667,0.7142857142857143,0.8181818181818181,0.7435897435897435,0.6705882352941177,0.7686567164179104,0.6595744680851063,0.7142857142857142,0.7241379310344828,0.7727272727272728,0.7536231884057971,0.6363636363636364,0.8387096774193548,0.796875,0.734567901234568,1.0,0.9285714285714285,0.8950617283950617,0.8372093023255813,1.0,0.9,0.7956989247311828,0.7636363636363638,0.6666666666666666,0.7241379310344828,0.76,0.7142857142857143,0.8055555555555556,0.6833333333333336,0.6842105263157894,0.7297297297297297,0.6739130434782609,0.6760563380281692,0.7149999999999999,0.6875,0.6875,0.8125000000000002,0.6666666666666666,0.6666666666666666,0.6875,0.7,0.8124999999999999,0.7187500000000003,0.6875000000000002,0.675,0.75,0.6874999999999998,0.6874999999999996,0.6794871794871795,0.6842105263157894,0.6527777777777779,0.6428571428571428,0.7142857142857142,0.6428571428571428,0.6903553299492386,0.7368421052631579,0.6862745098039217,0.6666666666666667,0.6666666666666665,0.6875000000000001,0.6000000000000001,0.7058823529411765,0.6470588235294112,0.7058823529411764,0.7647058823529411,0.6470588235294117,0.6499999999999999,0.6499999999999999,0.6799999999999998,0.6999999999999998,0.6500000000000001,0.8,0.6],"obj_AO_over_time":[0.0,null,0.0,0.0,0.0,null,0.0,0.0,null,0.0,0.0,0.0,null,0.0,0.0,0.0,null,0.0,0.0,0.0,null,0.0,0.0,0.0,0.0,0.0,0.0,0.0,0.0,0.0,0.0,0.0,0.0,0.1176470588235294,0.0,0.05769230769230768,0.09999999999999996,0.0,0.12727272727272726,0.15384615384615383,0.0,0.16666666666666666,0.23809523809523814,0.22727272727272727,0.2692307692307693,0.2588235294117647,0.31343283582089554,0.3191489361702127,0.23809523809523814,0.3448275862068966,0.3181818181818181,0.36231884057971014,0.2727272727272727,0.3387096774193549,0.42187499999999994,0.3641975308641976,0.5,0.5,0.4814814814814815,0.46511627906976727,0.41666666666666663,0.5,0.4838709677419356,0.5045454545454547,0.48148148148148145,0.49425287356321845,0.48000000000000004,0.4761904761904761,0.4722222222222222,0.5000000000000001,0.4736842105263155,0.4774774774774775,0.4782608695652174,0.5211267605633804,0.5250000000000001,0.5625,0.5625,0.562500000000001,0.5333333333333332,0.5333333333333333,0.5625,0.5333333333333333,0.5625000000000003,0.5624999999999999,0.5625000000000002,0.5249999999999999,0.5,0.5625,0.5625,0.5384615384615384,0.513157894736842,0.5694444444444444,0.5714285714285714,0.5714285714285714,0.5714285714285714,0.5583756345177671,0.5526315789473685,0.5784313725490201,0.5833333333333334,0.5833333333333333,0.5833333333333331,0.4,0.588235294117647,0.5882352941176472,0.5882352941176471,0.5882352941176471,0.588235294117647,0.6000000000000001,0.5999999999999999,0.6000000000000001,0.6000000000000001,0.6000000000000001,0.6000000000000001,0.6000000000000002],"coreLP_time_over_time":[4.197831553,0.004453118,0.009026983,0.004646522,0.004801874,0.004502982,0.004436888,0.004318195,0.004419184,0.006063077,0.004372285,0.005395681,0.00442768,0.006324448,0.004801634,0.004564158,0.004276375,0.006140002,0.004729338,0.004963368,0.010204097,0.004841058,0.007283614,0.004807505,0.005490541,0.004721502,0.005057846,0.004986752,0.004862337,0.004972445,0.005164677,0.004674044,0.004776495,0.004961254,0.004999075,0.005080518,0.004971223,0.005213358,0.005410619,0.005467686,0.005326231,0.005034451,0.005530014,0.005452798,0.005499226,0.005463289,0.0072285,0.005876516,0.00757436,0.006267682,0.00635726,0.006168955,0.007111319,0.006349296,0.006542939,0.006315823,0.006145933,0.006460114,0.006522341,0.006313549,0.006623551,0.006833887,0.006766881,0.006545766,0.006421091,0.0070052,0.00721797,0.007162395,0.007109015,0.006401715,0.007049072,0.007050064,0.00714392,0.007245882,0.007277622,0.006612682,0.006297589,0.006455575,0.007003746,0.007351792,0.006907956,0.007164028,0.007496083,0.007645112,0.007283773,0.007578989,0.007027352,0.007357763,0.007459916,0.008463171,0.007185409,0.00705925,0.007709314,0.006868191,0.007107643,0.007888983,0.007299604,0.00801536,0.007621539,0.007305634,0.008075293,0.032789118,0.008464586,0.008954255,0.007753448,0.008487939,0.00846239,0.008176503,0.008446501,0.007995734,0.008070564,0.008370838,0.008279197,0.00849901],"DO_time_over_time":[null,3.716612468,0.896601144,null,0.786371431,0.834895332,0.786508249,0.783998386,0.775335478,0.789749607,0.833938212,0.783128209,0.773554278,0.774335277,0.831539569,0.851480947,0.766579083,0.760168984,0.728898092,0.897301813,1.146287268,0.808527074,0.729329775,0.788074495,0.762229511,0.762814843,0.704390364,0.748993528,0.840168322,0.747730393,1.17880666,0.742466741,0.734814012,0.805907766,0.809811661,0.870900453,0.884059609,0.910371682,1.814858954,0.884874423,0.914492154,0.836743479,0.887517494,0.927164756,1.920809957,0.895633996,0.876607459,0.920254266,0.78099735,1.420351145,0.970111304,0.844702665,0.741730265,0.736357707,0.754067836,1.261733947,0.712787131,0.728595984,0.742603498,0.746289182,0.711484802,1.209186955,0.744074183,0.738764003,0.926679523,0.960143862,1.428429894,0.856506681,0.949746972,0.889259441,0.843240053,1.345796261,0.941823706,0.966871139,0.829881409,0.953034056,1.535912139,0.72893392,0.786560275,0.922462669,0.853993654,1.324282836,0.789115924,0.94869333,0.861397053,0.783770988,1.2393534,0.934539231,0.879398319,0.790784794,0.960537533,1.238395147,0.7537884,0.756305636,0.75558454,0.955093932,1.351911274,0.792105228,0.934850656,0.904809898,1.563784067,0.875243653,0.796906842,0.971755699,0.942314529,1.461239733,0.907118751,0.793864899,0.96698319,1.488336321,0.905918616,0.962965542,0.967497768,1.54555968],"AO_time_over_time":[3.983415335,null,0.614336048,0.577127855,0.535726653,null,0.541960001,0.625375678,null,0.557611518,0.573886327,0.674907945,null,0.57519035,0.65666824,0.575666737,null,0.5973821,0.655587788,1.386185087,null,0.727894995,0.602680038,0.616227225,0.661099847,0.596081073,0.747084477,0.589104177,0.584500356,1.178842296,0.585476202,0.736568273,0.741682003,0.7863551,0.786336747,0.804633409,0.821698465,0.801992651,0.813969434,0.797279554,0.78198025,0.828564402,0.836011002,0.834856781,0.823270051,0.913789142,0.766357457,0.855445385,0.750196182,0.770813321,0.813402676,1.01323681,0.698713122,0.735173339,0.729257538,0.735232319,0.647981949,0.65303226,0.769998829,0.717966486,0.700431125,0.658757931,0.771162457,0.806736546,0.926583172,1.078352388,0.981240052,0.913919387,0.825546313,0.948453549,0.980083356,0.808634055,0.93107376,1.030554994,0.81962865,0.782178763,0.936092172,0.958566506,0.92757583,0.856540255,0.975648973,1.028654877,0.870037408,0.783624263,0.973936612,1.064123427,0.856123831,0.839666088,1.015000347,0.91709465,0.843826525,0.991319025,1.005712714,0.864989411,1.071262828,1.045790005,1.093147042,1.040452132,0.826426108,1.059520077,1.020011525,1.047023285,1.038782781,0.801015752,1.213795296,1.12342755,1.125838336,1.059396724,0.799899933,1.035516026,1.050653556,1.076588449,1.067354004,1.042927701],"convergence_flag":true,"time_graph_att_constr":0.784915161,"time_graph_def_constr":0.574153028}}