{"time_zh":301.216015015,"results_zh":{"att_strats":[[{"v":3,"t":0.0},{"v":8,"t":4.0},{"v":7,"t":6.0},{"v":11,"t":14.0},{"v":26,"t":24.75}],[{"v":3,"t":0.0},{"v":8,"t":4.0},{"v":13,"t":10.0},{"v":18,"t":18.0},{"v":23,"t":24.0},{"v":26,"t":24.0}]],"att_probs":[-0.0,1.0],"def_strats":[[[{"v":7,"t_a":0.0,"t_b":0.0},{"v":11,"t_a":8.0,"t_b":25.0}]],[[{"v":7,"t_a":0.0,"t_b":-0.0}]],[[{"v":7,"t_a":0.0,"t_b":-0.0}]],[[{"v":7,"t_a":0.0,"t_b":-0.0}]],[[{"v":7,"t_a":0.0,"t_b":-0.0}]],[[{"v":7,"t_a":0.0,"t_b":-0.0}]],[[{"v":7,"t_a":0.0,"t_b":-0.0}]],[[{"v":7,"t_a":0.0,"t_b":-0.0}]],[[{"v":7,"t_a":0.0,"t_b":-0.0}]],[[{"v":7,"t_a":0.0,"t_b":-0.0}]],[[{"v":7,"t_a":0.0,"t_b":-0.0}]],[[{"v":7,"t_a":0.0,"t_b":-0.0}]],[[{"v":7,"t_a":0.0,"t_b":-0.0}]],[[{"v":7,"t_a":0.0,"t_b":-0.0}]],[[{"v":7,"t_a":0.0,"t_b":-0.0}]],[[{"v":7,"t_a":0.0,"t_b":-0.0}]],[[{"v":7,"t_a":0.0,"t_b":-0.0}]],[[{"v":7,"t_a":0.0,"t_b":-0.0}]],[[{"v":7,"t_a":0.0,"t_b":-0.0}]],[[{"v":7,"t_a":0.0,"t_b":-0.0}]],[[{"v":7,"t_a":0.0,"t_b":-0.0}]],[[{"v":7,"t_a":0.0,"t_b":-0.0}]],[[{"v":7,"t_a":0.0,"t_b":-0.0}]]],"def_probs":[0.0,1.0,0.0,0.0,0.0,0.0,0.0,0.0,0.0,0.0,0.0,0.0,0.0,0.0,0.0,0.0,0.0,0.0,0.0,0.0,0.0,0.0,0.0],"obj_core_over_time":[1.0,-0.0,-0.0,-0.0,-0.0,-0.0,-0.0,-0.0,-0.0,-0.0,-0.0,-0.0,-0.0,-0.0,-0.0,-0.0,-0.0,-0.0,-0.0,-0.0,-0.0,-0.0,-0.0,-0.0],"obj_DO_over_time":[null,1.0,1.0,1.0,1.0,1.0,1.0,1.0,1.0,1.0,1.0,1.0,1.0,1.0,1.0,1.0,1.0,1.0,1.0,1.0,1.0,1.0,1.0,null],"obj_AO_over_time":[0.0,null,null,null,null,null,null,null,null,null,null,null,null,null,null,null,null,null,null,null,null,null,null,null],"coreLP_time_over_time":[0.004425686,0.004547444,0.0048851,0.00502813,0.004811953,0.005387696,0.004945504,0.015388601,0.005696246,0.00557572,0.004848722,0.010851665,0.004711493,0.006377127,0.006657304,0.005287267,0.005426719,0.005265475,0.004947317,0.005184524,0.005317144,0.004661128,0.005997794,0.004906531],"DO_time_over_time":[null,17.322994586,12.708428209,13.003651896,12.499515997,13.10052482,12.620081835,13.362377106,12.946725532,13.214705635,12.756975971,13.317687703,12.82138467,12.616737332,13.142622599,12.74374526,13.386713069,12.611155842,13.253345948,12.699004099,13.231252744,12.44031908,12.973721428,7.202689619],"AO_time_over_time":[4.40133942,null,null,null,null,null,null,null,null,null,null,null,null,null,null,null,null,null,null,null,null,null,null,null],"convergence_flag":false,"time_graph_att_constr":null,"time_graph_def_constr":null},"time_ne":13.868845101,"results_ne":{"att_strats":[[{"v":3,"t":0.0},{"v":8,"t":4.5},{"v":7,"t":6.5},{"v":11,"t":14.5},{"v":26,"t":24.5}],[{"v":3,"t":0.0},{"v":8,"t":4.5},{"v":13,"t":10.5},{"v":18,"t":17.5},{"v":23,"t":23.5},{"v":26,"t":23.5}],[{"v":3,"t":0.0},{"v":2,"t":10.5},{"v":1,"t":12.5},{"v":6,"t":15.5},{"v":11,"t":24.5},{"v":26,"t":24.5}],[{"v":3,"t":0.0},{"v":2,"t":10.5},{"v":7,"t":14.5},{"v":11,"t":22.5},{"v":26,"t":24.5}]],"att_probs":[-0.0,-0.0,-0.0,1.0],"def_strats":[[[{"v":7,"t_a":0.0,"t_b":0.0},{"v":11,"t_a":8.0,"t_b":25.0}]],[[{"v":7,"t_a":0.0,"t_b":1.0},{"v":8,"t_a":4.0,"t_b":7.0},{"v":13,"t_a":13.0,"t_b":15.0},{"v":18,"t_a":22.0,"t_b":25.0}]],[[{"v":7,"t_a":0.0,"t_b":0.0},{"v":8,"t_a":3.0,"t_b":5.0},{"v":13,"t_a":11.0,"t_b":11.0},{"v":8,"t_a":14.0,"t_b":14.0},{"v":7,"t_a":16.0,"t_b":16.0},{"v":11,"t_a":24.0,"t_b":25.0}]],[[{"v":7,"t_a":0.0,"t_b":1.0},{"v":8,"t_a":4.0,"t_b":7.0},{"v":7,"t_a":9.0,"t_b":15.0},{"v":11,"t_a":23.0,"t_b":25.0}]]],"def_probs":[0.0,0.0,0.0,1.0],"obj_core_over_time":[1.0,-0.0,1.0,0.5,1.0,0.5,1.0],"obj_DO_over_time":[null,1.0,null,1.0,null,1.0,null],"obj_AO_over_time":[0.0,null,0.0,0.5,0.0,0.5,1.0],"coreLP_time_over_time":[4.01041848,0.004574725,0.004613609,0.004330647,0.004464148,0.004352899,0.004098992],"DO_time_over_time":[null,2.928010854,null,0.118089178,null,0.110845982,null],"AO_time_over_time":[3.339050453,null,0.089298926,0.10311603,0.052952588,0.091009714,0.049670975],"convergence_flag":true,"time_graph_att_constr":0.772104561,"time_graph_def_constr":0.509192671}}