{"time_zh":301.198657423,"results_zh":{"att_strats":[[{"v":6,"t":0.0},{"v":3,"t":63.0},{"v":17,"t":280.75}],[{"v":6,"t":0.0},{"v":10,"t":21.0},{"v":6,"t":28.0},{"v":2,"t":42.0},{"v":6,"t":63.0},{"v":2,"t":77.0},{"v":1,"t":84.0},{"v":2,"t":105.0},{"v":1,"t":112.0},{"v":2,"t":133.0},{"v":1,"t":140.0},{"v":2,"t":161.0},{"v":1,"t":168.0},{"v":5,"t":189.0},{"v":9,"t":252.0},{"v":17,"t":280.75}]],"att_probs":[-0.0,1.0],"def_strats":[[[{"v":8,"t_a":0.0,"t_b":0.0},{"v":3,"t_a":25.0,"t_b":281.0}]],[[{"v":8,"t_a":0.0,"t_b":-0.0},{"v":14,"t_a":90.0,"t_b":90.0},{"v":13,"t_a":110.0,"t_b":110.0}]],[[{"v":8,"t_a":0.0,"t_b":-0.0},{"v":14,"t_a":90.0,"t_b":90.0},{"v":13,"t_a":110.0,"t_b":110.0}]],[[{"v":8,"t_a":0.0,"t_b":-0.0},{"v":14,"t_a":90.0,"t_b":90.0},{"v":13,"t_a":110.0,"t_b":110.0}]],[[{"v":8,"t_a":0.0,"t_b":-0.0},{"v":14,"t_a":90.0,"t_b":90.0},{"v":13,"t_a":110.0,"t_b":110.0}]],[[{"v":8,"t_a":0.0,"t_b":-0.0},{"v":14,"t_a":90.0,"t_b":90.0},{"v":13,"t_a":110.0,"t_b":110.0}]],[[{"v":8,"t_a":0.0,"t_b":-0.0},{"v":14,"t_a":90.0,"t_b":90.0},{"v":13,"t_a":110.0,"t_b":110.0}]],[[{"v":8,"t_a":0.0,"t_b":-0.0},{"v":14,"t_a":90.0,"t_b":90.0},{"v":13,"t_a":110.0,"t_b":110.0}]],[[{"v":8,"t_a":0.0,"t_b":-0.0},{"v":14,"t_a":90.0,"t_b":90.0},{"v":13,"t_a":110.0,"t_b":110.0}]],[[{"v":8,"t_a":0.0,"t_b":-0.0},{"v":14,"t_a":90.0,"t_b":90.0},{"v":13,"t_a":110.0,"t_b":110.0}]],[[{"v":8,"t_a":0.0,"t_b":-0.0},{"v":14,"t_a":90.0,"t_b":90.0},{"v":13,"t_a":110.0,"t_b":110.0}]],[[{"v":8,"t_a":0.0,"t_b":-0.0},{"v":14,"t_a":90.0,"t_b":90.0},{"v":13,"t_a":110.0,"t_b":110.0}]],[[{"v":8,"t_a":0.0,"t_b":-0.0},{"v":14,"t_a":90.0,"t_b":90.0},{"v":13,"t_a":110.0,"t_b":110.0}]],[[{"v":8,"t_a":0.0,"t_b":-0.0},{"v":14,"t_a":90.0,"t_b":90.0},{"v":13,"t_a":110.0,"t_b":110.0}]],[[{"v":8,"t_a":0.0,"t_b":-0.0},{"v":14,"t_a":90.0,"t_b":90.0},{"v":13,"t_a":110.0,"t_b":110.0}]],[[{"v":8,"t_a":0.0,"t_b":-0.0},{"v":14,"t_a":90.0,"t_b":90.0},{"v":13,"t_a":110.0,"t_b":110.0}]],[[{"v":8,"t_a":0.0,"t_b":-0.0},{"v":14,"t_a":90.0,"t_b":90.0},{"v":13,"t_a":110.0,"t_b":110.0}]],[[{"v":8,"t_a":0.0,"t_b":-0.0},{"v":14,"t_a":90.0,"t_b":90.0},{"v":13,"t_a":110.0,"t_b":110.0}]],[[{"v":8,"t_a":0.0,"t_b":-0.0},{"v":14,"t_a":90.0,"t_b":90.0},{"v":13,"t_a":110.0,"t_b":110.0}]],[[{"v":8,"t_a":0.0,"t_b":-0.0},{"v":14,"t_a":90.0,"t_b":90.0},{"v":13,"t_a":110.0,"t_b":110.0}]],[[{"v":8,"t_a":0.0,"t_b":-0.0},{"v":14,"t_a":90.0,"t_b":90.0},{"v":13,"t_a":110.0,"t_b":110.0}]],[[{"v":8,"t_a":0.0,"t_b":-0.0},{"v":14,"t_a":90.0,"t_b":90.0},{"v":13,"t_a":110.0,"t_b":110.0}]],[[{"v":8,"t_a":0.0,"t_b":-0.0},{"v":14,"t_a":90.0,"t_b":90.0},{"v":13,"t_a":110.0,"t_b":110.0}]],[[{"v":8,"t_a":0.0,"t_b":-0.0},{"v":14,"t_a":90.0,"t_b":90.0},{"v":13,"t_a":110.0,"t_b":110.0}]],[[{"v":8,"t_a":0.0,"t_b":-0.0},{"v":14,"t_a":90.0,"t_b":90.0},{"v":13,"t_a":110.0,"t_b":110.0}]],[[{"v":8,"t_a":0.0,"t_b":-0.0},{"v":14,"t_a":90.0,"t_b":90.0},{"v":13,"t_a":110.0,"t_b":110.0}]],[[{"v":8,"t_a":0.0,"t_b":-0.0},{"v":14,"t_a":90.0,"t_b":90.0},{"v":13,"t_a":110.0,"t_b":110.0}]],[[{"v":8,"t_a":0.0,"t_b":-0.0},{"v":14,"t_a":90.0,"t_b":90.0},{"v":13,"t_a":110.0,"t_b":110.0}]],[[{"v":8,"t_a":0.0,"t_b":-0.0},{"v":14,"t_a":90.0,"t_b":90.0},{"v":13,"t_a":110.0,"t_b":110.0}]],[[{"v":8,"t_a":0.0,"t_b":-0.0},{"v":14,"t_a":90.0,"t_b":90.0},{"v":13,"t_a":110.0,"t_b":110.0}]],[[{"v":8,"t_a":0.0,"t_b":-0.0},{"v":14,"t_a":90.0,"t_b":90.0},{"v":13,"t_a":110.0,"t_b":110.0}]],[[{"v":8,"t_a":0.0,"t_b":-0.0},{"v":14,"t_a":90.0,"t_b":90.0},{"v":13,"t_a":110.0,"t_b":110.0}]],[[{"v":8,"t_a":0.0,"t_b":-0.0},{"v":14,"t_a":90.0,"t_b":90.0},{"v":13,"t_a":110.0,"t_b":110.0}]],[[{"v":8,"t_a":0.0,"t_b":-0.0},{"v":14,"t_a":90.0,"t_b":90.0},{"v":13,"t_a":110.0,"t_b":110.0}]],[[{"v":8,"t_a":0.0,"t_b":-0.0},{"v":14,"t_a":90.0,"t_b":90.0},{"v":13,"t_a":110.0,"t_b":110.0}]],[[{"v":8,"t_a":0.0,"t_b":-0.0},{"v":14,"t_a":90.0,"t_b":90.0},{"v":13,"t_a":110.0,"t_b":110.0}]],[[{"v":8,"t_a":0.0,"t_b":-0.0},{"v":14,"t_a":90.0,"t_b":90.0},{"v":13,"t_a":110.0,"t_b":110.0}]],[[{"v":8,"t_a":0.0,"t_b":-0.0},{"v":14,"t_a":90.0,"t_b":90.0},{"v":13,"t_a":110.0,"t_b":110.0}]],[[{"v":8,"t_a":0.0,"t_b":-0.0},{"v":14,"t_a":90.0,"t_b":90.0},{"v":13,"t_a":110.0,"t_b":110.0}]],[[{"v":8,"t_a":0.0,"t_b":-0.0},{"v":14,"t_a":90.0,"t_b":90.0},{"v":13,"t_a":110.0,"t_b":110.0}]],[[{"v":8,"t_a":0.0,"t_b":-0.0},{"v":14,"t_a":90.0,"t_b":90.0},{"v":13,"t_a":110.0,"t_b":110.0}]],[[{"v":8,"t_a":0.0,"t_b":-0.0},{"v":14,"t_a":90.0,"t_b":90.0},{"v":13,"t_a":110.0,"t_b":110.0}]],[[{"v":8,"t_a":0.0,"t_b":-0.0},{"v":14,"t_a":90.0,"t_b":90.0},{"v":13,"t_a":110.0,"t_b":110.0}]],[[{"v":8,"t_a":0.0,"t_b":-0.0},{"v":14,"t_a":90.0,"t_b":90.0},{"v":13,"t_a":110.0,"t_b":110.0}]],[[{"v":8,"t_a":0.0,"t_b":-0.0},{"v":14,"t_a":90.0,"t_b":90.0},{"v":13,"t_a":110.0,"t_b":110.0}]],[[{"v":8,"t_a":0.0,"t_b":-0.0},{"v":14,"t_a":90.0,"t_b":90.0},{"v":13,"t_a":110.0,"t_b":110.0}]],[[{"v":8,"t_a":0.0,"t_b":-0.0},{"v":14,"t_a":90.0,"t_b":90.0},{"v":13,"t_a":110.0,"t_b":110.0}]],[[{"v":8,"t_a":0.0,"t_b":-0.0},{"v":14,"t_a":90.0,"t_b":90.0},{"v":13,"t_a":110.0,"t_b":110.0}]],[[{"v":8,"t_a":0.0,"t_b":-0.0},{"v":14,"t_a":90.0,"t_b":90.0},{"v":13,"t_a":110.0,"t_b":110.0}]],[[{"v":8,"t_a":0.0,"t_b":-0.0},{"v":14,"t_a":90.0,"t_b":90.0},{"v":13,"t_a":110.0,"t_b":110.0}]],[[{"v":8,"t_a":0.0,"t_b":-0.0},{"v":14,"t_a":90.0,"t_b":90.0},{"v":13,"t_a":110.0,"t_b":110.0}]],[[{"v":8,"t_a":0.0,"t_b":-0.0},{"v":14,"t_a":90.0,"t_b":90.0},{"v":13,"t_a":110.0,"t_b":110.0}]],[[{"v":8,"t_a":0.0,"t_b":-0.0},{"v":14,"t_a":90.0,"t_b":90.0},{"v":13,"t_a":110.0,"t_b":110.0}]],[[{"v":8,"t_a":0.0,"t_b":-0.0},{"v":14,"t_a":90.0,"t_b":90.0},{"v":13,"t_a":110.0,"t_b":110.0}]],[[{"v":8,"t_a":0.0,"t_b":-0.0},{"v":14,"t_a":90.0,"t_b":90.0},{"v":13,"t_a":110.0,"t_b":110.0}]],[[{"v":8,"t_a":0.0,"t_b":-0.0},{"v":14,"t_a":90.0,"t_b":90.0},{"v":13,"t_a":110.0,"t_b":110.0}]],[[{"v":8,"t_a":0.0,"t_b":-0.0},{"v":14,"t_a":90.0,"t_b":90.0},{"v":13,"t_a":110.0,"t_b":110.0}]],[[{"v":8,"t_a":0.0,"t_b":-0.0},{"v":14,"t_a":90.0,"t_b":90.0},{"v":13,"t_a":110.0,"t_b":110.0}]],[[{"v":8,"t_a":0.0,"t_b":-0.0},{"v":14,"t_a":90.0,"t_b":90.0},{"v":13,"t_a":110.0,"t_b":110.0}]],[[{"v":8,"t_a":0.0,"t_b":-0.0},{"v":14,"t_a":90.0,"t_b":90.0},{"v":13,"t_a":110.0,"t_b":110.0}]],[[{"v":8,"t_a":0.0,"t_b":-0.0},{"v":14,"t_a":90.0,"t_b":90.0},{"v":13,"t_a":110.0,"t_b":110.0}]],[[{"v":8,"t_a":0.0,"t_b":-0.0},{"v":14,"t_a":90.0,"t_b":90.0},{"v":13,"t_a":110.0,"t_b":110.0}]],[[{"v":8,"t_a":0.0,"t_b":-0.0},{"v":14,"t_a":90.0,"t_b":90.0},{"v":13,"t_a":110.0,"t_b":110.0}]],[[{"v":8,"t_a":0.0,"t_b":-0.0},{"v":14,"t_a":90.0,"t_b":90.0},{"v":13,"t_a":110.0,"t_b":110.0}]],[[{"v":8,"t_a":0.0,"t_b":-0.0},{"v":14,"t_a":90.0,"t_b":90.0},{"v":13,"t_a":110.0,"t_b":110.0}]],[[{"v":8,"t_a":0.0,"t_b":-0.0},{"v":14,"t_a":90.0,"t_b":90.0},{"v":13,"t_a":110.0,"t_b":110.0}]],[[{"v":8,"t_a":0.0,"t_b":-0.0},{"v":14,"t_a":90.0,"t_b":90.0},{"v":13,"t_a":110.0,"t_b":110.0}]],[[{"v":8,"t_a":0.0,"t_b":-0.0},{"v":14,"t_a":90.0,"t_b":90.0},{"v":13,"t_a":110.0,"t_b":110.0}]],[[{"v":8,"t_a":0.0,"t_b":-0.0},{"v":14,"t_a":90.0,"t_b":90.0},{"v":13,"t_a":110.0,"t_b":110.0}]],[[{"v":8,"t_a":0.0,"t_b":-0.0},{"v":14,"t_a":90.0,"t_b":90.0},{"v":13,"t_a":110.0,"t_b":110.0}]],[[{"v":8,"t_a":0.0,"t_b":-0.0},{"v":14,"t_a":90.0,"t_b":90.0},{"v":13,"t_a":110.0,"t_b":110.0}]],[[{"v":8,"t_a":0.0,"t_b":-0.0},{"v":14,"t_a":90.0,"t_b":90.0},{"v":13,"t_a":110.0,"t_b":110.0}]],[[{"v":8,"t_a":0.0,"t_b":-0.0},{"v":14,"t_a":90.0,"t_b":90.0},{"v":13,"t_a":110.0,"t_b":110.0}]],[[{"v":8,"t_a":0.0,"t_b":-0.0},{"v":14,"t_a":90.0,"t_b":90.0},{"v":13,"t_a":110.0,"t_b":110.0}]],[[{"v":8,"t_a":0.0,"t_b":-0.0},{"v":14,"t_a":90.0,"t_b":90.0},{"v":13,"t_a":110.0,"t_b":110.0}]],[[{"v":8,"t_a":0.0,"t_b":-0.0},{"v":14,"t_a":90.0,"t_b":90.0},{"v":13,"t_a":110.0,"t_b":110.0}]],[[{"v":8,"t_a":0.0,"t_b":-0.0},{"v":14,"t_a":90.0,"t_b":90.0},{"v":13,"t_a":110.0,"t_b":110.0}]],[[{"v":8,"t_a":0.0,"t_b":-0.0},{"v":14,"t_a":90.0,"t_b":90.0},{"v":13,"t_a":110.0,"t_b":110.0}]],[[{"v":8,"t_a":0.0,"t_b":-0.0},{"v":14,"t_a":90.0,"t_b":90.0},{"v":13,"t_a":110.0,"t_b":110.0}]],[[{"v":8,"t_a":0.0,"t_b":-0.0},{"v":14,"t_a":90.0,"t_b":90.0},{"v":13,"t_a":110.0,"t_b":110.0}]],[[{"v":8,"t_a":0.0,"t_b":-0.0},{"v":14,"t_a":90.0,"t_b":90.0},{"v":13,"t_a":110.0,"t_b":110.0}]],[[{"v":8,"t_a":0.0,"t_b":-0.0},{"v":14,"t_a":90.0,"t_b":90.0},{"v":13,"t_a":110.0,"t_b":110.0}]],[[{"v":8,"t_a":0.0,"t_b":-0.0},{"v":14,"t_a":90.0,"t_b":90.0},{"v":13,"t_a":110.0,"t_b":110.0}]],[[{"v":8,"t_a":0.0,"t_b":-0.0},{"v":14,"t_a":90.0,"t_b":90.0},{"v":13,"t_a":110.0,"t_b":110.0}]],[[{"v":8,"t_a":0.0,"t_b":-0.0},{"v":14,"t_a":90.0,"t_b":90.0},{"v":13,"t_a":110.0,"t_b":110.0}]],[[{"v":8,"t_a":0.0,"t_b":-0.0},{"v":14,"t_a":90.0,"t_b":90.0},{"v":13,"t_a":110.0,"t_b":110.0}]],[[{"v":8,"t_a":0.0,"t_b":-0.0},{"v":14,"t_a":90.0,"t_b":90.0},{"v":13,"t_a":110.0,"t_b":110.0}]],[[{"v":8,"t_a":0.0,"t_b":-0.0},{"v":14,"t_a":90.0,"t_b":90.0},{"v":13,"t_a":110.0,"t_b":110.0}]],[[{"v":8,"t_a":0.0,"t_b":-0.0},{"v":14,"t_a":90.0,"t_b":90.0},{"v":13,"t_a":110.0,"t_b":110.0}]],[[{"v":8,"t_a":0.0,"t_b":-0.0},{"v":14,"t_a":90.0,"t_b":90.0},{"v":13,"t_a":110.0,"t_b":110.0}]],[[{"v":8,"t_a":0.0,"t_b":-0.0},{"v":14,"t_a":90.0,"t_b":90.0},{"v":13,"t_a":110.0,"t_b":110.0}]],[[{"v":8,"t_a":0.0,"t_b":-0.0},{"v":14,"t_a":90.0,"t_b":90.0},{"v":13,"t_a":110.0,"t_b":110.0}]],[[{"v":8,"t_a":0.0,"t_b":-0.0},{"v":14,"t_a":90.0,"t_b":90.0},{"v":13,"t_a":110.0,"t_b":110.0}]],[[{"v":8,"t_a":0.0,"t_b":-0.0},{"v":14,"t_a":90.0,"t_b":90.0},{"v":13,"t_a":110.0,"t_b":110.0}]],[[{"v":8,"t_a":0.0,"t_b":-0.0},{"v":14,"t_a":90.0,"t_b":90.0},{"v":13,"t_a":110.0,"t_b":110.0}]],[[{"v":8,"t_a":0.0,"t_b":-0.0},{"v":14,"t_a":90.0,"t_b":90.0},{"v":13,"t_a":110.0,"t_b":110.0}]],[[{"v":8,"t_a":0.0,"t_b":-0.0},{"v":14,"t_a":90.0,"t_b":90.0},{"v":13,"t_a":110.0,"t_b":110.0}]],[[{"v":8,"t_a":0.0,"t_b":-0.0},{"v":14,"t_a":90.0,"t_b":90.0},{"v":13,"t_a":110.0,"t_b":110.0}]],[[{"v":8,"t_a":0.0,"t_b":-0.0},{"v":14,"t_a":90.0,"t_b":90.0},{"v":13,"t_a":110.0,"t_b":110.0}]],[[{"v":8,"t_a":0.0,"t_b":-0.0},{"v":14,"t_a":90.0,"t_b":90.0},{"v":13,"t_a":110.0,"t_b":110.0}]],[[{"v":8,"t_a":0.0,"t_b":-0.0},{"v":14,"t_a":90.0,"t_b":90.0},{"v":13,"t_a":110.0,"t_b":110.0}]],[[{"v":8,"t_a":0.0,"t_b":-0.0},{"v":14,"t_a":90.0,"t_b":90.0},{"v":13,"t_a":110.0,"t_b":110.0}]],[[{"v":8,"t_a":0.0,"t_b":-0.0},{"v":14,"t_a":90.0,"t_b":90.0},{"v":13,"t_a":110.0,"t_b":110.0}]],[[{"v":8,"t_a":0.0,"t_b":-0.0},{"v":14,"t_a":90.0,"t_b":90.0},{"v":13,"t_a":110.0,"t_b":110.0}]],[[{"v":8,"t_a":0.0,"t_b":-0.0},{"v":14,"t_a":90.0,"t_b":90.0},{"v":13,"t_a":110.0,"t_b":110.0}]],[[{"v":8,"t_a":0.0,"t_b":-0.0},{"v":14,"t_a":90.0,"t_b":90.0},{"v":13,"t_a":110.0,"t_b":110.0}]],[[{"v":8,"t_a":0.0,"t_b":-0.0},{"v":14,"t_a":90.0,"t_b":90.0},{"v":13,"t_a":110.0,"t_b":110.0}]],[[{"v":8,"t_a":0.0,"t_b":-0.0},{"v":14,"t_a":90.0,"t_b":90.0},{"v":13,"t_a":110.0,"t_b":110.0}]],[[{"v":8,"t_a":0.0,"t_b":-0.0},{"v":14,"t_a":90.0,"t_b":90.0},{"v":13,"t_a":110.0,"t_b":110.0}]],[[{"v":8,"t_a":0.0,"t_b":-0.0},{"v":14,"t_a":90.0,"t_b":90.0},{"v":13,"t_a":110.0,"t_b":110.0}]],[[{"v":8,"t_a":0.0,"t_b":-0.0},{"v":14,"t_a":90.0,"t_b":90.0},{"v":13,"t_a":110.0,"t_b":110.0}]],[[{"v":8,"t_a":0.0,"t_b":-0.0},{"v":14,"t_a":90.0,"t_b":90.0},{"v":13,"t_a":110.0,"t_b":110.0}]],[[{"v":8,"t_a":0.0,"t_b":-0.0},{"v":14,"t_a":90.0,"t_b":90.0},{"v":13,"t_a":110.0,"t_b":110.0}]],[[{"v":8,"t_a":0.0,"t_b":-0.0},{"v":14,"t_a":90.0,"t_b":90.0},{"v":13,"t_a":110.0,"t_b":110.0}]],[[{"v":8,"t_a":0.0,"t_b":-0.0},{"v":14,"t_a":90.0,"t_b":90.0},{"v":13,"t_a":110.0,"t_b":110.0}]],[[{"v":8,"t_a":0.0,"t_b":-0.0},{"v":14,"t_a":90.0,"t_b":90.0},{"v":13,"t_a":110.0,"t_b":110.0}]],[[{"v":8,"t_a":0.0,"t_b":-0.0},{"v":14,"t_a":90.0,"t_b":90.0},{"v":13,"t_a":110.0,"t_b":110.0}]],[[{"v":8,"t_a":0.0,"t_b":-0.0},{"v":14,"t_a":90.0,"t_b":90.0},{"v":13,"t_a":110.0,"t_b":110.0}]],[[{"v":8,"t_a":0.0,"t_b":-0.0},{"v":14,"t_a":90.0,"t_b":90.0},{"v":13,"t_a":110.0,"t_b":110.0}]],[[{"v":8,"t_a":0.0,"t_b":-0.0},{"v":14,"t_a":90.0,"t_b":90.0},{"v":13,"t_a":110.0,"t_b":110.0}]],[[{"v":8,"t_a":0.0,"t_b":-0.0},{"v":14,"t_a":90.0,"t_b":90.0},{"v":13,"t_a":110.0,"t_b":110.0}]],[[{"v":8,"t_a":0.0,"t_b":-0.0},{"v":14,"t_a":90.0,"t_b":90.0},{"v":13,"t_a":110.0,"t_b":110.0}]],[[{"v":8,"t_a":0.0,"t_b":-0.0},{"v":14,"t_a":90.0,"t_b":90.0},{"v":13,"t_a":110.0,"t_b":110.0}]],[[{"v":8,"t_a":0.0,"t_b":-0.0},{"v":14,"t_a":90.0,"t_b":90.0},{"v":13,"t_a":110.0,"t_b":110.0}]],[[{"v":8,"t_a":0.0,"t_b":-0.0},{"v":14,"t_a":90.0,"t_b":90.0},{"v":13,"t_a":110.0,"t_b":110.0}]],[[{"v":8,"t_a":0.0,"t_b":-0.0},{"v":14,"t_a":90.0,"t_b":90.0},{"v":13,"t_a":110.0,"t_b":110.0}]],[[{"v":8,"t_a":0.0,"t_b":-0.0},{"v":14,"t_a":90.0,"t_b":90.0},{"v":13,"t_a":110.0,"t_b":110.0}]],[[{"v":8,"t_a":0.0,"t_b":-0.0},{"v":14,"t_a":90.0,"t_b":90.0},{"v":13,"t_a":110.0,"t_b":110.0}]],[[{"v":8,"t_a":0.0,"t_b":-0.0},{"v":14,"t_a":90.0,"t_b":90.0},{"v":13,"t_a":110.0,"t_b":110.0}]],[[{"v":8,"t_a":0.0,"t_b":-0.0},{"v":14,"t_a":90.0,"t_b":90.0},{"v":13,"t_a":110.0,"t_b":110.0}]],[[{"v":8,"t_a":0.0,"t_b":-0.0},{"v":14,"t_a":90.0,"t_b":90.0},{"v":13,"t_a":110.0,"t_b":110.0}]],[[{"v":8,"t_a":0.0,"t_b":-0.0},{"v":14,"t_a":90.0,"t_b":90.0},{"v":13,"t_a":110.0,"t_b":110.0}]],[[{"v":8,"t_a":0.0,"t_b":-0.0},{"v":14,"t_a":90.0,"t_b":90.0},{"v":13,"t_a":110.0,"t_b":110.0}]],[[{"v":8,"t_a":0.0,"t_b":-0.0},{"v":14,"t_a":90.0,"t_b":90.0},{"v":13,"t_a":110.0,"t_b":110.0}]],[[{"v":8,"t_a":0.0,"t_b":-0.0},{"v":14,"t_a":90.0,"t_b":90.0},{"v":13,"t_a":110.0,"t_b":110.0}]],[[{"v":8,"t_a":0.0,"t_b":-0.0},{"v":14,"t_a":90.0,"t_b":90.0},{"v":13,"t_a":110.0,"t_b":110.0}]],[[{"v":8,"t_a":0.0,"t_b":-0.0},{"v":14,"t_a":90.0,"t_b":90.0},{"v":13,"t_a":110.0,"t_b":110.0}]],[[{"v":8,"t_a":0.0,"t_b":-0.0},{"v":14,"t_a":90.0,"t_b":90.0},{"v":13,"t_a":110.0,"t_b":110.0}]],[[{"v":8,"t_a":0.0,"t_b":-0.0},{"v":14,"t_a":90.0,"t_b":90.0},{"v":13,"t_a":110.0,"t_b":110.0}]],[[{"v":8,"t_a":0.0,"t_b":-0.0},{"v":14,"t_a":90.0,"t_b":90.0},{"v":13,"t_a":110.0,"t_b":110.0}]],[[{"v":8,"t_a":0.0,"t_b":-0.0},{"v":14,"t_a":90.0,"t_b":90.0},{"v":13,"t_a":110.0,"t_b":110.0}]],[[{"v":8,"t_a":0.0,"t_b":-0.0},{"v":14,"t_a":90.0,"t_b":90.0},{"v":13,"t_a":110.0,"t_b":110.0}]],[[{"v":8,"t_a":0.0,"t_b":-0.0},{"v":14,"t_a":90.0,"t_b":90.0},{"v":13,"t_a":110.0,"t_b":110.0}]],[[{"v":8,"t_a":0.0,"t_b":-0.0},{"v":14,"t_a":90.0,"t_b":90.0},{"v":13,"t_a":110.0,"t_b":110.0}]],[[{"v":8,"t_a":0.0,"t_b":-0.0},{"v":14,"t_a":90.0,"t_b":90.0},{"v":13,"t_a":110.0,"t_b":110.0}]],[[{"v":8,"t_a":0.0,"t_b":-0.0},{"v":14,"t_a":90.0,"t_b":90.0},{"v":13,"t_a":110.0,"t_b":110.0}]],[[{"v":8,"t_a":0.0,"t_b":-0.0},{"v":14,"t_a":90.0,"t_b":90.0},{"v":13,"t_a":110.0,"t_b":110.0}]],[[{"v":8,"t_a":0.0,"t_b":-0.0},{"v":14,"t_a":90.0,"t_b":90.0},{"v":13,"t_a":110.0,"t_b":110.0}]],[[{"v":8,"t_a":0.0,"t_b":-0.0},{"v":14,"t_a":90.0,"t_b":90.0},{"v":13,"t_a":110.0,"t_b":110.0}]],[[{"v":8,"t_a":0.0,"t_b":-0.0},{"v":14,"t_a":90.0,"t_b":90.0},{"v":13,"t_a":110.0,"t_b":110.0}]],[[{"v":8,"t_a":0.0,"t_b":-0.0},{"v":14,"t_a":90.0,"t_b":90.0},{"v":13,"t_a":110.0,"t_b":110.0}]],[[{"v":8,"t_a":0.0,"t_b":-0.0},{"v":14,"t_a":90.0,"t_b":90.0},{"v":13,"t_a":110.0,"t_b":110.0}]],[[{"v":8,"t_a":0.0,"t_b":-0.0},{"v":14,"t_a":90.0,"t_b":90.0},{"v":13,"t_a":110.0,"t_b":110.0}]],[[{"v":8,"t_a":0.0,"t_b":-0.0},{"v":14,"t_a":90.0,"t_b":90.0},{"v":13,"t_a":110.0,"t_b":110.0}]],[[{"v":8,"t_a":0.0,"t_b":-0.0},{"v":14,"t_a":90.0,"t_b":90.0},{"v":13,"t_a":110.0,"t_b":110.0}]],[[{"v":8,"t_a":0.0,"t_b":-0.0},{"v":14,"t_a":90.0,"t_b":90.0},{"v":13,"t_a":110.0,"t_b":110.0}]],[[{"v":8,"t_a":0.0,"t_b":-0.0},{"v":14,"t_a":90.0,"t_b":90.0},{"v":13,"t_a":110.0,"t_b":110.0}]],[[{"v":8,"t_a":0.0,"t_b":-0.0},{"v":14,"t_a":90.0,"t_b":90.0},{"v":13,"t_a":110.0,"t_b":110.0}]],[[{"v":8,"t_a":0.0,"t_b":-0.0},{"v":14,"t_a":90.0,"t_b":90.0},{"v":13,"t_a":110.0,"t_b":110.0}]],[[{"v":8,"t_a":0.0,"t_b":-0.0},{"v":14,"t_a":90.0,"t_b":90.0},{"v":13,"t_a":110.0,"t_b":110.0}]],[[{"v":8,"t_a":0.0,"t_b":-0.0},{"v":14,"t_a":90.0,"t_b":90.0},{"v":13,"t_a":110.0,"t_b":110.0}]],[[{"v":8,"t_a":0.0,"t_b":-0.0},{"v":14,"t_a":90.0,"t_b":90.0},{"v":13,"t_a":110.0,"t_b":110.0}]],[[{"v":8,"t_a":0.0,"t_b":-0.0},{"v":14,"t_a":90.0,"t_b":90.0},{"v":13,"t_a":110.0,"t_b":110.0}]],[[{"v":8,"t_a":0.0,"t_b":-0.0},{"v":14,"t_a":90.0,"t_b":90.0},{"v":13,"t_a":110.0,"t_b":110.0}]],[[{"v":8,"t_a":0.0,"t_b":-0.0},{"v":14,"t_a":90.0,"t_b":90.0},{"v":13,"t_a":110.0,"t_b":110.0}]],[[{"v":8,"t_a":0.0,"t_b":-0.0},{"v":14,"t_a":90.0,"t_b":90.0},{"v":13,"t_a":110.0,"t_b":110.0}]],[[{"v":8,"t_a":0.0,"t_b":-0.0},{"v":14,"t_a":90.0,"t_b":90.0},{"v":13,"t_a":110.0,"t_b":110.0}]],[[{"v":8,"t_a":0.0,"t_b":-0.0},{"v":14,"t_a":90.0,"t_b":90.0},{"v":13,"t_a":110.0,"t_b":110.0}]],[[{"v":8,"t_a":0.0,"t_b":-0.0},{"v":14,"t_a":90.0,"t_b":90.0},{"v":13,"t_a":110.0,"t_b":110.0}]],[[{"v":8,"t_a":0.0,"t_b":-0.0},{"v":14,"t_a":90.0,"t_b":90.0},{"v":13,"t_a":110.0,"t_b":110.0}]],[[{"v":8,"t_a":0.0,"t_b":-0.0},{"v":14,"t_a":90.0,"t_b":90.0},{"v":13,"t_a":110.0,"t_b":110.0}]],[[{"v":8,"t_a":0.0,"t_b":-0.0},{"v":14,"t_a":90.0,"t_b":90.0},{"v":13,"t_a":110.0,"t_b":110.0}]],[[{"v":8,"t_a":0.0,"t_b":-0.0},{"v":14,"t_a":90.0,"t_b":90.0},{"v":13,"t_a":110.0,"t_b":110.0}]],[[{"v":8,"t_a":0.0,"t_b":-0.0},{"v":14,"t_a":90.0,"t_b":90.0},{"v":13,"t_a":110.0,"t_b":110.0}]],[[{"v":8,"t_a":0.0,"t_b":-0.0},{"v":14,"t_a":90.0,"t_b":90.0},{"v":13,"t_a":110.0,"t_b":110.0}]],[[{"v":8,"t_a":0.0,"t_b":-0.0},{"v":14,"t_a":90.0,"t_b":90.0},{"v":13,"t_a":110.0,"t_b":110.0}]],[[{"v":8,"t_a":0.0,"t_b":-0.0},{"v":14,"t_a":90.0,"t_b":90.0},{"v":13,"t_a":110.0,"t_b":110.0}]],[[{"v":8,"t_a":0.0,"t_b":-0.0},{"v":14,"t_a":90.0,"t_b":90.0},{"v":13,"t_a":110.0,"t_b":110.0}]],[[{"v":8,"t_a":0.0,"t_b":-0.0},{"v":14,"t_a":90.0,"t_b":90.0},{"v":13,"t_a":110.0,"t_b":110.0}]],[[{"v":8,"t_a":0.0,"t_b":-0.0},{"v":14,"t_a":90.0,"t_b":90.0},{"v":13,"t_a":110.0,"t_b":110.0}]],[[{"v":8,"t_a":0.0,"t_b":-0.0},{"v":14,"t_a":90.0,"t_b":90.0},{"v":13,"t_a":110.0,"t_b":110.0}]],[[{"v":8,"t_a":0.0,"t_b":-0.0},{"v":14,"t_a":90.0,"t_b":90.0},{"v":13,"t_a":110.0,"t_b":110.0}]],[[{"v":8,"t_a":0.0,"t_b":-0.0},{"v":14,"t_a":90.0,"t_b":90.0},{"v":13,"t_a":110.0,"t_b":110.0}]],[[{"v":8,"t_a":0.0,"t_b":-0.0},{"v":14,"t_a":90.0,"t_b":90.0},{"v":13,"t_a":110.0,"t_b":110.0}]],[[{"v":8,"t_a":0.0,"t_b":-0.0},{"v":14,"t_a":90.0,"t_b":90.0},{"v":13,"t_a":110.0,"t_b":110.0}]],[[{"v":8,"t_a":0.0,"t_b":-0.0},{"v":14,"t_a":90.0,"t_b":90.0},{"v":13,"t_a":110.0,"t_b":110.0}]],[[{"v":8,"t_a":0.0,"t_b":-0.0},{"v":14,"t_a":90.0,"t_b":90.0},{"v":13,"t_a":110.0,"t_b":110.0}]],[[{"v":8,"t_a":0.0,"t_b":-0.0},{"v":14,"t_a":90.0,"t_b":90.0},{"v":13,"t_a":110.0,"t_b":110.0}]],[[{"v":8,"t_a":0.0,"t_b":-0.0},{"v":14,"t_a":90.0,"t_b":90.0},{"v":13,"t_a":110.0,"t_b":110.0}]],[[{"v":8,"t_a":0.0,"t_b":-0.0},{"v":14,"t_a":90.0,"t_b":90.0},{"v":13,"t_a":110.0,"t_b":110.0}]],[[{"v":8,"t_a":0.0,"t_b":-0.0},{"v":14,"t_a":90.0,"t_b":90.0},{"v":13,"t_a":110.0,"t_b":110.0}]],[[{"v":8,"t_a":0.0,"t_b":-0.0},{"v":14,"t_a":90.0,"t_b":90.0},{"v":13,"t_a":110.0,"t_b":110.0}]],[[{"v":8,"t_a":0.0,"t_b":-0.0},{"v":14,"t_a":90.0,"t_b":90.0},{"v":13,"t_a":110.0,"t_b":110.0}]],[[{"v":8,"t_a":0.0,"t_b":-0.0},{"v":14,"t_a":90.0,"t_b":90.0},{"v":13,"t_a":110.0,"t_b":110.0}]],[[{"v":8,"t_a":0.0,"t_b":-0.0},{"v":14,"t_a":90.0,"t_b":90.0},{"v":13,"t_a":110.0,"t_b":110.0}]],[[{"v":8,"t_a":0.0,"t_b":-0.0},{"v":14,"t_a":90.0,"t_b":90.0},{"v":13,"t_a":110.0,"t_b":110.0}]],[[{"v":8,"t_a":0.0,"t_b":-0.0},{"v":14,"t_a":90.0,"t_b":90.0},{"v":13,"t_a":110.0,"t_b":110.0}]],[[{"v":8,"t_a":0.0,"t_b":-0.0},{"v":14,"t_a":90.0,"t_b":90.0},{"v":13,"t_a":110.0,"t_b":110.0}]],[[{"v":8,"t_a":0.0,"t_b":-0.0},{"v":14,"t_a":90.0,"t_b":90.0},{"v":13,"t_a":110.0,"t_b":110.0}]],[[{"v":8,"t_a":0.0,"t_b":-0.0},{"v":14,"t_a":90.0,"t_b":90.0},{"v":13,"t_a":110.0,"t_b":110.0}]],[[{"v":8,"t_a":0.0,"t_b":-0.0},{"v":14,"t_a":90.0,"t_b":90.0},{"v":13,"t_a":110.0,"t_b":110.0}]],[[{"v":8,"t_a":0.0,"t_b":-0.0},{"v":14,"t_a":90.0,"t_b":90.0},{"v":13,"t_a":110.0,"t_b":110.0}]],[[{"v":8,"t_a":0.0,"t_b":-0.0},{"v":14,"t_a":90.0,"t_b":90.0},{"v":13,"t_a":110.0,"t_b":110.0}]],[[{"v":8,"t_a":0.0,"t_b":-0.0},{"v":14,"t_a":90.0,"t_b":90.0},{"v":13,"t_a":110.0,"t_b":110.0}]],[[{"v":8,"t_a":0.0,"t_b":-0.0},{"v":14,"t_a":90.0,"t_b":90.0},{"v":13,"t_a":110.0,"t_b":110.0}]],[[{"v":8,"t_a":0.0,"t_b":-0.0},{"v":14,"t_a":90.0,"t_b":90.0},{"v":13,"t_a":110.0,"t_b":110.0}]],[[{"v":8,"t_a":0.0,"t_b":-0.0},{"v":14,"t_a":90.0,"t_b":90.0},{"v":13,"t_a":110.0,"t_b":110.0}]],[[{"v":8,"t_a":0.0,"t_b":-0.0},{"v":14,"t_a":90.0,"t_b":90.0},{"v":13,"t_a":110.0,"t_b":110.0}]],[[{"v":8,"t_a":0.0,"t_b":-0.0},{"v":14,"t_a":90.0,"t_b":90.0},{"v":13,"t_a":110.0,"t_b":110.0}]],[[{"v":8,"t_a":0.0,"t_b":-0.0},{"v":14,"t_a":90.0,"t_b":90.0},{"v":13,"t_a":110.0,"t_b":110.0}]],[[{"v":8,"t_a":0.0,"t_b":-0.0},{"v":14,"t_a":90.0,"t_b":90.0},{"v":13,"t_a":110.0,"t_b":110.0}]],[[{"v":8,"t_a":0.0,"t_b":-0.0},{"v":14,"t_a":90.0,"t_b":90.0},{"v":13,"t_a":110.0,"t_b":110.0}]],[[{"v":8,"t_a":0.0,"t_b":-0.0},{"v":14,"t_a":90.0,"t_b":90.0},{"v":13,"t_a":110.0,"t_b":110.0}]],[[{"v":8,"t_a":0.0,"t_b":-0.0},{"v":14,"t_a":90.0,"t_b":90.0},{"v":13,"t_a":110.0,"t_b":110.0}]],[[{"v":8,"t_a":0.0,"t_b":-0.0},{"v":14,"t_a":90.0,"t_b":90.0},{"v":13,"t_a":110.0,"t_b":110.0}]],[[{"v":8,"t_a":0.0,"t_b":-0.0},{"v":14,"t_a":90.0,"t_b":90.0},{"v":13,"t_a":110.0,"t_b":110.0}]],[[{"v":8,"t_a":0.0,"t_b":-0.0},{"v":14,"t_a":90.0,"t_b":90.0},{"v":13,"t_a":110.0,"t_b":110.0}]],[[{"v":8,"t_a":0.0,"t_b":-0.0},{"v":14,"t_a":90.0,"t_b":90.0},{"v":13,"t_a":110.0,"t_b":110.0}]],[[{"v":8,"t_a":0.0,"t_b":-0.0},{"v":14,"t_a":90.0,"t_b":90.0},{"v":13,"t_a":110.0,"t_b":110.0}]],[[{"v":8,"t_a":0.0,"t_b":-0.0},{"v":14,"t_a":90.0,"t_b":90.0},{"v":13,"t_a":110.0,"t_b":110.0}]],[[{"v":8,"t_a":0.0,"t_b":-0.0},{"v":14,"t_a":90.0,"t_b":90.0},{"v":13,"t_a":110.0,"t_b":110.0}]],[[{"v":8,"t_a":0.0,"t_b":-0.0},{"v":14,"t_a":90.0,"t_b":90.0},{"v":13,"t_a":110.0,"t_b":110.0}]],[[{"v":8,"t_a":0.0,"t_b":-0.0},{"v":14,"t_a":90.0,"t_b":90.0},{"v":13,"t_a":110.0,"t_b":110.0}]],[[{"v":8,"t_a":0.0,"t_b":-0.0},{"v":14,"t_a":90.0,"t_b":90.0},{"v":13,"t_a":110.0,"t_b":110.0}]],[[{"v":8,"t_a":0.0,"t_b":-0.0},{"v":14,"t_a":90.0,"t_b":90.0},{"v":13,"t_a":110.0,"t_b":110.0}]],[[{"v":8,"t_a":0.0,"t_b":-0.0},{"v":14,"t_a":90.0,"t_b":90.0},{"v":13,"t_a":110.0,"t_b":110.0}]],[[{"v":8,"t_a":0.0,"t_b":-0.0},{"v":14,"t_a":90.0,"t_b":90.0},{"v":13,"t_a":110.0,"t_b":110.0}]],[[{"v":8,"t_a":0.0,"t_b":-0.0},{"v":14,"t_a":90.0,"t_b":90.0},{"v":13,"t_a":110.0,"t_b":110.0}]],[[{"v":8,"t_a":0.0,"t_b":-0.0},{"v":14,"t_a":90.0,"t_b":90.0},{"v":13,"t_a":110.0,"t_b":110.0}]],[[{"v":8,"t_a":0.0,"t_b":-0.0},{"v":14,"t_a":90.0,"t_b":90.0},{"v":13,"t_a":110.0,"t_b":110.0}]],[[{"v":8,"t_a":0.0,"t_b":-0.0},{"v":14,"t_a":90.0,"t_b":90.0},{"v":13,"t_a":110.0,"t_b":110.0}]],[[{"v":8,"t_a":0.0,"t_b":-0.0},{"v":14,"t_a":90.0,"t_b":90.0},{"v":13,"t_a":110.0,"t_b":110.0}]],[[{"v":8,"t_a":0.0,"t_b":-0.0},{"v":14,"t_a":90.0,"t_b":90.0},{"v":13,"t_a":110.0,"t_b":110.0}]],[[{"v":8,"t_a":0.0,"t_b":-0.0},{"v":14,"t_a":90.0,"t_b":90.0},{"v":13,"t_a":110.0,"t_b":110.0}]],[[{"v":8,"t_a":0.0,"t_b":-0.0},{"v":14,"t_a":90.0,"t_b":90.0},{"v":13,"t_a":110.0,"t_b":110.0}]],[[{"v":8,"t_a":0.0,"t_b":-0.0},{"v":14,"t_a":90.0,"t_b":90.0},{"v":13,"t_a":110.0,"t_b":110.0}]],[[{"v":8,"t_a":0.0,"t_b":-0.0},{"v":14,"t_a":90.0,"t_b":90.0},{"v":13,"t_a":110.0,"t_b":110.0}]],[[{"v":8,"t_a":0.0,"t_b":-0.0},{"v":14,"t_a":90.0,"t_b":90.0},{"v":13,"t_a":110.0,"t_b":110.0}]],[[{"v":8,"t_a":0.0,"t_b":-0.0},{"v":14,"t_a":90.0,"t_b":90.0},{"v":13,"t_a":110.0,"t_b":110.0}]],[[{"v":8,"t_a":0.0,"t_b":-0.0},{"v":14,"t_a":90.0,"t_b":90.0},{"v":13,"t_a":110.0,"t_b":110.0}]],[[{"v":8,"t_a":0.0,"t_b":-0.0},{"v":14,"t_a":90.0,"t_b":90.0},{"v":13,"t_a":110.0,"t_b":110.0}]],[[{"v":8,"t_a":0.0,"t_b":-0.0},{"v":14,"t_a":90.0,"t_b":90.0},{"v":13,"t_a":110.0,"t_b":110.0}]],[[{"v":8,"t_a":0.0,"t_b":-0.0},{"v":14,"t_a":90.0,"t_b":90.0},{"v":13,"t_a":110.0,"t_b":110.0}]],[[{"v":8,"t_a":0.0,"t_b":-0.0},{"v":14,"t_a":90.0,"t_b":90.0},{"v":13,"t_a":110.0,"t_b":110.0}]],[[{"v":8,"t_a":0.0,"t_b":-0.0},{"v":14,"t_a":90.0,"t_b":90.0},{"v":13,"t_a":110.0,"t_b":110.0}]],[[{"v":8,"t_a":0.0,"t_b":-0.0},{"v":14,"t_a":90.0,"t_b":90.0},{"v":13,"t_a":110.0,"t_b":110.0}]],[[{"v":8,"t_a":0.0,"t_b":-0.0},{"v":14,"t_a":90.0,"t_b":90.0},{"v":13,"t_a":110.0,"t_b":110.0}]],[[{"v":8,"t_a":0.0,"t_b":-0.0},{"v":14,"t_a":90.0,"t_b":90.0},{"v":13,"t_a":110.0,"t_b":110.0}]],[[{"v":8,"t_a":0.0,"t_b":-0.0},{"v":14,"t_a":90.0,"t_b":90.0},{"v":13,"t_a":110.0,"t_b":110.0}]],[[{"v":8,"t_a":0.0,"t_b":-0.0},{"v":14,"t_a":90.0,"t_b":90.0},{"v":13,"t_a":110.0,"t_b":110.0}]],[[{"v":8,"t_a":0.0,"t_b":-0.0},{"v":14,"t_a":90.0,"t_b":90.0},{"v":13,"t_a":110.0,"t_b":110.0}]],[[{"v":8,"t_a":0.0,"t_b":-0.0},{"v":14,"t_a":90.0,"t_b":90.0},{"v":13,"t_a":110.0,"t_b":110.0}]],[[{"v":8,"t_a":0.0,"t_b":-0.0},{"v":14,"t_a":90.0,"t_b":90.0},{"v":13,"t_a":110.0,"t_b":110.0}]],[[{"v":8,"t_a":0.0,"t_b":-0.0},{"v":14,"t_a":90.0,"t_b":90.0},{"v":13,"t_a":110.0,"t_b":110.0}]],[[{"v":8,"t_a":0.0,"t_b":-0.0},{"v":14,"t_a":90.0,"t_b":90.0},{"v":13,"t_a":110.0,"t_b":110.0}]],[[{"v":8,"t_a":0.0,"t_b":-0.0},{"v":14,"t_a":90.0,"t_b":90.0},{"v":13,"t_a":110.0,"t_b":110.0}]],[[{"v":8,"t_a":0.0,"t_b":-0.0},{"v":14,"t_a":90.0,"t_b":90.0},{"v":13,"t_a":110.0,"t_b":110.0}]],[[{"v":8,"t_a":0.0,"t_b":-0.0},{"v":14,"t_a":90.0,"t_b":90.0},{"v":13,"t_a":110.0,"t_b":110.0}]],[[{"v":8,"t_a":0.0,"t_b":-0.0},{"v":14,"t_a":90.0,"t_b":90.0},{"v":13,"t_a":110.0,"t_b":110.0}]],[[{"v":8,"t_a":0.0,"t_b":-0.0},{"v":14,"t_a":90.0,"t_b":90.0},{"v":13,"t_a":110.0,"t_b":110.0}]],[[{"v":8,"t_a":0.0,"t_b":-0.0},{"v":14,"t_a":90.0,"t_b":90.0},{"v":13,"t_a":110.0,"t_b":110.0}]],[[{"v":8,"t_a":0.0,"t_b":-0.0},{"v":14,"t_a":90.0,"t_b":90.0},{"v":13,"t_a":110.0,"t_b":110.0}]],[[{"v":8,"t_a":0.0,"t_b":-0.0},{"v":14,"t_a":90.0,"t_b":90.0},{"v":13,"t_a":110.0,"t_b":110.0}]],[[{"v":8,"t_a":0.0,"t_b":-0.0},{"v":14,"t_a":90.0,"t_b":90.0},{"v":13,"t_a":110.0,"t_b":110.0}]],[[{"v":8,"t_a":0.0,"t_b":-0.0},{"v":14,"t_a":90.0,"t_b":90.0},{"v":13,"t_a":110.0,"t_b":110.0}]],[[{"v":8,"t_a":0.0,"t_b":-0.0},{"v":14,"t_a":90.0,"t_b":90.0},{"v":13,"t_a":110.0,"t_b":110.0}]],[[{"v":8,"t_a":0.0,"t_b":-0.0},{"v":14,"t_a":90.0,"t_b":90.0},{"v":13,"t_a":110.0,"t_b":110.0}]],[[{"v":8,"t_a":0.0,"t_b":-0.0},{"v":14,"t_a":90.0,"t_b":90.0},{"v":13,"t_a":110.0,"t_b":110.0}]],[[{"v":8,"t_a":0.0,"t_b":-0.0},{"v":14,"t_a":90.0,"t_b":90.0},{"v":13,"t_a":110.0,"t_b":110.0}]],[[{"v":8,"t_a":0.0,"t_b":-0.0},{"v":14,"t_a":90.0,"t_b":90.0},{"v":13,"t_a":110.0,"t_b":110.0}]],[[{"v":8,"t_a":0.0,"t_b":-0.0},{"v":14,"t_a":90.0,"t_b":90.0},{"v":13,"t_a":110.0,"t_b":110.0}]],[[{"v":8,"t_a":0.0,"t_b":-0.0},{"v":14,"t_a":90.0,"t_b":90.0},{"v":13,"t_a":110.0,"t_b":110.0}]],[[{"v":8,"t_a":0.0,"t_b":-0.0},{"v":14,"t_a":90.0,"t_b":90.0},{"v":13,"t_a":110.0,"t_b":110.0}]],[[{"v":8,"t_a":0.0,"t_b":-0.0},{"v":14,"t_a":90.0,"t_b":90.0},{"v":13,"t_a":110.0,"t_b":110.0}]],[[{"v":8,"t_a":0.0,"t_b":-0.0},{"v":14,"t_a":90.0,"t_b":90.0},{"v":13,"t_a":110.0,"t_b":110.0}]],[[{"v":8,"t_a":0.0,"t_b":-0.0},{"v":14,"t_a":90.0,"t_b":90.0},{"v":13,"t_a":110.0,"t_b":110.0}]],[[{"v":8,"t_a":0.0,"t_b":-0.0},{"v":14,"t_a":90.0,"t_b":90.0},{"v":13,"t_a":110.0,"t_b":110.0}]],[[{"v":8,"t_a":0.0,"t_b":-0.0},{"v":14,"t_a":90.0,"t_b":90.0},{"v":13,"t_a":110.0,"t_b":110.0}]],[[{"v":8,"t_a":0.0,"t_b":-0.0},{"v":14,"t_a":90.0,"t_b":90.0},{"v":13,"t_a":110.0,"t_b":110.0}]],[[{"v":8,"t_a":0.0,"t_b":-0.0},{"v":14,"t_a":90.0,"t_b":90.0},{"v":13,"t_a":110.0,"t_b":110.0}]],[[{"v":8,"t_a":0.0,"t_b":-0.0},{"v":14,"t_a":90.0,"t_b":90.0},{"v":13,"t_a":110.0,"t_b":110.0}]],[[{"v":8,"t_a":0.0,"t_b":-0.0},{"v":14,"t_a":90.0,"t_b":90.0},{"v":13,"t_a":110.0,"t_b":110.0}]],[[{"v":8,"t_a":0.0,"t_b":-0.0},{"v":14,"t_a":90.0,"t_b":90.0},{"v":13,"t_a":110.0,"t_b":110.0}]],[[{"v":8,"t_a":0.0,"t_b":-0.0},{"v":14,"t_a":90.0,"t_b":90.0},{"v":13,"t_a":110.0,"t_b":110.0}]],[[{"v":8,"t_a":0.0,"t_b":-0.0},{"v":14,"t_a":90.0,"t_b":90.0},{"v":13,"t_a":110.0,"t_b":110.0}]],[[{"v":8,"t_a":0.0,"t_b":-0.0},{"v":14,"t_a":90.0,"t_b":90.0},{"v":13,"t_a":110.0,"t_b":110.0}]],[[{"v":8,"t_a":0.0,"t_b":-0.0},{"v":14,"t_a":90.0,"t_b":90.0},{"v":13,"t_a":110.0,"t_b":110.0}]],[[{"v":8,"t_a":0.0,"t_b":-0.0},{"v":14,"t_a":90.0,"t_b":90.0},{"v":13,"t_a":110.0,"t_b":110.0}]],[[{"v":8,"t_a":0.0,"t_b":-0.0},{"v":14,"t_a":90.0,"t_b":90.0},{"v":13,"t_a":110.0,"t_b":110.0}]],[[{"v":8,"t_a":0.0,"t_b":-0.0},{"v":14,"t_a":90.0,"t_b":90.0},{"v":13,"t_a":110.0,"t_b":110.0}]],[[{"v":8,"t_a":0.0,"t_b":-0.0},{"v":14,"t_a":90.0,"t_b":90.0},{"v":13,"t_a":110.0,"t_b":110.0}]],[[{"v":8,"t_a":0.0,"t_b":-0.0},{"v":14,"t_a":90.0,"t_b":90.0},{"v":13,"t_a":110.0,"t_b":110.0}]],[[{"v":8,"t_a":0.0,"t_b":-0.0},{"v":14,"t_a":90.0,"t_b":90.0},{"v":13,"t_a":110.0,"t_b":110.0}]],[[{"v":8,"t_a":0.0,"t_b":-0.0},{"v":14,"t_a":90.0,"t_b":90.0},{"v":13,"t_a":110.0,"t_b":110.0}]],[[{"v":8,"t_a":0.0,"t_b":-0.0},{"v":14,"t_a":90.0,"t_b":90.0},{"v":13,"t_a":110.0,"t_b":110.0}]],[[{"v":8,"t_a":0.0,"t_b":-0.0},{"v":14,"t_a":90.0,"t_b":90.0},{"v":13,"t_a":110.0,"t_b":110.0}]],[[{"v":8,"t_a":0.0,"t_b":-0.0},{"v":14,"t_a":90.0,"t_b":90.0},{"v":13,"t_a":110.0,"t_b":110.0}]],[[{"v":8,"t_a":0.0,"t_b":-0.0},{"v":14,"t_a":90.0,"t_b":90.0},{"v":13,"t_a":110.0,"t_b":110.0}]],[[{"v":8,"t_a":0.0,"t_b":-0.0},{"v":14,"t_a":90.0,"t_b":90.0},{"v":13,"t_a":110.0,"t_b":110.0}]],[[{"v":8,"t_a":0.0,"t_b":-0.0},{"v":14,"t_a":90.0,"t_b":90.0},{"v":13,"t_a":110.0,"t_b":110.0}]],[[{"v":8,"t_a":0.0,"t_b":-0.0},{"v":14,"t_a":90.0,"t_b":90.0},{"v":13,"t_a":110.0,"t_b":110.0}]],[[{"v":8,"t_a":0.0,"t_b":-0.0},{"v":14,"t_a":90.0,"t_b":90.0},{"v":13,"t_a":110.0,"t_b":110.0}]],[[{"v":8,"t_a":0.0,"t_b":-0.0},{"v":14,"t_a":90.0,"t_b":90.0},{"v":13,"t_a":110.0,"t_b":110.0}]],[[{"v":8,"t_a":0.0,"t_b":-0.0},{"v":14,"t_a":90.0,"t_b":90.0},{"v":13,"t_a":110.0,"t_b":110.0}]],[[{"v":8,"t_a":0.0,"t_b":-0.0},{"v":14,"t_a":90.0,"t_b":90.0},{"v":13,"t_a":110.0,"t_b":110.0}]],[[{"v":8,"t_a":0.0,"t_b":-0.0},{"v":14,"t_a":90.0,"t_b":90.0},{"v":13,"t_a":110.0,"t_b":110.0}]],[[{"v":8,"t_a":0.0,"t_b":-0.0},{"v":14,"t_a":90.0,"t_b":90.0},{"v":13,"t_a":110.0,"t_b":110.0}]],[[{"v":8,"t_a":0.0,"t_b":-0.0},{"v":14,"t_a":90.0,"t_b":90.0},{"v":13,"t_a":110.0,"t_b":110.0}]],[[{"v":8,"t_a":0.0,"t_b":-0.0},{"v":14,"t_a":90.0,"t_b":90.0},{"v":13,"t_a":110.0,"t_b":110.0}]],[[{"v":8,"t_a":0.0,"t_b":-0.0},{"v":14,"t_a":90.0,"t_b":90.0},{"v":13,"t_a":110.0,"t_b":110.0}]],[[{"v":8,"t_a":0.0,"t_b":-0.0},{"v":14,"t_a":90.0,"t_b":90.0},{"v":13,"t_a":110.0,"t_b":110.0}]],[[{"v":8,"t_a":0.0,"t_b":-0.0},{"v":14,"t_a":90.0,"t_b":90.0},{"v":13,"t_a":110.0,"t_b":110.0}]],[[{"v":8,"t_a":0.0,"t_b":-0.0},{"v":14,"t_a":90.0,"t_b":90.0},{"v":13,"t_a":110.0,"t_b":110.0}]],[[{"v":8,"t_a":0.0,"t_b":-0.0},{"v":14,"t_a":90.0,"t_b":90.0},{"v":13,"t_a":110.0,"t_b":110.0}]],[[{"v":8,"t_a":0.0,"t_b":-0.0},{"v":14,"t_a":90.0,"t_b":90.0},{"v":13,"t_a":110.0,"t_b":110.0}]],[[{"v":8,"t_a":0.0,"t_b":-0.0},{"v":14,"t_a":90.0,"t_b":90.0},{"v":13,"t_a":110.0,"t_b":110.0}]],[[{"v":8,"t_a":0.0,"t_b":-0.0},{"v":14,"t_a":90.0,"t_b":90.0},{"v":13,"t_a":110.0,"t_b":110.0}]],[[{"v":8,"t_a":0.0,"t_b":-0.0},{"v":14,"t_a":90.0,"t_b":90.0},{"v":13,"t_a":110.0,"t_b":110.0}]],[[{"v":8,"t_a":0.0,"t_b":-0.0},{"v":14,"t_a":90.0,"t_b":90.0},{"v":13,"t_a":110.0,"t_b":110.0}]]],"def_probs":[0.0,1.0,0.0,0.0,0.0,0.0,0.0,0.0,0.0,0.0,0.0,0.0,0.0,0.0,0.0,0.0,0.0,0.0,0.0,0.0,0.0,0.0,0.0,0.0,0.0,0.0,0.0,0.0,0.0,0.0,0.0,0.0,0.0,0.0,0.0,0.0,0.0,0.0,0.0,0.0,0.0,0.0,0.0,0.0,0.0,0.0,0.0,0.0,0.0,0.0,0.0,0.0,0.0,0.0,0.0,0.0,0.0,0.0,0.0,0.0,0.0,0.0,0.0,0.0,0.0,0.0,0.0,0.0,0.0,0.0,0.0,0.0,0.0,0.0,0.0,0.0,0.0,0.0,0.0,0.0,0.0,0.0,0.0,0.0,0.0,0.0,0.0,0.0,0.0,0.0,0.0,0.0,0.0,0.0,0.0,0.0,0.0,0.0,0.0,0.0,0.0,0.0,0.0,0.0,0.0,0.0,0.0,0.0,0.0,0.0,0.0,0.0,0.0,0.0,0.0,0.0,0.0,0.0,0.0,0.0,0.0,0.0,0.0,0.0,0.0,0.0,0.0,0.0,0.0,0.0,0.0,0.0,0.0,0.0,0.0,0.0,0.0,0.0,0.0,0.0,0.0,0.0,0.0,0.0,0.0,0.0,0.0,0.0,0.0,0.0,0.0,0.0,0.0,0.0,0.0,0.0,0.0,0.0,0.0,0.0,0.0,0.0,0.0,0.0,0.0,0.0,0.0,0.0,0.0,0.0,0.0,0.0,0.0,0.0,0.0,0.0,0.0,0.0,0.0,0.0,0.0,0.0,0.0,0.0,0.0,0.0,0.0,0.0,0.0,0.0,0.0,0.0,0.0,0.0,0.0,0.0,0.0,0.0,0.0,0.0,0.0,0.0,0.0,0.0,0.0,0.0,0.0,0.0,0.0,0.0,0.0,0.0,0.0,0.0,0.0,0.0,0.0,0.0,0.0,0.0,0.0,0.0,0.0,0.0,0.0,0.0,0.0,0.0,0.0,0.0,0.0,0.0,0.0,0.0,0.0,0.0,0.0,0.0,0.0,0.0,0.0,0.0,0.0,0.0,0.0,0.0,0.0,0.0,0.0,0.0,0.0,0.0,0.0,0.0,0.0,0.0,0.0,0.0,0.0,0.0,0.0,0.0,0.0,0.0,0.0,0.0,0.0,0.0,0.0,0.0,0.0,0.0,0.0,0.0,0.0,0.0,0.0,0.0,0.0,0.0,0.0,0.0,0.0,0.0,0.0,0.0,0.0,0.0,0.0,0.0,0.0,0.0,0.0,0.0,0.0,0.0,0.0,0.0,0.0,0.0,0.0,0.0,0.0,0.0,0.0,0.0,0.0,0.0,0.0,0.0,0.0,0.0,0.0,0.0,0.0,0.0,0.0,0.0,0.0],"obj_core_over_time":[1.0,-0.0,-0.0,-0.0,-0.0,-0.0,-0.0,-0.0,-0.0,-0.0,-0.0,-0.0,-0.0,-0.0,-0.0,-0.0,-0.0,-0.0,-0.0,-0.0,-0.0,-0.0,-0.0,-0.0,-0.0,-0.0,-0.0,-0.0,-0.0,-0.0,-0.0,-0.0,-0.0,-0.0,-0.0,-0.0,-0.0,-0.0,-0.0,-0.0,-0.0,-0.0,-0.0,-0.0,-0.0,-0.0,-0.0,-0.0,-0.0,-0.0,-0.0,-0.0,-0.0,-0.0,-0.0,-0.0,-0.0,-0.0,-0.0,-0.0,-0.0,-0.0,-0.0,-0.0,-0.0,-0.0,-0.0,-0.0,-0.0,-0.0,-0.0,-0.0,-0.0,-0.0,-0.0,-0.0,-0.0,-0.0,-0.0,-0.0,-0.0,-0.0,-0.0,-0.0,-0.0,-0.0,-0.0,-0.0,-0.0,-0.0,-0.0,-0.0,-0.0,-0.0,-0.0,-0.0,-0.0,-0.0,-0.0,-0.0,-0.0,-0.0,-0.0,-0.0,-0.0,-0.0,-0.0,-0.0,-0.0,-0.0,-0.0,-0.0,-0.0,-0.0,-0.0,-0.0,-0.0,-0.0,-0.0,-0.0,-0.0,-0.0,-0.0,-0.0,-0.0,-0.0,-0.0,-0.0,-0.0,-0.0,-0.0,-0.0,-0.0,-0.0,-0.0,-0.0,-0.0,-0.0,-0.0,-0.0,-0.0,-0.0,-0.0,-0.0,-0.0,-0.0,-0.0,-0.0,-0.0,-0.0,-0.0,-0.0,-0.0,-0.0,-0.0,-0.0,-0.0,-0.0,-0.0,-0.0,-0.0,-0.0,-0.0,-0.0,-0.0,-0.0,-0.0,-0.0,-0.0,-0.0,-0.0,-0.0,-0.0,-0.0,-0.0,-0.0,-0.0,-0.0,-0.0,-0.0,-0.0,-0.0,-0.0,-0.0,-0.0,-0.0,-0.0,-0.0,-0.0,-0.0,-0.0,-0.0,-0.0,-0.0,-0.0,-0.0,-0.0,-0.0,-0.0,-0.0,-0.0,-0.0,-0.0,-0.0,-0.0,-0.0,-0.0,-0.0,-0.0,-0.0,-0.0,-0.0,-0.0,-0.0,-0.0,-0.0,-0.0,-0.0,-0.0,-0.0,-0.0,-0.0,-0.0,-0.0,-0.0,-0.0,-0.0,-0.0,-0.0,-0.0,-0.0,-0.0,-0.0,-0.0,-0.0,-0.0,-0.0,-0.0,-0.0,-0.0,-0.0,-0.0,-0.0,-0.0,-0.0,-0.0,-0.0,-0.0,-0.0,-0.0,-0.0,-0.0,-0.0,-0.0,-0.0,-0.0,-0.0,-0.0,-0.0,-0.0,-0.0,-0.0,-0.0,-0.0,-0.0,-0.0,-0.0,-0.0,-0.0,-0.0,-0.0,-0.0,-0.0,-0.0,-0.0,-0.0,-0.0,-0.0,-0.0,-0.0,-0.0,-0.0,-0.0,-0.0,-0.0,-0.0,-0.0,-0.0,-0.0,-0.0,-0.0,-0.0,-0.0,-0.0,-0.0,-0.0,-0.0,-0.0,-0.0,-0.0,-0.0,-0.0,-0.0,-0.0,-0.0,-0.0,-0.0,-0.0,-0.0,-0.0,-0.0,-0.0,-0.0,-0.0,-0.0,-0.0,-0.0,-0.0,-0.0,-0.0],"obj_DO_over_time":[null,1.0,1.0,1.0,1.0,1.0,1.0,1.0,1.0,1.0,1.0,1.0,1.0,1.0,1.0,1.0,1.0,1.0,1.0,1.0,1.0,1.0,1.0,1.0,1.0,1.0,1.0,1.0,1.0,1.0,1.0,1.0,1.0,1.0,1.0,1.0,1.0,1.0,1.0,1.0,1.0,1.0,1.0,1.0,1.0,1.0,1.0,1.0,1.0,1.0,1.0,1.0,1.0,1.0,1.0,1.0,1.0,1.0,1.0,1.0,1.0,1.0,1.0,1.0,1.0,1.0,1.0,1.0,1.0,1.0,1.0,1.0,1.0,1.0,1.0,1.0,1.0,1.0,1.0,1.0,1.0,1.0,1.0,1.0,1.0,1.0,1.0,1.0,1.0,1.0,1.0,1.0,1.0,1.0,1.0,1.0,1.0,1.0,1.0,1.0,1.0,1.0,1.0,1.0,1.0,1.0,1.0,1.0,1.0,1.0,1.0,1.0,1.0,1.0,1.0,1.0,1.0,1.0,1.0,1.0,1.0,1.0,1.0,1.0,1.0,1.0,1.0,1.0,1.0,1.0,1.0,1.0,1.0,1.0,1.0,1.0,1.0,1.0,1.0,1.0,1.0,1.0,1.0,1.0,1.0,1.0,1.0,1.0,1.0,1.0,1.0,1.0,1.0,1.0,1.0,1.0,1.0,1.0,1.0,1.0,1.0,1.0,1.0,1.0,1.0,1.0,1.0,1.0,1.0,1.0,1.0,1.0,1.0,1.0,1.0,1.0,1.0,1.0,1.0,1.0,1.0,1.0,1.0,1.0,1.0,1.0,1.0,1.0,1.0,1.0,1.0,1.0,1.0,1.0,1.0,1.0,1.0,1.0,1.0,1.0,1.0,1.0,1.0,1.0,1.0,1.0,1.0,1.0,1.0,1.0,1.0,1.0,1.0,1.0,1.0,1.0,1.0,1.0,1.0,1.0,1.0,1.0,1.0,1.0,1.0,1.0,1.0,1.0,1.0,1.0,1.0,1.0,1.0,1.0,1.0,1.0,1.0,1.0,1.0,1.0,1.0,1.0,1.0,1.0,1.0,1.0,1.0,1.0,1.0,1.0,1.0,1.0,1.0,1.0,1.0,1.0,1.0,1.0,1.0,1.0,1.0,1.0,1.0,1.0,1.0,1.0,1.0,1.0,1.0,1.0,1.0,1.0,1.0,1.0,1.0,1.0,1.0,1.0,1.0,1.0,1.0,1.0,1.0,1.0,1.0,1.0,1.0,1.0,1.0,1.0,1.0,1.0,1.0,1.0,1.0,1.0,1.0,1.0,1.0,1.0,1.0,1.0,1.0,1.0,1.0,1.0,1.0,1.0,1.0,1.0,1.0,1.0,1.0,1.0,1.0,1.0,1.0,1.0,1.0,null],"obj_AO_over_time":[0.0,null,null,null,null,null,null,null,null,null,null,null,null,null,null,null,null,null,null,null,null,null,null,null,null,null,null,null,null,null,null,null,null,null,null,null,null,null,null,null,null,null,null,null,null,null,null,null,null,null,null,null,null,null,null,null,null,null,null,null,null,null,null,null,null,null,null,null,null,null,null,null,null,null,null,null,null,null,null,null,null,null,null,null,null,null,null,null,null,null,null,null,null,null,null,null,null,null,null,null,null,null,null,null,null,null,null,null,null,null,null,null,null,null,null,null,null,null,null,null,null,null,null,null,null,null,null,null,null,null,null,null,null,null,null,null,null,null,null,null,null,null,null,null,null,null,null,null,null,null,null,null,null,null,null,null,null,null,null,null,null,null,null,null,null,null,null,null,null,null,null,null,null,null,null,null,null,null,null,null,null,null,null,null,null,null,null,null,null,null,null,null,null,null,null,null,null,null,null,null,null,null,null,null,null,null,null,null,null,null,null,null,null,null,null,null,null,null,null,null,null,null,null,null,null,null,null,null,null,null,null,null,null,null,null,null,null,null,null,null,null,null,null,null,null,null,null,null,null,null,null,null,null,null,null,null,null,null,null,null,null,null,null,null,null,null,null,null,null,null,null,null,null,null,null,null,null,null,null,null,null,null,null,null,null,null,null,null,null,null,null,null,null,null,null,null,null,null,null,null,null,null,null,null,null,null,null,null,null,null,null,null,null,null,null,null,null,null,null,null],"coreLP_time_over_time":[0.006082184,0.005025245,0.005297316,0.005367458,0.006877039,0.005319059,0.005212457,0.006237815,0.006490952,0.0051344,0.005377498,0.006870547,0.005461997,0.005339887,0.007925091,0.005300763,0.005696619,0.005638008,0.006301556,0.005148908,0.005626456,0.008922598,0.005310792,0.00545832,0.006239921,0.011051703,0.005302117,0.005433273,0.006466797,0.00705255,0.006268333,0.005450225,0.005451908,0.006284985,0.005261389,0.005416241,0.006301567,0.009681936,0.005410089,0.005496893,0.005234209,0.009128445,0.005438112,0.006503375,0.005549622,0.007116849,0.0053147,0.005452419,0.006869606,0.007084089,0.006025346,0.005547979,0.006369454,0.00541553,0.005631245,0.005394981,0.006415281,0.006606269,0.005863753,0.005872519,0.007211258,0.005512131,0.006399742,0.005803799,0.005254296,0.004956626,0.004711264,0.004585738,0.00474042,0.00483179,0.005478347,0.005132417,0.004686628,0.004727244,0.005000218,0.004859452,0.004875243,0.004676859,0.005731994,0.004560821,0.004839677,0.004751911,0.005021458,0.004933343,0.01085776,0.004832963,0.004663665,0.004944293,0.005004697,0.005007282,0.004614102,0.004722145,0.004382095,0.004580218,0.004616466,0.005106669,0.004946587,0.005026328,0.004735029,0.005445726,0.004966895,0.004768373,0.005034623,0.004612098,0.004719229,0.004967637,0.004790264,0.004840798,0.004744898,0.004705433,0.004744927,0.004728308,0.004803548,0.004822573,0.005377087,0.00462417,0.004961846,0.004762099,0.004429395,0.004992113,0.004742693,0.006931421,0.005454273,0.005175148,0.005251752,0.005002522,0.004682611,0.004920308,0.004995769,0.004978457,0.004554098,0.00467735,0.004837212,0.004733696,0.004801343,0.004781957,0.005022199,0.005078466,0.004722246,0.004696888,0.005041466,0.004837722,0.004508292,0.004736802,0.004866455,0.00470933,0.004705093,0.004760116,0.005072003,0.004810621,0.004965554,0.004886755,0.00491626,0.004510797,0.004771748,0.004851728,0.009260845,0.005140902,0.005467197,0.005158086,0.005274905,0.005223299,0.005228267,0.004879722,0.004703139,0.005389591,0.005410179,0.006779315,0.005164718,0.005502924,0.005403496,0.005467938,0.00527794,0.005582384,0.005565161,0.007405263,0.005563467,0.005641945,0.005209652,0.005539632,0.005178754,0.005419737,0.006262904,0.005171751,0.005253775,0.005434976,0.005185877,0.005417944,0.005538681,0.005380002,0.005396725,0.005183092,0.005361188,0.00519823,0.005317846,0.005054931,0.005197379,0.00553836,0.006243037,0.005536938,0.005387517,0.005737956,0.005341069,0.005501922,0.005789954,0.005329968,0.005509877,0.005407043,0.005179476,0.005413746,0.005305793,0.005501562,0.005350638,0.005587032,0.00532542,0.005254596,0.005606769,0.005880293,0.005429566,0.005673705,0.006032781,0.0055168,0.005470032,0.005578206,0.005818357,0.005573696,0.005509135,0.005580681,0.005598423,0.008732792,0.005462087,0.005508183,0.005501632,0.005641565,0.005445625,0.005565261,0.006004598,0.011077302,0.005476754,0.005650461,0.005565342,0.009434201,0.005743697,0.00528811,0.005578035,0.008475457,0.006336493,0.005725743,0.005861769,0.006579829,0.005586422,0.005163264,0.005523793,0.008387852,0.005592062,0.005523102,0.005890052,0.005621548,0.006445759,0.005685547,0.011345346,0.005795886,0.005952399,0.005747694,0.009842028,0.006341131,0.006240722,0.006223289,0.007792773,0.006306506,0.005512913,0.005534854,0.009179952,0.00569785,0.005764236,0.005531397,0.007486426,0.005712659,0.005962228,0.005786787,0.009238543,0.005842672,0.005750759,0.006944958,0.009344401,0.005172051,0.006573287,0.005709653,0.009343319,0.00565993,0.005832894,0.005653938,0.006862221,0.05386669,0.005970724,0.005789763,0.006488469,0.006287981,0.005776257,0.006320643,0.006626739,0.005784194,0.005842203,0.00579303,0.007029557,0.005811073,0.006399772,0.006472938,0.005604875,0.005443051,0.00585231,0.005849176,0.005978689,0.006179176,0.005889421,0.005820392,0.005852602,0.0064256,0.005856379,0.005777841],"DO_time_over_time":[null,0.907720836,0.918150591,1.111993096,0.91023687,0.920153118,1.117652915,0.920262553,0.931012951,1.692615274,0.931843443,0.937336488,1.565472334,0.977862779,0.966041487,0.945942451,1.017680567,1.016664956,0.959443974,0.960708243,1.006414149,0.979297508,0.962967795,0.945770017,0.949883616,0.97419042,0.899563638,0.949961954,0.940849509,0.936999995,0.92369328,0.933353474,0.947869036,0.944455313,0.929435744,0.93716685,0.939432662,0.935924932,0.932550664,0.932600888,0.951508312,0.943806141,0.925704844,0.930183419,0.967806627,0.936738893,0.926835611,0.949208836,0.945053638,0.928432185,0.935461201,0.959353784,0.962748802,0.929192606,0.93065167,0.960381659,0.953063428,0.938532729,0.96106853,0.949252879,0.910171828,0.946488898,0.924767679,0.935423859,0.940193154,0.912986904,0.90484786,0.909047993,0.912116056,0.913879584,0.909755855,0.909399094,0.914980817,0.907973032,0.915119016,0.925488335,0.882955861,0.929960381,0.905644158,0.902711862,0.907173866,0.900344557,0.916213025,0.90756335,0.914463372,0.911631845,0.911696376,0.914661396,0.914978251,0.91041748,0.925413625,0.916607205,0.885944283,0.930275623,0.903048395,0.911691057,0.901944829,0.907963583,0.909992911,0.915287704,0.915003738,0.918824607,0.914043903,0.914150414,0.915802441,0.88449178,0.921338408,0.901891007,0.90557584,0.911725691,0.908826747,0.909690812,0.913081412,0.902463285,0.919917614,0.906940899,0.928123896,0.913533172,0.887016321,0.922711782,0.908253107,0.923553186,0.913397758,0.920879374,0.919451868,0.923169183,0.910554408,0.91614703,0.910589243,0.920950549,0.881567237,0.923597519,0.908853537,0.909174792,0.912234599,0.90603268,0.909020061,0.909310377,0.913892448,0.914888823,0.922675745,0.919699986,0.887374274,0.924150509,0.907624296,0.910487141,0.909730708,0.908587146,0.910859652,0.914066897,0.912572615,0.915928339,0.915328741,0.886449665,0.9301943,0.927852053,0.93173505,0.942308964,1.000236055,0.968555247,0.983261306,0.973461087,0.973980093,0.928519168,0.897680605,0.980718382,0.961124466,0.9140105,0.923734256,0.973938836,0.962007808,0.920118954,0.978222156,0.991298088,0.932300553,0.937909626,0.958990581,0.964913384,0.980326214,0.932350336,0.934125808,0.971429404,0.922410806,0.926004016,0.949405277,0.936186665,0.951153496,0.970836359,0.972194464,0.929010863,0.924569567,0.94449102,0.923881483,0.935812291,0.926248135,0.895309775,0.9411635,0.962398934,0.916814807,0.923756908,0.958618771,0.962182216,0.928162668,0.980985274,0.940269718,0.932156822,0.930242461,0.922831947,0.91938384,0.928634315,0.919403488,0.934619587,0.934957072,0.940481727,0.887889894,0.943534499,0.92367768,0.969825616,0.964551443,0.977144938,0.977798678,0.918114341,0.934606222,0.942334703,0.890999404,0.934635646,0.917367125,0.918570791,0.932738937,0.932242423,0.911583955,0.933854737,0.930872136,0.896183989,0.938229749,0.969462665,0.977644347,0.92633543,0.92404456,0.937409867,0.942023457,0.933339448,0.896395447,0.927002354,0.935912439,0.930845395,0.923804638,0.923569596,0.939174057,0.933147336,0.928066587,0.894698043,0.95122471,0.930420987,0.92378991,0.929897372,0.945657243,0.929731339,0.940251032,0.899737676,0.942819404,0.924571641,0.966881186,0.949841928,0.936341356,0.923063844,0.932585439,0.995362535,0.891845266,0.929484214,0.914454515,0.933060603,0.935006804,0.916628927,0.933656654,0.956941405,0.900968632,0.932045433,0.915214896,0.931599073,0.917678141,0.919345507,0.939175197,0.95364887,0.944196396,0.893533703,0.92643173,0.927282262,0.933443624,0.919587854,0.929542733,0.94815836,0.899706606,0.892730742,0.924149597,0.924297094,0.918838855,0.924296944,0.942768638,0.953567878,0.920619014,0.892268512,0.935930644,0.921924872,0.923012086,0.945152974,0.98208899,0.934677956,0.935988252,0.892043147,0.946183273,0.928223631,0.920268395,0.96910413,0.929039198,0.94061142,0.894804715,0.946461567,0.930368999,0.413888776],"AO_time_over_time":[0.106301357,null,null,null,null,null,null,null,null,null,null,null,null,null,null,null,null,null,null,null,null,null,null,null,null,null,null,null,null,null,null,null,null,null,null,null,null,null,null,null,null,null,null,null,null,null,null,null,null,null,null,null,null,null,null,null,null,null,null,null,null,null,null,null,null,null,null,null,null,null,null,null,null,null,null,null,null,null,null,null,null,null,null,null,null,null,null,null,null,null,null,null,null,null,null,null,null,null,null,null,null,null,null,null,null,null,null,null,null,null,null,null,null,null,null,null,null,null,null,null,null,null,null,null,null,null,null,null,null,null,null,null,null,null,null,null,null,null,null,null,null,null,null,null,null,null,null,null,null,null,null,null,null,null,null,null,null,null,null,null,null,null,null,null,null,null,null,null,null,null,null,null,null,null,null,null,null,null,null,null,null,null,null,null,null,null,null,null,null,null,null,null,null,null,null,null,null,null,null,null,null,null,null,null,null,null,null,null,null,null,null,null,null,null,null,null,null,null,null,null,null,null,null,null,null,null,null,null,null,null,null,null,null,null,null,null,null,null,null,null,null,null,null,null,null,null,null,null,null,null,null,null,null,null,null,null,null,null,null,null,null,null,null,null,null,null,null,null,null,null,null,null,null,null,null,null,null,null,null,null,null,null,null,null,null,null,null,null,null,null,null,null,null,null,null,null,null,null,null,null,null,null,null,null,null,null,null,null,null,null,null,null,null,null,null,null,null,null,null,null],"convergence_flag":false},"time_ne":162.731064432,"results_ne":{"att_strats":[[{"v":6,"t":0.0},{"v":3,"t":63.0},{"v":17,"t":280.75}],[{"v":6,"t":0.0},{"v":2,"t":44.5},{"v":1,"t":53.5},{"v":2,"t":74.5},{"v":1,"t":188.5},{"v":5,"t":213.5},{"v":9,"t":277.5},{"v":17,"t":279.5}]],"att_probs":[-0.0,1.0],"def_strats":[[[{"v":8,"t_a":0.0,"t_b":0.0},{"v":3,"t_a":25.0,"t_b":281.0}]]],"def_probs":[1.0],"obj_core_over_time":[1.0,-0.0],"obj_DO_over_time":[null,-0.0],"obj_AO_over_time":[0.0,null],"coreLP_time_over_time":[0.004923394,0.005930438],"DO_time_over_time":[null,1.108411498],"AO_time_over_time":[160.527068872,null],"convergence_flag":true}}